Workbook

Sheet PRESUPUESTO
A1: #VALUE! | C1: CODIGO | D1: PROYECTO | E1: FECHA DE MODIFICACIÓN: | F1: M2 | H1: Ancho | I1: Fondo | J1: Complejidad | M1: € Empresa | N1: Markup | O1: €+Margen | P1: Ben.Bruto | Q1: €/M2
E2: =NOW() | F2: =H2*I2 | M2: =M14+M46+M54+M59+M64+M69+M74+M78+M87+M111+M119+M122+M126+M132+M144+M169 | N2: 1 | O2: =O14+O46+O54+O59+O64+O69+O74+O78+O87+O111+O119+O122+O126+O132+O144+O169 | P2: =P14+P46+P54+P59+P64+P69+P74+P78+P87+P111+P119+P122+P126+P132+P144+P169 | Q2: =IFERROR(O2/F2,0)
A4: FAMILIA | B4: SUB F. | C4: MATERIAL | D4: TARIMA | E4: COMENTARIOS | F4: Largo | G4: Ancho | I4: m2 | J4: UDS | K4: €/m2 | L4: €/m2 Real | M4: €/Empresa | N4: Markup % | O4: € TOTAL | P4: BEN.EMP | Q4: COSTE TOT | R4: Diseño (50m2/4-6h) | S4: COSTE MAT | T4: Tarima Mala | U4: (35m2/h) Corte | V4: Merma 20% | W4: Tarima Buena | X4: Corte | Y4: Merma 20 % | Z4: Rastreles ® | AA4: (15m2/h) T. Corte | AB4: (1,6m2/h) T.Montaje | AC4: Zocalo | AD4: Corte | AE4: Perfil Alu. | AF4: Plastico | AG4: Tornilleria | AH4: (30m2/h) T. Paletizacion | AI4: Palets
A5: Tarima | B5: Suelo | C5: Aglomerado Reciclado | D5: Tarima con Moqueta | F5: 0 | G5: 0 | I5: =F5*G5 | J5: 0 | K5: 7.77 | L5: =IFERROR(ROUNDUP((Q5/I5)/0.5,0)*0.5,0) | M5: =IF(I5=0,J5*K5,I5*J5*K5) | N5: =$N$14 | O5: =SUM(M5*N5)+M5 | P5: =SUM(O5-M5) | Q5: =R5+S5 | R5: =J5*(MAX(1,ROUNDUP(I5/50,0)*4)*COSTE!$G$3) | S5: =SUM(T5:AU5) | T5: =(I5*COSTE!$G$20)/3 | U5: =(I5/35)*COSTE!$G$4 | V5: =T5*20% | Z5: =(((((2*F5)+1)*G5)*0.08)*COSTE!$G$21)/3 | AA5: =(((((2*F5)+1)*G5)*0.08)/15)*COSTE!$G$4 | AC5: =((((F5*2)+(G5*2))*0.1)*2.44)*COSTE!$G$23 | AD5: =((((F5*2)+(G5*2))*0.1)*2.44)*COSTE!$J$23 | AE5: =((F5*2)+(G5*2))*COSTE!$G$55 | AF5: =I5*COSTE!$G$66 | AG5: =I5*0.1 | AH5: =(I5/30)*COSTE!$G$5 | AI5: =ROUNDUP(I5/35,0)*((COSTE!$G$20/3)+(COSTE!$G$45*1)+(COSTE!$G$4/6)+(0.5))
A6: Tarima | B6: Suelo | C6: Melamina Reciclado | D6: Tarima Melamina Reciclada | F6: 0 | G6: 0 | I6: =F6*G6 | J6: 0 | K6: 22 | L6: =IFERROR(ROUNDUP((Q6/I6)/0.5,0)*0.5,0) | M6: =IF(I6=0,J6*K6,I6*J6*K6) | N6: =$N$14 | O6: =SUM(M6*N6)+M6 | P6: =SUM(O6-M6) | Q6: =R6+S6 | R6: =J6*(MAX(1,ROUNDUP(I6/50,0)*6)*COSTE!$G$3) | S6: =SUM(T6:AU6) | T6: =(I6*COSTE!$G$20)/3 | U6: =(I6/35)*COSTE!$G$4 | V6: =T6*20% | W6: =(I6*COSTE!$G$14) | X6: =I6*COSTE!$J$14 | Y6: =W6*20% | Z6: =((((((2*F6)+1)*G6)*0.08)*2)*COSTE!$G$21)/3 | AA6: =((((((2*F6)+1)*G6)*0.08)*2)/15)*COSTE!$G$4 | AB6: =(((((2*F7)+1)*G7)*0.08)/1.6)*COSTE!$G$4 | AC6: =((((F6*2)+(G6*2))*0.1)*2.44)*COSTE!$G$23 | AD6: =((((F6*2)+(G6*2))*0.1)*2.44)*COSTE!$J$23 | AE6: =((F6*2)+(G6*2))*COSTE!$G$55 | AF6: =I6*COSTE!$G$66 | AG6: =I6*0.1 | AH6: =((I6*2)/30)*COSTE!$G$5 | AI6: =ROUNDUP((I6*2)/35,0)*((COSTE!$G$20/3)+(COSTE!$G$45*1)+(COSTE!$G$4/6)+(0.5))
A7: Tarima | B7: Suelo | C7: Melamina | D7: Tarima Melamina Nueva | E7: *New | F7: 0 | G7: 0 | I7: =F7*G7 | J7: 0 | K7: 30 | L7: =IFERROR(ROUNDUP((Q7/I7)/0.5,0)*0.5,0) | M7: =IF(I7=0,J7*K7,I7*J7*K7) | N7: =$N$14 | O7: =SUM(M7*N7)+M7 | P7: =SUM(O7-M7) | Q7: =R7+S7 | R7: =J7*MAX(1,ROUNDUP(I7/50,0)*6)*COSTE!$G$3 | S7: =SUM(T7:AU7) | T7: =I7*COSTE!$G$20 | U7: =I7*COSTE!$J$20 | V7: =T7*20% | W7: =I7*COSTE!$G$14 | X7: =I7*COSTE!$J$14 | Y7: =W7*20% | Z7: =((((((2*F7)+1)*G7)*0.08)*2)*COSTE!$G$21)/3 | AA7: =((((((2*F7)+1)*G7)*0.08)*2)/15)*COSTE!$G$4 | AB7: =(((((2*F5)+1)*G5)*0.08)/1.6)*COSTE!$G$4 | AC7: =((((F7*2)+(G7*2))*0.1)*2.44)*COSTE!$G$23 | AD7: =((((F7*2)+(G7*2))*0.1)*2.44)*COSTE!$J$23 | AE7: =((F7*2)+(G7*2))*COSTE!$G$55 | AF7: =I7*COSTE!$G$66 | AG7: =I7*0.1
A8: Tarima | B8: Suelo | C8: Melamina Especial | D8: Tarima Melamina Especial | F8: 0 | G8: 0 | I8: =F8*G8 | J8: 0 | K8: 32.58 | L8: =IFERROR(ROUNDUP((Q8/I8)/0.5,0)*0.5,0) | M8: =IF(I8=0,J8*K8,I8*J8*K8) | N8: =$N$14 | O8: =SUM(M8*N8)+M8 | P8: =SUM(O8-M8) | Q8: =R8+S8 | R8: =J8*MAX(1,ROUNDUP(I8/50,0)*6)*COSTE!$G$3 | S8: =SUM(T8:AU8) | T8: =(I8*COSTE!$G$20)/3 | U8: =(I8/35)*COSTE!$G$4 | V8: =T8*20% | W8: =(I8*COSTE!$G$17) | X8: =I8*COSTE!$J$17 | Y8: =W8*20% | Z8: =((((((2*F8)+1)*G8)*0.08)*2)*COSTE!$G$21)/3 | AA8: =((((((2*F8)+1)*G8)*0.08)*2)/15)*COSTE!$G$4 | AB8: =(((((2*F6)+1)*G6)*0.08)/1.6)*COSTE!$G$4 | AC8: =((((F8*2)+(G8*2))*0.1)*2.44)*COSTE!$G$23 | AD8: =((((F8*2)+(G8*2))*0.1)*2.44)*COSTE!$J$23 | AE8: =((F8*2)+(G8*2))*COSTE!$G$55 | AF8: =I8*COSTE!$G$66 | AG8: =I8*0.1 | AH8: =((I8*2)/30)*COSTE!$G$5 | AI8: =ROUNDUP((I8*2)/35,0)*((COSTE!$G$20/3)+(COSTE!$G$45*1)+(COSTE!$G$4/6)+(0.5))
A9: FAMILIA | B9: SUB F. | C9: MATERIAL | D9: TARIMA - RAMPA | E9: COMENTARIOS | F9: Fondo | G9: Ancho | I9: m2 | J9: UDS | K9: €/m2 | L9: €/m2 Real | M9: €/Empresa | N9: Markup % | O9: € TOTAL | P9: BEN.EMP | Q9: COSTE TOT | R9: Diseño (1uni/1h) | S9: COSTE MAT | T9: Perfil Alu. | U9: (1m2/h) T. Fabricación
A10: Tarima | B10: Rampa | C10: Tarima | D10: Rampa (Estandar 1x1) | E10: *El coste rampa lo pondria siempre igual por m2 ya que el valor del material esta en la tarima | F10: 0 | G10: 0 | I10: =F10*G10 | J10: 0 | K10: 28 | L10: =IFERROR(ROUNDUP((Q10/I10)/0.5,0)*0.5,0) | M10: =IF(I10=0,J10*K10,I10*J10*K10) | N10: =$N$14 | O10: =SUM(M10*N10)+M10 | P10: =SUM(O10-M10) | Q10: =R10+S10 | R10: =J10*MAX(1,ROUNDUP(J10/1,0)*1)*COSTE!$G$3 | S10: =SUM(T10:AU10) | T10: =(F10*2)*COSTE!$G$55 | U10: =I10*COSTE!$G$5
A11: FAMILIA | B11: SUB F. | C11: MATERIAL | D11: TARIMA - REGATA LED | E11: COMENTARIOS | I11: ml | J11: UDS | K11: €/ml | L11: €/ml Real | M11: €/Empresa | N11: Markup % | O11: € TOTAL | P11: BEN.EMP | Q11: COSTE TOT | R11: Diseño (10ml/2h) | S11: COSTE MAT | T11: (4 ml/h) T. Fabricación | U11: (2 ml/h) T. Fabricación
A12: Tarima | B12: Proceso | C12: Regata | D12: Regata Led Recta | I12: 0 | J12: 0 | K12: 5 | L12: =IFERROR(ROUNDUP((Q12/I12)/0.5,0)*0.5,0) | M12: =IF(I12=0,J12*K12,I12*J12*K12) | N12: =$N$14 | O12: =SUM(M12*N12)+M12 | P12: =SUM(O12-M12) | Q12: =R12+S12 | R12: =J12*(MAX(1,ROUNDUP(I12/10,0)*2)*COSTE!$G$3) | S12: =SUM(T12:AU12) | T12: =(I12/4)*COSTE!$G$5
A13: Tarima | B13: Proceso | C13: Regata | D13: Regata Led Diagonal o Curva | I13: 0 | J13: 0 | K13: 10 | L13: =IFERROR(ROUNDUP((Q13/I13)/0.5,0)*0.5,0) | M13: =IF(I13=0,J13*K13,I13*J13*K13) | N13: =$N$14 | O13: =SUM(M13*N13)+M13 | P13: =SUM(O13-M13) | Q13: =R13+S13 | R13: =J13*(MAX(1,ROUNDUP(I13/10,0)*2)*COSTE!$G$3) | S13: =SUM(T13:AU13) | U13: =(I13/2)*COSTE!$G$5
K14: TOTAL TARIMA | M14: =SUM(M5:M13) | N14: =$N$2 | O14: =SUM(O5:O13) | P14: =SUM(P5:P13) | Q14: =SUM(Q5:Q13) | S14: =SUM(S5:S13)
A15: FAMILIA | B15: SUB F. | C15: MATERIAL | D15: MURO | E15: COMENTARIOS | F15: Largo | G15: Altura | H15: Grosor | I15: m2 | J15: UDS | K15: €/m2 | L15: €/m2+G Real | M15: €/Empresa | N15: Markup % | O15: € TOTAL | P15: BEN.EMP | Q15: COSTE TOT | R15: Diseño 20m2/5h) | S15: COSTE MAT | T15: Tableros | U15: Corte | V15: Cadel | W15: Merma 20% | X15: Rastreles (r) | Y15: (15m2/h) Corte | Z15: Columnas | AA15: (15m2/h) Corte | AB15: (7,5 m2/h) Montaje | AC15: Almas | AD15: Corte | AE15: Yapasas | AF15: (30m2/h) T. Paletizacion | AG15: Palets | AH15: Tornilleria
A16: Muro | B16: Paredes | C16: Aglomerado | D16: 1 Cara (Grosor Estandar 0,1m / Altura 2,75m) | E16: *El grosor se pone en el excel | F16: 0 | G16: 0 | H16: 0 | I16: =F16*G16 | J16: 0 | K16: 14 | L16: =IFERROR(ROUNDUP((Q16/I16)/0.5,0)*0.5,0) | M16: =IF(I16=0,J16*K16,I16*J16*K16) | N16: =$N$46 | O16: =SUM(M16*N16)+M16 | P16: =SUM(O16-M16) | Q16: =R16+S16 | R16: =J16*(MAX(1,ROUNDUP(I16/20,0)*5)*COSTE!$G$3) | S16: =SUM(T16:AU16) | T16: =((F16*G16) + ((H16*G16)*2))*COSTE!$G$20 | U16: =((F16*G16) + ((H16*G16)*2))*COSTE!$J$20 | W16: =T16*20% | X16: =(((F16*(H16-(0.016*2)))*2)*COSTE!$G$20)/3 | Y16: =(((F16*(H16-(0.016*2)))*2)/15)*COSTE!$G$4 | Z16: =((F16+1)*(((0.08*G16)*2)+((H16-(0.016*4))*G16)))*COSTE!$G$20 | AA16: =(((F16+1)*(((0.08*G16)*2)+((H16-(0.016*4))*G16)))/15)*COSTE!$G$4 | AB16: =(((F16+1)*(((0.08*G16)*2)+((H16-(0.016*4))*G16)))/7.5)*COSTE!$G$4 | AF16: =(I16/30)*COSTE!$G$5 | AG16: =ROUNDUP(I16/35,0)*((COSTE!$G$20/3)+(COSTE!$G$45*1)+(COSTE!$G$4/6)+(0.5)) | AH16: =I16*0.1
A17: Muro | B17: Paredes | C17: Aglomerado | D17: 2 Cara (Grosor Estandar 0,1m / Altura 2,75m) | E17: *El grosor se pone en el excel | F17: 0 | G17: 0 | H17: 0 | I17: =F17*G17 | J17: 0 | K17: 22 | L17: =IFERROR(ROUNDUP((Q17/I17)/0.5,0)*0.5,0) | M17: =IF(I17=0,J17*K17,I17*J17*K17) | N17: =$N$46 | O17: =SUM(M17*N17)+M17 | P17: =SUM(O17-M17) | Q17: =R17+S17 | R17: =J17*(MAX(1,ROUNDUP(I17/20,0)*5)*COSTE!$G$3) | S17: =SUM(T17:AU17) | T17: =(((F17*G17) + ((H17*G17)*2))*2)*COSTE!$G$20 | U17: =(((F17*G17) + ((H17*G17)*2))*2)*COSTE!$J$20 | W17: =T17*20% | X17: =(((F17*(H17-(0.016*2)))*2)*COSTE!$G$20)/3 | Y17: =(((F17*(H17-(0.016*2)))*2)/15)*COSTE!$G$4 | Z17: =((F17+1)*(((0.08*G17)*2)+((H17-(0.016*4))*G17)))*COSTE!$G$20 | AA17: =(((F17+1)*(((0.08*G17)*2)+((H17-(0.016*4))*G17)))/15)*COSTE!$G$4 | AB17: =(((F17+1)*(((0.08*G17)*2)+((H17-(0.016*4))*G17)))/7.5)*COSTE!$G$4 | AF17: =(I17/30)*COSTE!$G$5 | AG17: =ROUNDUP(I17/35,0)*((COSTE!$G$20/3)+(COSTE!$G$45*1)+(COSTE!$G$4/6)+(0.5)) | AH17: =I17*0.1
A18: Muro | B18: Paredes | C18: MDF | D18: 1 Cara (Grosor Estandar 0,1m / Altura 2,75m) | E18: *El grosor se pone en el excel | F18: 0 | G18: 0 | H18: 0 | I18: =F18*G18 | J18: 0 | K18: 21 | L18: =IFERROR(ROUNDUP((Q18/I18)/0.5,0)*0.5,0) | M18: =IF(I18=0,J18*K18,I18*J18*K18) | N18: =$N$46 | O18: =SUM(M18*N18)+M18 | P18: =SUM(O18-M18) | Q18: =R18+S18 | R18: =J18*(MAX(1,ROUNDUP(I18/20,0)*5)*COSTE!$G$3) | S18: =SUM(T18:AU18) | T18: =((F18*G18) + ((H18*G18)*2))*COSTE!$G$27 | U18: =((F18*G18) + ((H18*G18)*2))*COSTE!$J$27 | W18: =T18*20% | X18: =(((F18*(H18-(0.016*2)))*2)*COSTE!$G$20)/3 | Y18: =(((F18*(H18-(0.016*2)))*2)/15)*COSTE!$G$4 | Z18: =((F18+1)*(((0.08*G18)*2)+((H18-(0.016*4))*G18)))*COSTE!$G$20 | AA18: =(((F18+1)*(((0.08*G18)*2)+((H18-(0.016*4))*G18)))/15)*COSTE!$G$4 | AB18: =(((F18+1)*(((0.08*G18)*2)+((H18-(0.016*4))*G18)))/7.5)*COSTE!$G$4 | AF18: =(I18/30)*COSTE!$G$5 | AG18: =ROUNDUP(I18/35,0)*((COSTE!$G$20/3)+(COSTE!$G$45*1)+(COSTE!$G$4/6)+(0.5)) | AH18: =I18*0.1
A19: Muro | B19: Paredes | C19: MDF | D19: 2 Cara (Grosor Estandar 0,1m/ Altura 2,75m) | E19: *El grosor se pone en el excel | F19: 0 | G19: 0 | H19: 0 | I19: =F19*G19 | J19: 0 | K19: 34 | L19: =IFERROR(ROUNDUP((Q19/I19)/0.5,0)*0.5,0) | M19: =IF(I19=0,J19*K19,I19*J19*K19) | N19: =$N$46 | O19: =SUM(M19*N19)+M19 | P19: =SUM(O19-M19) | Q19: =R19+S19 | R19: =J19*(MAX(1,ROUNDUP(I19/20,0)*5)*COSTE!$G$3) | S19: =SUM(T19:AU19) | T19: =(((F19*G19) + ((H19*G19)*2))*2)*COSTE!$G$27 | U19: =(((F19*G19) + ((H19*G19)*2))*2)*COSTE!$J$27 | W19: =T19*20% | X19: =(((F19*(H19-(0.016*2)))*2)*COSTE!$G$20)/3 | Y19: =(((F19*(H19-(0.016*2)))*2)/15)*COSTE!$G$4 | Z19: =((F19+1)*(((0.08*G19)*2)+((H19-(0.016*4))*G19)))*COSTE!$G$20 | AA19: =(((F19+1)*(((0.08*G19)*2)+((H19-(0.016*4))*G19)))/15)*COSTE!$G$4 | AB19: =(((F19+1)*(((0.08*G19)*2)+((H19-(0.016*4))*G19)))/7.5)*COSTE!$G$4 | AF19: =(I19/30)*COSTE!$G$5 | AG19: =ROUNDUP(I19/35,0)*((COSTE!$G$20/3)+(COSTE!$G$45*1)+(COSTE!$G$4/6)+(0.5)) | AH19: =I19*0.1
A20: Muro | B20: Paredes | C20: Melamina | D20: 1 Cara (Grosor Estandar 0,1m / Altura 2,75m) | E20: *El grosor se pone en el excel | F20: 0 | G20: 0 | H20: 0 | I20: =F20*G20 | J20: 0 | K20: 15 | L20: =IFERROR(ROUNDUP((Q20/I20)/0.5,0)*0.5,0) | M20: =IF(I20=0,J20*K20,I20*J20*K20) | N20: =$N$46 | O20: =SUM(M20*N20)+M20 | P20: =SUM(O20-M20) | Q20: =R20+S20 | R20: =J20*(MAX(1,ROUNDUP(I20/20,0)*5)*COSTE!$G$3) | S20: =SUM(T20:AU20) | T20: =((F20*G20) + ((H20*G20)*2))*COSTE!$G$13 | U20: =((F20*G20) + ((H20*G20)*2))*COSTE!$J$13 | V20: =((F20*G20) + ((H20*G20)*2))*COSTE!$L$13 | W20: =T20*20% | X20: =(((F20*(H20-(0.016*2)))*2)*COSTE!$G$20)/3 | Y20: =(((F20*(H20-(0.016*2)))*2)/15)*COSTE!$G$4 | Z20: =((F20+1)*(((0.08*G20)*2)+((H20-(0.016*4))*G20)))*COSTE!$G$20 | AA20: =(((F20+1)*(((0.08*G20)*2)+((H20-(0.016*4))*G20)))/15)*COSTE!$G$4 | AB20: =(((F20+1)*(((0.08*G20)*2)+((H20-(0.016*4))*G20)))/7.5)*COSTE!$G$4 | AC20: =(((F20*G20)+F20)*0.027)*COSTE!$G$25 | AD20: =(((F20*G20)+F20)*0.027)*COSTE!J25 | AE20: =(F20*COSTE!$G$20)/3 | AF20: =(I20/30)*COSTE!$G$5 | AG20: =ROUNDUP(I20/35,0)*((COSTE!$G$20/3)+(COSTE!$G$45*1)+(COSTE!$G$4/6)+(0.5)) | AH20: =I20*0.1
A21: Muro | B21: Paredes | C21: Melamina | D21: 2 Cara (Grosor Estandar 0,1m / Altura 2,75m) | E21: *El grosor se pone en el excel | F21: 0 | G21: 0 | H21: 0 | I21: =F21*G21 | J21: 0 | K21: 25 | L21: =IFERROR(ROUNDUP((Q21/I21)/0.5,0)*0.5,0) | M21: =IF(I21=0,J21*K21,I21*J21*K21) | N21: =$N$46 | O21: =SUM(M21*N21)+M21 | P21: =SUM(O21-M21) | Q21: =R21+S21 | R21: =J21*(MAX(1,ROUNDUP(I21/20,0)*5)*COSTE!$G$3) | S21: =SUM(T21:AU21) | T21: =(((F21*G21) + ((H21*G21)*2))*2)*COSTE!$G$13 | U21: =(((F21*G21) + ((H21*G21)*2))*2)*COSTE!$J$13 | V21: =(((F21*G21) + ((H21*G21)*2))*2)*COSTE!$L$13 | W21: =T21*20% | X21: =(((F21*(H21-(0.016*2)))*2)*COSTE!$G$20)/3 | Y21: =(((F21*(H21-(0.016*2)))*2)/15)*COSTE!$G$4 | Z21: =((F21+1)*(((0.08*G21)*2)+((H21-(0.016*4))*G21)))*COSTE!$G$20 | AA21: =(((F21+1)*(((0.08*G21)*2)+((H21-(0.016*4))*G21)))/15)*COSTE!$G$4 | AB21: =(((F21+1)*(((0.08*G21)*2)+((H21-(0.016*4))*G21)))/7.5)*COSTE!$G$4 | AC21: =(((F21*G21)+F21)*0.027)*COSTE!$G$25 | AD21: =(((F21*G21)+F21)*0.027)*COSTE!J26 | AE21: =(F21*COSTE!$G$20)/3 | AF21: =(I21/30)*COSTE!$G$5 | AG21: =ROUNDUP(I21/35,0)*((COSTE!$G$20/3)+(COSTE!$G$45*1)+(COSTE!$G$4/6)+(0.5)) | AH21: =I21*0.1
A22: Muro | B22: Paredes | C22: Melamina Especial / Chopo | D22: 1 Cara (Grosor Estandar 0,1m/ Altura 2,75m) | E22: *El grosor se pone en el excel | F22: 0 | G22: 0 | H22: 0 | I22: =F22*G22 | J22: 0 | K22: 21 | L22: =IFERROR(ROUNDUP((Q22/I22)/0.5,0)*0.5,0) | M22: =IF(I22=0,J22*K22,I22*J22*K22) | N22: =$N$46 | O22: =SUM(M22*N22)+M22 | P22: =SUM(O22-M22) | Q22: =R22+S22 | R22: =J22*(MAX(1,ROUNDUP(I22/20,0)*5)*COSTE!$G$3) | S22: =SUM(T22:AU22) | T22: =((F22*G22) + ((H22*G22)*2))*COSTE!$G$17 | U22: =((F22*G22) + ((H22*G22)*2))*COSTE!$J$17 | V22: =((F22*G22) + ((H22*G22)*2))*COSTE!$L$17 | W22: =T22*20% | X22: =(((F22*(H22-(0.016*2)))*2)*COSTE!$G$20)/3 | Y22: =(((F22*(H22-(0.016*2)))*2)/15)*COSTE!$G$4 | Z22: =((F22+1)*(((0.08*G22)*2)+((H22-(0.016*4))*G22)))*COSTE!$G$20 | AA22: =(((F22+1)*(((0.08*G22)*2)+((H22-(0.016*4))*G22)))/15)*COSTE!$G$4 | AB22: =(((F22+1)*(((0.08*G22)*2)+((H22-(0.016*4))*G22)))/7.5)*COSTE!$G$4 | AC22: =(((F22*G22)+F22)*0.027)*COSTE!$G$25 | AD22: =(((F22*G22)+F22)*0.027)*COSTE!J27 | AE22: =(F22*COSTE!$G$20)/3 | AF22: =(I22/30)*COSTE!$G$5 | AG22: =ROUNDUP(I22/35,0)*((COSTE!$G$20/3)+(COSTE!$G$45*1)+(COSTE!$G$4/6)+(0.5)) | AH22: =I22*0.1
A23: Muro | B23: Paredes | C23: Melamina Especial / Chopo | D23: 2 Cara (Grosor Estandar 0,1m/ Altura 2,75m) | E23: *El grosor se pone en el excel | F23: 0 | G23: 0 | H23: 0 | I23: =F23*G23 | J23: 0 | K23: 36 | L23: =IFERROR(ROUNDUP((Q23/I23)/0.5,0)*0.5,0) | M23: =IF(I23=0,J23*K23,I23*J23*K23) | N23: =$N$46 | O23: =SUM(M23*N23)+M23 | P23: =SUM(O23-M23) | Q23: =R23+S23 | R23: =J23*(MAX(1,ROUNDUP(I23/20,0)*5)*COSTE!$G$3) | S23: =SUM(T23:AU23) | T23: =(((F23*G23) + ((H23*G23)*2))*2)*COSTE!$G$17 | U23: =(((F23*G23) + ((H23*G23)*2))*2)*COSTE!$J$17 | V23: =(((F23*G23) + ((H23*G23)*2))*2)*COSTE!$L$17 | W23: =T23*20% | X23: =(((F23*(H23-(0.016*2)))*2)*COSTE!$G$20)/3 | Y23: =(((F23*(H23-(0.016*2)))*2)/15)*COSTE!$G$4 | Z23: =((F23+1)*(((0.08*G23)*2)+((H23-(0.016*4))*G23)))*COSTE!$G$20 | AA23: =(((F23+1)*(((0.08*G23)*2)+((H23-(0.016*4))*G23)))/15)*COSTE!$G$4 | AB23: =(((F23+1)*(((0.08*G23)*2)+((H23-(0.016*4))*G23)))/7.5)*COSTE!$G$4 | AC23: =(((F23*G23)+F23)*0.027)*COSTE!$G$25 | AD23: =(((F23*G23)+F23)*0.027)*COSTE!J28 | AE23: =(F23*COSTE!$G$20)/3 | AF23: =(I23/30)*COSTE!$G$5 | AG23: =ROUNDUP(I23/35,0)*((COSTE!$G$20/3)+(COSTE!$G$45*1)+(COSTE!$G$4/6)+(0.5)) | AH23: =I23*0.1
A24: FAMILIA | B24: SUB F. | C24: MATERIAL | D24: MURO - BMATRIX | E24: COMENTARIOS | F24: Largo | G24: Altura | H24: Grosor | I24: m2 | J24: UDS | K24: €/m2 | L24: €/m2 Real | M24: €/Empresa | N24: Markup % | O24: € TOTAL | P24: BEN.EMP | Q24: COSTE TOT | R24: Diseño 20m2/6h) | S24: COSTE MAT | T24: Alquiler | U24: Logistica
A25: Muro | B25: Paredes | C25: Bmatrix | D25: Alquiler Muro Bmatrix | E25: *Modificar coste?? | F25: 0 | G25: 0 | H25: 0 | I25: =F25*G25 | J25: 0 | K25: 50 | L25: =IFERROR(ROUNDUP((Q25/I25)/0.5,0)*0.5,0) | M25: =IF(I25=0,J25*K25,I25*J25*K25) | N25: =$N$46 | O25: =SUM(M25*N25)+M25 | P25: =SUM(O25-M25) | Q25: =R25+S25 | R25: =J25*(MAX(1,ROUNDUP(I25/20,0)*6)*COSTE!$G$3) | S25: =SUM(T25:AU25) | T25: =(F25*G25)*COSTE!G64 | U25: =IF(J25=0,0,3*COSTE!G5)
A26: FAMILIA | B26: SUB F. | C26: MATERIAL | D26: MURO - PUERTA | E26: COMENTARIOS | J26: UDS | K26: €/Uni | L26: €/Uni Real | M26: €/Empresa | N26: Markup % | O26: € TOTAL | P26: BEN.EMP | Q26: COSTE TOT | R26: Diseño (1h x 1uni) | S26: COSTE MAT | T26: Puerta (/3) | U26: (2h) Compra | V26: Alquiler Maneta (/5) | W26: Palet | X26: (4 uni/h) T. Paletizacion | Y26: Material | Z26: 6h/uni Fabricacion
A27: Muro | B27: Puerta | C27: Pintar | D27: Puerta + Maneta Codigo | J27: 0 | K27: 85 | L27: =IFERROR(ROUNDUP((Q27/J27)/0.5,0)*0.5,0) | M27: =IF(J27=0,J27*K27,J27*K27) | N27: =$N$46 | O27: =SUM(M27*N27)+M27 | P27: =SUM(O27-M27) | Q27: =R27+S27 | R27: =J27*(MAX(1,ROUNDUP(J27/1,0)*1)*COSTE!$G$3) | S27: =SUM(T27:AU27) | T27: =J27*(54/3) | U27: =J27*((COSTE!$G$4*2)/3) | V27: =J27*(131/5) | W27: =IF(J27=0,0,(((COSTE!$G$20/3)+(COSTE!$G$45*1)+(COSTE!$G$4/6)+(0.5)))/2) | X27: =(J27/4)*COSTE!$G$5
A28: Muro | B28: Puerta | C28: Pintar | D28: Puerta + Maneta Normal | J28: 0 | K28: 65 | L28: =IFERROR(ROUNDUP((Q28/J28)/0.5,0)*0.5,0) | M28: =IF(J28=0,J28*K28,J28*K28) | N28: =$N$46 | O28: =SUM(M28*N28)+M28 | P28: =SUM(O28-M28) | Q28: =R28+S28 | R28: =J28*(MAX(1,ROUNDUP(J28/1,0)*1)*COSTE!$G$3) | S28: =SUM(T28:AU28) | T28: =J28*(54/3) | U28: =J28*((COSTE!$G$4*2)/3) | V28: =J28*(10/5) | W28: =IF(J28=0,0,(((COSTE!$G$20/3)+(COSTE!$G$45*1)+(COSTE!$G$4/6)+(0.5)))/2) | X28: =(J28/4)*COSTE!$G$5
A29: Muro | B29: Puerta | C29: Blanco Lacado | D29: Puerta Melamina 1 cara + Maneta Codigo | J29: 0 | K29: 300 | L29: =IFERROR(ROUNDUP((Q29/J29)/0.5,0)*0.5,0) | M29: =IF(J29=0,J29*K29,J29*K29) | N29: =$N$46 | O29: =SUM(M29*N29)+M29 | P29: =SUM(O29-M29) | Q29: =R29+S29 | R29: =J29*(MAX(1,ROUNDUP(J29/1,0)*1)*COSTE!$G$3) | S29: =SUM(T29:AU29) | T29: =J29*(210/3) | U29: =J29*((COSTE!$G$4*2)/3) | V29: =(131/5)*J29 | W29: =IF(J29=0,0,(((COSTE!$G$20/3)+(COSTE!$G$45*1)+(COSTE!$G$4/6)+(0.5)))/2) | X29: =(J29/4)*COSTE!$G$5
A30: Muro | B30: Puerta | C30: Blanco Lacado | D30: Puerta Melamina 1 cara + Maneta Normal | J30: 0 | K30: 300 | L30: =IFERROR(ROUNDUP((Q30/J30)/0.5,0)*0.5,0) | M30: =IF(J30=0,J30*K30,J30*K30) | N30: =$N$46 | O30: =SUM(M30*N30)+M30 | P30: =SUM(O30-M30) | Q30: =R30+S30 | R30: =J30*(MAX(1,ROUNDUP(J30/1,0)*1)*COSTE!$G$3) | S30: =SUM(T30:AU30) | T30: =J30*(210/3) | U30: =J30*((COSTE!$G$4*2)/3) | V30: =J30*(10/5) | W30: =IF(J30=0,0,(((COSTE!$G$20/3)+(COSTE!$G$45*1)+(COSTE!$G$4/6)+(0.5)))/2) | X30: =(J30/4)*COSTE!$G$5
A31: Muro | B31: Puerta | C31: Chopo | D31: Puerta para Pintar a Medida + Maneta Codigo | E31: *New | J31: 0 | K31: 257 | L31: =IFERROR(ROUNDUP((Q31/J31)/0.5,0)*0.5,0) | M31: =IF(J31=0,J31*K31,J31*K31) | N31: =$N$46 | O31: =SUM(M31*N31)+M31 | P31: =SUM(O31-M31) | Q31: =R31+S31 | R31: =J31*(MAX(1,ROUNDUP(J31/1,0)*1)*COSTE!$G$3) | S31: =SUM(T31:AU31) | V31: =J31*(131/5) | W31: =IF(J31=0,0,(((COSTE!$G$20/3)+(COSTE!$G$45*1)+(COSTE!$G$4/6)+(0.5)))/2) | X31: =(J31/4)*COSTE!$G$5 | Y31: =J31*((COSTE!$G$41*10)+(COSTE!$G$43*5)+(COSTE!$G$30 *1)+(COSTE!$G$34)+ 20) | Z31: =(6*COSTE!$G$4)*J31
A32: Muro | B32: Puerta | C32: Chopo | D32: Puerta para Pintar a Medida + Maneta Normal | E32: *New | J32: 0 | K32: 233 | L32: =IFERROR(ROUNDUP((Q32/J32)/0.5,0)*0.5,0) | M32: =IF(J32=0,J32*K32,J32*K32) | N32: =$N$46 | O32: =SUM(M32*N32)+M32 | P32: =SUM(O32-M32) | Q32: =R32+S32 | R32: =J32*(MAX(1,ROUNDUP(J32/1,0)*1)*COSTE!$G$3) | S32: =SUM(T32:AU32) | V32: =J32*(10/5) | W32: =IF(J32=0,0,(((COSTE!$G$20/3)+(COSTE!$G$45*1)+(COSTE!$G$4/6)+(0.5)))/2) | X32: =(J32/4)*COSTE!$G$5 | Y32: =J32*((COSTE!$G$41*10)+(COSTE!$G$43*5)+(COSTE!$G$30 *1)+(COSTE!$G$34)+ 20) | Z32: =(6*COSTE!$G$4)*J32
A33: Muro | B33: Puerta | C33: Melamina | D33: Puerta Melamina a Medida + Maneta Codigo | E33: *New | J33: 0 | K33: 251 | L33: =IFERROR(ROUNDUP((Q33/J33)/0.5,0)*0.5,0) | M33: =IF(J33=0,J33*K33,J33*K33) | N33: =$N$46 | O33: =SUM(M33*N33)+M33 | P33: =SUM(O33-M33) | Q33: =R33+S33 | R33: =J33*(MAX(1,ROUNDUP(J33/1,0)*1)*COSTE!$G$3) | S33: =SUM(T33:AU33) | V33: =J33*(131/5) | W33: =IF(J33=0,0,(((COSTE!$G$20/3)+(COSTE!$G$45*1)+(COSTE!$G$4/6)+(0.5)))/2) | X33: =(J33/4)*COSTE!$G$5 | Y33: =J33*((COSTE!$G$41*10)+(COSTE!$G$43*5)+(COSTE!$G$30 *1)+(COSTE!$G$34)+ 20) | Z33: =(6*COSTE!$G$4)*J33
A34: Muro | B34: Puerta | C34: Melamina | D34: Puerta Melamina a Medida + Maneta Normal | E34: *New | J34: 0 | K34: 227 | L34: =IFERROR(ROUNDUP((Q34/J34)/0.5,0)*0.5,0) | M34: =IF(J34=0,J34*K34,J34*K34) | N34: =$N$46 | O34: =SUM(M34*N34)+M34 | P34: =SUM(O34-M34) | Q34: =R34+S34 | R34: =J34*(MAX(1,ROUNDUP(J34/1,0)*1)*COSTE!$G$3) | S34: =SUM(T34:AU34) | V34: =J34*(10/5) | W34: =IF(J34=0,0,(((COSTE!$G$20/3)+(COSTE!$G$45*1)+(COSTE!$G$4/6)+(0.5)))/2) | X34: =(J34/4)*COSTE!$G$5 | Y34: =J34*((COSTE!$G$41*10)+(COSTE!$G$43*5)+(COSTE!$G$30 *1)+(COSTE!$G$34)+ 20) | Z34: =(6*COSTE!$G$4)*J34
A35: Muro | B35: Puerta | C35: Cristal Alquiler | D35: Puerta (2,68m con Tarja) Alquiler | J35: 0 | K35: 209 | L35: =IFERROR(ROUNDUP((Q35/J35)/0.5,0)*0.5,0) | M35: =IF(J35=0,J35*K35,J35*K35) | N35: =$N$46 | O35: =SUM(M35*N35)+M35 | P35: =SUM(O35-M35) | Q35: =R35+S35 | R35: =J35*(MAX(1,ROUNDUP(J35/1,0)*1)*COSTE!$G$3) | S35: =SUM(T35:AU35) | T35: =(COSTE!G62/3)*J35 | V35: =J35*((200+150+150)/5) | X35: =(J35/4)*COSTE!$G$5
A36: FAMILIA | B36: SUB F. | C36: MATERIAL | D36: MURO - CRISTALES | E36: COMENTARIOS | F36: Largo | G36: Altura | I36: m2 | J36: UDS | K36: €/m2 | L36: €/Uni Real | M36: €/Empresa | N36: Markup % | O36: € TOTAL | P36: BEN.EMP | Q36: COSTE TOT | R36: Diseño 20m2/5h) | S36: COSTE MAT | T36: Cristal | U36: Cristal (/5) | V36: (8m2/h) T. Paletizacion | W36: Junquillos | X36: Canto | Y36: (20m2/h) Corte | Z36: (7m2/h) Cantear
A37: Muro | B37: Paredes | C37: Cristal | D37: Semimuro Compra | F37: 0 | G37: 0 | I37: =F37*G37 | J37: 0 | K37: 70 | L37: =IFERROR(ROUNDUP((Q37/I37)/0.5,0)*0.5,0) | M37: =IF(I37=0,J37*K37,I37*J37*K37) | N37: =$N$46 | O37: =SUM(M37*N37)+M37 | P37: =SUM(O37-M37) | Q37: =R37+S37 | R37: =J37*(MAX(1,ROUNDUP(I37/20,0)*5)*COSTE!$G$3) | S37: =SUM(T37:AU37) | T37: =((I37*6.49)+(I37*67.28)+(30))*J37 | V37: =(I37/8)*COSTE!$G$5 | W37: =(((F37*0.04)*4) +((G37*0.04)*4))*COSTE!$G$13 | X37: =((F37*8)+(G37*8))*COSTE!$G$49 | Y37: =((((F37*0.04)*4) +((G37*0.04)*4))/20)*COSTE!$G$4 | Z37: =((((F37*0.04)*4) +((G37*0.04)*4))/7)*COSTE!$G$4
A38: Muro | B38: Paredes | C38: Cristal Alquiler | D38: Pared (2,68m Altura) Alquiler | F38: 0 | G38: 0 | I38: =F38*G38 | J38: 0 | K38: 25 | L38: =IFERROR(ROUNDUP((Q38/I38)/0.5,0)*0.5,0) | M38: =IF(I38=0,J38*K38,I38*J38*K38) | N38: =$N$46 | O38: =SUM(M38*N38)+M38 | P38: =SUM(O38-M38) | Q38: =R38+S38 | R38: =J38*(MAX(1,ROUNDUP(I38/20,0)*5)*COSTE!$G$3) | S38: =SUM(U38:AU38) | U38: =(((I38*6.49)+(I38*67.28)+(30))/5)*J38 | V38: =(I38/8)*COSTE!$G$5 | W38: =(((F38*0.04)*4) +((G38*0.04)*4))*COSTE!$G$13 | X38: =((F38*8)+(G38*8))*COSTE!$G$49 | Y38: =((((F38*0.04)*4) +((G38*0.04)*4))/20)*COSTE!$G$4 | Z38: =((((F38*0.04)*4) +((G38*0.04)*4))/7)*COSTE!$G$4
A39: FAMILIA | B39: SUB F. | C39: MATERIAL | D39: MURO - CURVAS / REGATA LED / AISLANTE MURO | E39: COMENTARIOS | F39: Ancho | G39: Fondo | H39: Altura | I39: ml / m2 | J39: UDS | K39: €/ml m2 | L39: €/Uni Real | M39: €/Empresa | N39: Markup % | O39: € TOTAL | P39: BEN.EMP | Q39: COSTE TOT | R39: Diseño | S39: COSTE MAT | T39: (4 ml/h) T. Fabricación | U39: (2 ml/h) T. Fabricación | V39: Material | W39: (30m2/h) T. Paletizacion | X39: Palets | Y39: Tableros chopo | Z39: ( 20m2/h) Corte | AA39: Merma 20% | AB39: Estructura | AC39: Corte | AD39: Merma 20% | AE39: CNC | AF39: (2m2/h) T. Fabricación | AG39: (30m2/h) T. Paletizacion | AH39: Palets | AI39: Tornilleria
A40: Muro | B40: Curvas | C40: Chopo | D40: Para Pintar Chopo 5mm a 1 caras (Minimo 1m2 por tira) | F40: 0 | G40: 0 | H40: 0 | I40: =F40*G40 | J40: 0 | K40: 44 | L40: =IFERROR(ROUNDUP((Q40/I40)/0.5,0)*0.5,0) | M40: =IF(I40=0,J40*K40,I40*J40*K40) | N40: =$N$126 | O40: =SUM(M40*N40)+M40 | P40: =SUM(O40-M40) | Q40: =R40+S40 | R40: =J40*(MAX(1,ROUNDUP(I40/2,0)*1)*COSTE!$G$3) | S40: =SUM(T40:AU40) | Y40: =COSTE!$G$32*( (0.25*2*3.1415*F40)*H40) | Z40: =(( (0.25*2*3.1415*F40)*H40)/20)*COSTE!$G$4 | AA40: =Y40*20% | AB40: =COSTE!$G$20*((F40*G40)*H40)+((F40*H40)*((0.25*2*3.1415*F40)/0.5)) | AC40: =((F40*H40)*((0.25*2*3.1415*F40)*COSTE!$J$14)) | AD40: =AB40*20% | AE40: =(((F40*G40)*H40)/5)*25 | AF40: =(I40/1)*COSTE!$G$4 | AG40: =(I40/30)*COSTE!$G$5 | AH40: =ROUNDUP(I40/35,0)*((COSTE!$G$20/3)+(COSTE!$G$45*1)+(COSTE!$G$4/6)+(0.5)) | AI40: =I40*0.1
A41: Muro | B41: Curvas | C41: Chopo | D41: Para Pintar Chopo 5mm a 2 caras (Minimo 1m2 por tira) | F41: 0 | G41: 0 | H41: 0 | I41: =F41*G41 | J41: 0 | K41: 58 | L41: =IFERROR(ROUNDUP((Q41/I41)/0.5,0)*0.5,0) | M41: =IF(I41=0,J41*K41,I41*J41*K41) | N41: =$N$126 | O41: =SUM(M41*N41)+M41 | P41: =SUM(O41-M41) | Q41: =R41+S41 | R41: =J41*(MAX(1,ROUNDUP(I41/2,0)*1)*COSTE!$G$3) | S41: =SUM(T41:AU41) | Y41: =COSTE!$G$32*(( (0.25*2*3.1415*F41)*H41)*2) | Z41: =(( ((0.25*2*3.1415*F41)*H41)*2)/20)*COSTE!$G$4 | AA41: =Y41*20% | AB41: =COSTE!$G$20*((F41*G41)*H41)+((F41*H41)*((0.25*2*3.1415*F41)/0.5)) | AC41: =((F41*H41)*((0.25*2*3.1415*F41)*COSTE!$J$14)) | AD41: =AB41*20% | AE41: =(((F41*G41)*H41)/5)*25 | AF41: =(I41/0.75)*COSTE!$G$4 | AG41: =(I41/30)*COSTE!$G$5 | AH41: =ROUNDUP(I41/35,0)*((COSTE!$G$20/3)+(COSTE!$G$45*1)+(COSTE!$G$4/6)+(0.5)) | AI41: =I41*0.1
A42: Muro | B42: Tapetas | C42: MDF | D42: 5mm (Minimo 1m2 por tira) | F42: 0 | G42: 0 | I42: =F42*G42 | J42: 0 | K42: 5 | L42: =IFERROR(ROUNDUP((Q42/I42)/0.5,0)*0.5,0) | M42: =IF(I42=0,J42*K42,I42*J42*K42) | N42: =$N$64 | O42: =SUM(M42*N42)+M42 | P42: =SUM(O42-M42) | Q42: =R42+S42 | R42: =J42*(MAX(1,ROUNDUP(I42/5,0)*0.5)*COSTE!$G$3) | S42: =SUM(T42:AU42) | T42: =I42*COSTE!$G$26 | U42: =(I42/15)*COSTE!$G$4 | V42: =(I42/30)*COSTE!$G$5
A43: Muro | B43: Proceso | C43: Regata | D43: Regata Led Recta | I43: 0 | J43: 0 | K43: 5 | L43: =IFERROR(ROUNDUP((Q43/I43)/0.5,0)*0.5,0) | M43: =IF(I43=0,J43*K43,I43*J43*K43) | N43: =$N$14 | O43: =SUM(M43*N43)+M43 | P43: =SUM(O43-M43) | Q43: =R43+S43 | R43: =J43*(MAX(1,ROUNDUP(I43/10,0)*3)*COSTE!$G$3) | S43: =SUM(T43:AU43) | T43: =(I43/4)*COSTE!$G$5
A44: Muro | B44: Proceso | C44: Regata | D44: Regata Led Diagonal o Curva | I44: 0 | J44: 0 | K44: 10 | L44: =IFERROR(ROUNDUP((Q44/I44)/0.5,0)*0.5,0) | M44: =IF(I44=0,J44*K44,I44*J44*K44) | N44: =$N$14 | O44: =SUM(M44*N44)+M44 | P44: =SUM(O44-M44) | Q44: =R44+S44 | R44: =J44*(MAX(1,ROUNDUP(I44/10,0)*3)*COSTE!$G$3) | S44: =SUM(T44:AU44) | U44: =(I44/2)*COSTE!$G$5
A45: Muro | B45: Aislante | C45: Lana Roca | D45: Panel acustico | F45: 0 | G45: 0 | I45: =F45*G45 | J45: 0 | K45: 3 | L45: =IFERROR(ROUNDUP((Q45/I45)/0.5,0)*0.5,0) | M45: =IF(I45=0,J45*K45,I45*J45*K45) | N45: =$N$46 | O45: =SUM(M45*N45)+M45 | P45: =SUM(O45-M45) | Q45: =R45+S45 | R45: =J45*(MAX(1,ROUNDUP(I45/20,0)*1)*COSTE!$G$3) | S45: =SUM(T45:AU45) | V45: =I45*COSTE!$G$67 | W45: =(I45/30)*COSTE!$G$5 | X45: =ROUNDUP(I45/35,0)*((COSTE!$G$20/3)+(COSTE!$G$45*1)+(COSTE!$G$4/6)+(0.5))
K46: TOTAL MURO | M46: =SUM(M15:M45) | N46: =$N$2 | O46: =SUM(O16:O45) | P46: =SUM(P15:P45) | Q46: =SUM(Q15:Q45) | S46: =SUM(S15:S45)
A47: FAMILIA | B47: SUB F. | C47: MATERIAL | D47: BANNER | E47: COMENTARIOS | F47: Largo | G47: Altura | H47: Grosor | I47: m2 | J47: UDS | K47: €/m2 | L47: €/Uni Real | M47: €/Empresa | N47: Markup % | O47: € TOTAL | P47: BEN.EMP | Q47: COSTE TOT | R47: Diseño (50m2/6h) | S47: COSTE MAT | T47: Tableros | U47: (20m2/h) Corte | V47: Merma 20% | W47: Estructura | X47: (18ml/h) Corte | Y47: Merma 20% | Z47: (5/4m2/h) T. Fabricación | AA47: (50m2/h) T. Paletizacion | AB47: Palets | AC47: Tornilleria
A48: Banner | B48: Banner | C48: Chopo | D48: Banner 1 cara Chopo 5mm + Estructura Pino (Grosor Estandar 0,05m) | F48: 0 | G48: 0 | H48: 0 | I48: =F48*G48 | J48: 0 | K48: 23 | L48: =IFERROR(ROUNDUP((Q48/I48)/0.5,0)*0.5,0) | M48: =IF(I48=0,J48*K48,I48*J48*K48) | N48: =$N$54 | O48: =SUM(M48*N48)+M48 | P48: =SUM(O48-M48) | Q48: =R48+S48 | R48: =J48*(MAX(1,ROUNDUP(I48/50,0)*6)*COSTE!$G$3) | S48: =SUM(T48:AU48) | T48: =(F48*G48)*COSTE!$G$30 | U48: =(I48/20)*COSTE!$G$4 | V48: =T48*20% | W48: =((F48*2)+(G48*6))*COSTE!$G$41 | X48: =(((F48*2)+(G48*6))/18)*COSTE!$G$4 | Y48: =W48*20% | Z48: =(I48/5)*COSTE!$G$4 | AA48: =(I48/50)*COSTE!$G$4 | AB48: =ROUNDUP(I48/50,0)*((COSTE!$G$20/3)+(COSTE!$G$45*1)+(COSTE!$G$4/6)+(0.5)) | AC48: =I48*0.01
A49: Banner | B49: Banner | C49: Chopo | D49: Banner 2 caras Chopo 5mm + Estructura Pino (Grosor Estandar 0,055m) | F49: 0 | G49: 0 | H49: 0 | I49: =F49*G49 | J49: 0 | K49: 37 | L49: =IFERROR(ROUNDUP((Q49/I49)/0.5,0)*0.5,0) | M49: =IF(I49=0,J49*K49,I49*J49*K49) | N49: =$N$54 | O49: =SUM(M49*N49)+M49 | P49: =SUM(O49-M49) | Q49: =R49+S49 | R49: =J49*(MAX(1,ROUNDUP(I49/50,0)*6)*COSTE!$G$3) | S49: =SUM(T49:AU49) | T49: =((F49*G49)*2)*COSTE!$G$30 | U49: =((I49*2)/20)*COSTE!$G$4 | V49: =T49*20% | W49: =((F49*2)+(G49*6))*COSTE!$G$41 | X49: =(((F49*2)+(G49*6))/18)*COSTE!$G$4 | Y49: =W49*20% | Z49: =(I49/4)*COSTE!$G$4 | AA49: =(I49/50)*COSTE!$G$4 | AB49: =ROUNDUP(I49/50,0)*((COSTE!$G$20/3)+(COSTE!$G$45*1)+(COSTE!$G$4/6)+(0.5)) | AC49: =I49*0.01
A50: Banner | B50: Banner | C50: Chopo | D50: Banner 2 caras Chopo 5mm + Estructura Pino (Grosor <0,055mm) | F50: 0 | G50: 0 | H50: 0 | I50: =F50*G50 | J50: 0 | K50: 37 | L50: =IFERROR(ROUNDUP((Q50/I50)/0.5,0)*0.5,0) | M50: =IF(I50=0,J50*K50,I50*J50*K50) | N50: =$N$54 | O50: =SUM(M50*N50)+M50 | P50: =SUM(O50-M50) | Q50: =R50+S50 | R50: =J50*(MAX(1,ROUNDUP(I50/50,0)*6)*COSTE!$G$3) | S50: =SUM(T50:AU50) | T50: =(((F50*G50)*2)+((F50*H50)*2)+(G50*H50*2))*COSTE!$G$30 | U50: =((I50*2)/20)*COSTE!$G$4 | V50: =T50*20% | W50: =((((F50*2)+(G50*6)*2)+(H50*20))*COSTE!$G$41) | X50: =((((F50*2)+(G50*6)*2)+(H50*20))/18)*COSTE!$G$4 | Y50: =W50*20% | Z50: =(I50/4)*COSTE!$G$4 | AA50: =(I50/50)*COSTE!$G$4 | AB50: =ROUNDUP(I50/50,0)*((COSTE!$G$20/3)+(COSTE!$G$45*1)+(COSTE!$G$4/6)+(0.5)) | AC50: =I50*0.01
A51: FAMILIA | B51: SUB F. | C51: MATERIAL | D51: BANNER - CURVAS / REGATA LED / AISLANTE MURO | E51: COMENTARIOS | F51: Ancho | G51: Fondo | H51: Altura | I51: m2 | J51: UDS | K51: €/Um2 | L51: €/Uni Real | M51: €/Empresa | N51: Markup % | O51: € TOTAL | P51: BEN.EMP | Q51: COSTE TOT | R51: Diseño | S51: COSTE MAT | T51: Tableros chopo | U51: ( 20m2/h) Corte | V51: Merma 20% | W51: Estructura | X51: Corte | Y51: Merma 20% | Z51: CNC | AA51: (2m2/h) T. Fabricación | AB51: (30m2/h) T. Paletizacion | AC51: Palets | AD51: Tornilleria
A52: Banner | B52: Curvas | C52: Chopo | D52: Para Pintar Chopo 5mm a 1 caras (Minimo 1m2 por tira) | F52: 0 | G52: 0 | H52: 0 | I52: =F52*G52 | J52: 0 | K52: 44 | L52: =IFERROR(ROUNDUP((Q52/I52)/0.5,0)*0.5,0) | M52: =IF(I52=0,J52*K52,I52*J52*K52) | N52: =$N$126 | O52: =SUM(M52*N52)+M52 | P52: =SUM(O52-M52) | Q52: =R52+S52 | R52: =J52*(MAX(1,ROUNDUP(I52/2,0)*1)*COSTE!$G$3) | S52: =SUM(T52:AU52) | T52: =COSTE!$G$32*( (0.25*2*3.1415*F52)*H52) | U52: =(( (0.25*2*3.1415*F52)*H52)/20)*COSTE!$G$4 | V52: =T52*20% | W52: =COSTE!$G$20*((F52*G52)*H52)+((F52*H52)*((0.25*2*3.1415*F52)/0.5)) | X52: =((F52*H52)*((0.25*2*3.1415*F52)*COSTE!$J$14)) | Y52: =W52*20% | Z52: =(((F52*G52)*H52)/5)*25 | AA52: =(I52/1)*COSTE!$G$4 | AB52: =(I52/30)*COSTE!$G$5 | AC52: =ROUNDUP(I52/35,0)*((COSTE!$G$20/3)+(COSTE!$G$45*1)+(COSTE!$G$4/6)+(0.5)) | AD52: =I52*0.1
A53: Banner | B53: Curvas | C53: Chopo | D53: Para Pintar Chopo 5mm a 2 caras (Minimo 1m2 por tira) | F53: 0 | G53: 0 | H53: 0 | I53: =F53*G53 | J53: 0 | K53: 58 | L53: =IFERROR(ROUNDUP((Q53/I53)/0.5,0)*0.5,0) | M53: =IF(I53=0,J53*K53,I53*J53*K53) | N53: =$N$126 | O53: =SUM(M53*N53)+M53 | P53: =SUM(O53-M53) | Q53: =R53+S53 | R53: =J53*(MAX(1,ROUNDUP(I53/2,0)*1)*COSTE!$G$3) | S53: =SUM(T53:AU53) | T53: =COSTE!$G$32*(( (0.25*2*3.1415*F53)*H53)*2) | U53: =(( ((0.25*2*3.1415*F53)*H53)/20)*2)*COSTE!$G$4 | V53: =T53*20% | W53: =COSTE!$G$20*((F53*G53)*H53)+((F53*H53)*((0.25*2*3.1415*F53)/0.5)) | X53: =((F53*H53)*((0.25*2*3.1415*F53)*COSTE!$J$14)) | Y53: =W53*20% | Z53: =(((F53*G53)*H53)/5)*25 | AA53: =(I53/0.75)*COSTE!$G$4 | AB53: =(I53/30)*COSTE!$G$5 | AC53: =ROUNDUP(I53/35,0)*((COSTE!$G$20/3)+(COSTE!$G$45*1)+(COSTE!$G$4/6)+(0.5)) | AD53: =I53*0.1
K54: TOTAL BANNER | M54: =SUM(M48:M53) | N54: =$N$2 | O54: =SUM(O48:O53) | P54: =SUM(P48:P53) | Q54: =SUM(Q48:Q53) | S54: =SUM(S48:S53)
A55: FAMILIA | B55: SUB F. | C55: MATERIAL | D55: VIGA | E55: COMENTARIOS | F55: Largo | G55: Ancho | H55: Alto | I55: m2 | J55: UDS | K55: €/m2 | L55: €/Uni Real | M55: €/Empresa | N55: Markup % | O55: € TOTAL | P55: BEN.EMP | Q55: COSTE TOT | R55: Diseño (1m2/1h) | S55: COSTE MAT | T55: Tableros | U55: (10m2/h) Corte | V55: Merma 30% | W55: (5m2/h) T. Fabricación | X55: (10m2/h) T. Paletizacion | Y55: Palets | Z55: Tornilleria
A56: Viga | B56: Viga | C56: Aglomerado | D56: Viga en U (Estandar 0,15m) | F56: 0 | G56: 0 | H56: 0 | I56: =(F56*G56)+((F56*H56)*2) | J56: 0 | K56: 110 | L56: =IFERROR(ROUNDUP((Q56/I56)/0.5,0)*0.5,0) | M56: =IF(I56=0,J56*K56,I56*J56*K56) | N56: =$N$69 | O56: =SUM(M56*N56)+M56 | P56: =SUM(O56-M56) | Q56: =R56+S56 | R56: =J56*(MAX(1, ROUNDUP(I56/1, 0) * 1) *COSTE!$G$3) | S56: =SUM(T56:AU56) | T56: =COSTE!$G$20*I56 | U56: =(I56/10)*COSTE!$G$4 | V56: =T56*30% | W56: =(I56/5)*COSTE!$G$4 | X56: =(I56/10)*COSTE!$G$4 | Y56: =ROUNDUP(I56/50,0)*((COSTE!$G$20/3)+(COSTE!$G$45*1)+(COSTE!$G$4/6)+(0.5)) | Z56: =I56*0.02
A57: Viga | B57: Viga | C57: Melamina | D57: Viga en U (Estandar 0,15m) | F57: 0 | G57: 0 | H57: 0 | I57: =(F57*G57)+((F57*H57)*2) | J57: 0 | K57: 145 | L57: =IFERROR(ROUNDUP((Q57/I57)/0.5,0)*0.5,0) | M57: =IF(I57=0,J57*K57,I57*J57*K57) | N57: =$N$69 | O57: =SUM(M57*N57)+M57 | P57: =SUM(O57-M57) | Q57: =R57+S57 | R57: =J57*(MAX(1, ROUNDUP(I57/1, 0) * 1) *COSTE!$G$3) | S57: =SUM(T57:AU57) | T57: =COSTE!$G$13*I57 | U57: =(I57/5)*COSTE!$G$4 | V57: =T57*30% | W57: =(I57/5)*COSTE!$G$4 | X57: =(I57/10)*COSTE!$G$4 | Y57: =ROUNDUP(I57/50,0)*((COSTE!$G$20/3)+(COSTE!$G$45*1)+(COSTE!$G$4/6)+(0.5)) | Z57: =I57*0.02
A58: Viga | B58: Viga | C58: Mel. Especial / Chopo | D58: Viga en U (Estandar 0,15m) | F58: 0 | G58: 0 | H58: 0 | I58: =(F58*G58)+((F58*H58)*2) | J58: 0 | K58: 150 | L58: =IFERROR(ROUNDUP((Q58/I58)/0.5,0)*0.5,0) | M58: =IF(I58=0,J58*K58,I58*J58*K58) | N58: =$N$69 | O58: =SUM(M58*N58)+M58 | P58: =SUM(O58-M58) | Q58: =R58+S58 | R58: =J58*(MAX(1, ROUNDUP(I58/1, 0) * 1) *COSTE!$G$3) | S58: =SUM(T58:AU58) | T58: =COSTE!$G$34*I58 | U58: =(I58/5)*COSTE!$G$4 | V58: =T58*30% | W58: =(I58/5)*COSTE!$G$4 | X58: =(I58/10)*COSTE!$G$4 | Y58: =ROUNDUP(I58/50,0)*((COSTE!$G$20/3)+(COSTE!$G$45*1)+(COSTE!$G$4/6)+(0.5)) | Z58: =I58*0.02
K59: TOTAL VIGAS | M59: =SUM(M56:M58) | N59: =$N$2 | O59: =SUM(O56:O58) | P59: =SUM(P56:P58) | Q59: =SUM(Q56:Q58) | S59: =SUM(S56:S58)
A60: FAMILIA | B60: SUB F. | C60: MATERIAL | D60: PILAR | E60: COMENTARIOS | F60: Largo | G60: Ancho | H60: Alto | I60: m2 | J60: UDS | K60: €/m2 | L60: €/Uni Real | M60: €/Empresa | N60: Markup % | O60: € TOTAL | P60: BEN.EMP | Q60: COSTE TOT | R60: Diseño (1m3/1h) | S60: COSTE MAT | T60: Tableros | U60: (10 /5 m2/h) Corte | V60: Merma 30% | W60: (5m2/h) T. Fabricación | X60: (5m2/h) T. Paletizacion | Y60: Palets | Z60: Tornilleria
A61: Pilar | B61: Pilar | C61: Aglomerado | D61: Pilar (Estandar 0,15m) | F61: 0 | G61: 0 | H61: 0 | I61: =((F61*G61)*2)+((F61*H61)*2) | J61: 0 | K61: 110 | L61: =IFERROR(ROUNDUP((Q61/I61)/0.5,0)*0.5,0) | M61: =IF(I61=0,J61*K61,I61*J61*K61) | N61: =$N$69 | O61: =SUM(M61*N61)+M61 | P61: =SUM(O61-M61) | Q61: =R61+S61 | R61: =J61*(MAX(1, ROUNDUP(I61/1, 0) * 1) *COSTE!$G$3) | S61: =SUM(T61:AU61) | T61: =COSTE!$G$20*I61 | U61: =(I61/10)*COSTE!$G$4 | V61: =T61*30% | W61: =(I61/5)*COSTE!$G$4 | X61: =(I61/5)*COSTE!$G$4 | Y61: =ROUNDUP(I61/50,0)*((COSTE!$G$20/3)+(COSTE!$G$45*1)+(COSTE!$G$4/6)+(0.5)) | Z61: =I61*0.02
A62: Pilar | B62: Pilar | C62: Melamina | D62: Pilar (Estandar 0,15m) | F62: 0 | G62: 0 | H62: 0 | I62: =((F62*G62)*2)+((F62*H62)*2) | J62: 0 | K62: 130 | L62: =IFERROR(ROUNDUP((Q62/I62)/0.5,0)*0.5,0) | M62: =IF(I62=0,J62*K62,I62*J62*K62) | N62: =$N$69 | O62: =SUM(M62*N62)+M62 | P62: =SUM(O62-M62) | Q62: =R62+S62 | R62: =J62*(MAX(1, ROUNDUP(I62/1, 0) * 1) *COSTE!$G$3) | S62: =SUM(T62:AU62) | T62: =COSTE!$G$13*I62 | U62: =(I62/5)*COSTE!$G$4 | V62: =T62*30% | W62: =(I62/5)*COSTE!$G$4 | X62: =(I62/5)*COSTE!$G$4 | Y62: =ROUNDUP(I62/50,0)*((COSTE!$G$20/3)+(COSTE!$G$45*1)+(COSTE!$G$4/6)+(0.5)) | Z62: =I62*0.02
A63: Pilar | B63: Pilar | C63: Mel. Especial / Chopo | D63: Pilar (Estandar 0,15m) | F63: 0 | G63: 0 | H63: 0 | I63: =((F63*G63)*2)+((F63*H63)*2) | J63: 0 | K63: 150 | L63: =IFERROR(ROUNDUP((Q63/I63)/0.5,0)*0.5,0) | M63: =IF(I63=0,J63*K63,I63*J63*K63) | N63: =$N$69 | O63: =SUM(M63*N63)+M63 | P63: =SUM(O63-M63) | Q63: =R63+S63 | R63: =J63*(MAX(1, ROUNDUP(I63/1, 0) * 1) *COSTE!$G$3) | S63: =SUM(T63:AU63) | T63: =COSTE!$G$34*I63 | U63: =(I63/5)*COSTE!$G$4 | V63: =T63*30% | W63: =(I63/5)*COSTE!$G$4 | X63: =(I63/5)*COSTE!$G$4 | Y63: =ROUNDUP(I63/50,0)*((COSTE!$G$20/3)+(COSTE!$G$45*1)+(COSTE!$G$4/6)+(0.5)) | Z63: =I63*0.02
K64: TOTAL PILAR | M64: =SUM(M61:M63) | N64: =$N$2 | O64: =SUM(O61:O63) | P64: =SUM(P61:P63) | Q64: =SUM(Q61:Q63) | S64: =SUM(S61:S63)
A65: FAMILIA | B65: SUB F. | C65: MATERIAL | D65: PODIUM | E65: COMENTARIOS | F65: Largo | G65: Ancho | H65: Alto | I65: m3 | J65: UDS | K65: €/m3 | L65: €/Uni Real | M65: €/Empresa | N65: Markup % | O65: € TOTAL | P65: BEN.EMP | Q65: COSTE TOT | R65: Diseño (1m3/2h) | S65: COSTE MAT | T65: Tableros | U65: (10/5 m2/h) Corte | V65: Merma 30% | W65: (0,75m3/h) T. Fabricación | X65: (5m2/h) T. Paletizacion | Y65: Palets | Z65: Tornilleria
A66: Podium | B66: Podium | C66: Aglomerado | D66: Podium | E66: *Lo paso a m3 el precio | F66: 0 | G66: 0 | H66: 0 | I66: =F66*G66*H66 | J66: 0 | K66: 220 | L66: =IFERROR(ROUNDUP((Q66/I66)/0.5,0)*0.5,0) | M66: =IF(I66=0,J66*K66,I66*J66*K66) | N66: =$N$69 | O66: =SUM(M66*N66)+M66 | P66: =SUM(O66-M66) | Q66: =R66+S66 | R66: =J66*(MAX(1, ROUNDUP(I66/1, 0) * 2) *COSTE!$G$3) | S66: =SUM(T66:AU66) | T66: =COSTE!$G$20*(((F66*G66)*2)+((F66*H66)*2)+(F66*G66)) | U66: =((((F66*G66)*2)+((F66*H66)*2)+(F66*G66))/10)*COSTE!$G$4 | V66: =T66*30% | W66: =(I66/1)*COSTE!$G$4 | X66: =(I66/5)*COSTE!$G$4 | Y66: =ROUNDUP(I66/50,0)*((COSTE!$G$20/3)+(COSTE!$G$45*1)+(COSTE!$G$4/6)+(0.5)) | Z66: =I66*0.02
A67: Podium | B67: Podium | C67: Melamina | D67: Podium | E67: *Lo paso a m3 el precio | F67: 0 | G67: 0 | H67: 0 | I67: =F67*G67*H67 | J67: 0 | K67: 250 | L67: =IFERROR(ROUNDUP((Q67/I67)/0.5,0)*0.5,0) | M67: =IF(I67=0,J67*K67,I67*J67*K67) | N67: =$N$69 | O67: =SUM(M67*N67)+M67 | P67: =SUM(O67-M67) | Q67: =R67+S67 | R67: =J67*(MAX(1, ROUNDUP(I67/1, 0) * 2) *COSTE!$G$3) | S67: =SUM(T67:AU67) | T67: =COSTE!$G$13*(((F67*G67)*2)+((F67*H67)*2)+(F67*G67)) | U67: =((((F67*G67)*2)+((F67*H67)*2)+(F67*G67))/5)*COSTE!$G$4 | V67: =T67*30% | W67: =(I67/0.75)*COSTE!$G$4 | X67: =(I67/5)*COSTE!$G$4 | Y67: =ROUNDUP(I67/50,0)*((COSTE!$G$20/3)+(COSTE!$G$45*1)+(COSTE!$G$4/6)+(0.5)) | Z67: =I67*0.02
A68: Podium | B68: Podium | C68: Mel. Especial / Chopo | D68: Podium | E68: *Lo paso a m3 el precio | F68: 0 | G68: 0 | H68: 0 | I68: =F68*G68*H68 | J68: 0 | K68: 300 | L68: =IFERROR(ROUNDUP((Q68/I68)/0.5,0)*0.5,0) | M68: =IF(I68=0,J68*K68,I68*J68*K68) | N68: =$N$69 | O68: =SUM(M68*N68)+M68 | P68: =SUM(O68-M68) | Q68: =R68+S68 | R68: =J68*(MAX(1, ROUNDUP(I68/1, 0) * 2) *COSTE!$G$3) | S68: =SUM(T68:AU68) | T68: =COSTE!$G$34*(((F68*G68)*2)+((F68*H68)*2)+(F68*G68)) | U68: =((((F68*G68)*2)+((F68*H68)*2)+(F68*G68))/5)*COSTE!$G$4 | V68: =T68*30% | W68: =(I68/0.75)*COSTE!$G$4 | X68: =(I68/5)*COSTE!$G$4 | Y68: =ROUNDUP(I68/50,0)*((COSTE!$G$20/3)+(COSTE!$G$45*1)+(COSTE!$G$4/6)+(0.5)) | Z68: =I68*0.02
K69: TOTAL PODIUMS | M69: =SUM(M66:M68) | N69: =$N$2 | O69: =SUM(O66:O68) | P69: =SUM(P66:P68) | Q69: =SUM(Q66:Q68) | S69: =SUM(S66:S68)
A70: FAMILIA | B70: SUB F. | C70: MATERIAL | D70: TECHOS | E70: COMENTARIOS | F70: Largo | G70: Ancho | H70: Alto | I70: m2 | J70: UDS | K70: €/m3 | L70: €/m2 Real | M70: €/Empresa | N70: Markup % | O70: € TOTAL | P70: BEN.EMP | Q70: COSTE TOT | R70: Diseño (50-20m2/6-1h) | S70: COSTE MAT | T70: Tableros | U70: (20m2/h) Corte | V70: Merma 20% | W70: Estructura | X70: (18ml/h) Corte | Y70: Merma 20% | Z70: (5/4m2/h) T. Fabricación | AA70: (50m2/h) T. Paletizacion | AB70: Palets | AC70: Tornilleria | AD70: Material
A71: Techos | B71: Techos | C71: Chopo + Pino | D71: Techo Bastidor pino Chopo 5mm | F71: 0 | G71: 0 | H71: 0 | I71: =F71*G71 | J71: 0 | K71: 28 | L71: =IFERROR(ROUNDUP((Q71/I71)/0.5,0)*0.5,0) | M71: =IF(I71=0,J71*K71,I71*J71*K71) | N71: =$N$74 | O71: =SUM(M71*N71)+M71 | P71: =SUM(O71-M71) | Q71: =R71+S71 | R71: =J71*(MAX(1,ROUNDUP(I71/50,0)*6)*COSTE!$G$3) | S71: =SUM(T71:AU71) | T71: =((F71*G71)+((F71*H71)*2)+((G71*H71)*2))*COSTE!$G$30 | U71: =(((F71*G71)+((F71*H71)*2)+((G71*H71)*2))/20)*COSTE!$G$4 | V71: =T71*20% | W71: =(((F71+H71)*2)+((G71+H71)*2)+(H71*F71)+(G71*H71))*COSTE!$G$41 | X71: =((((F71+H71)*2)+((G71+H71)*2)+(H71*F71)+(G71*H71))/18)*COSTE!$G$4 | Y71: =W71*20% | Z71: =(I71/5)*COSTE!$G$4 | AA71: =(I71/50)*COSTE!$G$4 | AB71: =ROUNDUP(I71/50,0)*((COSTE!$G$20/3)+(COSTE!$G$45*1)+(COSTE!$G$4/6)+(0.5)) | AC71: =I71*0.01
A72: Techos | B72: Techos | C72: Chopo | D72: Chopo de 15mm + Chopo de 5mm | F72: 0 | G72: 0 | H72: 0 | I72: =F72*G72 | J72: 0 | K72: 25 | L72: =IFERROR(ROUNDUP((Q72/I72)/0.5,0)*0.5,0) | M72: =IF(I72=0,J72*K72,I72*J72*K72) | N72: =$N$74 | O72: =SUM(M72*N72)+M72 | P72: =SUM(O72-M72) | Q72: =R72+S72 | R72: =J72*(MAX(1,ROUNDUP(I72/50,0)*6)*COSTE!$G$3) | S72: =SUM(T72:AU72) | T72: =(((F72*G72)*COSTE!$G$30))+(((F72*H72)*2)+((G72*H72)*2)+((F72*H72)*G72)*COSTE!$G$34) | U72: =(((F72*G72)+((F72*H72)*2)+((G72*H72)*2)+((F72*H72)*G72))/20)*COSTE!$G$4 | V72: =T72*20% | Z72: =(I72/4)*COSTE!$G$4 | AA72: =(I72/50)*COSTE!$G$4 | AB72: =ROUNDUP(I72/50,0)*((COSTE!$G$20/3)+(COSTE!$G$45*1)+(COSTE!$G$4/6)+(0.5)) | AC72: =I72*0.01
A73: Techos | B73: Aislante | C73: Lana Roca | D73: Panel acustico | F73: 0 | G73: 0 | I73: =F73*G73 | J73: 0 | K73: 3 | L73: =IFERROR(ROUNDUP((Q73/I73)/0.5,0)*0.5,0) | M73: =IF(I73=0,J73*K73,I73*J73*K73) | N73: =$N$46 | O73: =SUM(M73*N73)+M73 | P73: =SUM(O73-M73) | Q73: =R73+S73 | R73: =J73*(MAX(1, ROUNDUP(I73/20, 0) *1) *COSTE!$G$3) | S73: =SUM(T73:AU73) | AA73: =(I73/30)*COSTE!$G$5 | AB73: =ROUNDUP(I73/35,0)*((COSTE!$G$20/3)+(COSTE!$G$45*1)+(COSTE!$G$4/6)+(0.5)) | AD73: =I73*COSTE!$G$67
K74: TOTAL TECHOS | M74: =SUM(M71:M73) | N74: =$N$2 | O74: =SUM(O71:O73) | P74: =SUM(P71:P73) | Q74: =SUM(Q71:Q73) | S74: =SUM(S71:S73)
A75: FAMILIA | B75: SUB F. | C75: MATERIAL | D75: BACKLIGHTS | E75: COMENTARIOS | F75: Largo | G75: Altura | H75: Grosor | I75: m2 | J75: UDS | K75: €/m2 | L75: €/m2 Real | M75: €/Empresa | N75: Markup % | O75: € TOTAL | P75: BEN.EMP | Q75: COSTE TOT | R75: Diseño (50m2/5h) | S75: COSTE MAT | T75: Tableros | U75: (20m2/h) Corte | V75: Merma 20% | W75: Estructura | X75: (18ml/h) Corte | Y75: Merma 20% | Z75: (4m2/h) T. Fabricación | AA75: (50m2/h) T. Paletizacion | AB75: Palets | AC75: Tornilleria
A76: Backlights | B76: Backlights | C76: Chopo + Pino + Aglo. | D76: Backlights: Bastidor Pino+Lateral Chopo10mm+Trasera Aglo.16mm (G. Estandar 0,3m) | F76: 0 | G76: 0 | H76: 0 | I76: =F76*G76 | J76: 0 | K76: 220 | L76: =IFERROR(ROUNDUP((Q76/I76)/0.5,0)*0.5,0) | M76: =IF(I76=0,J76*K76,I76*J76*K76) | N76: =$N$78 | O76: =SUM(M76*N76)+M76 | P76: =SUM(O76-M76) | Q76: =R76+S76 | R76: =J76*(MAX(1, ROUNDUP(I76/50, 0) * 5) *COSTE!$G$3) | S76: =SUM(T76:AU76) | T76: =(((F76*G76)*COSTE!$G$20))+(((F76*H76)*2)+((G76*H76)*2)*COSTE!$G$33) | U76: =(((F76*G76)+((F76*H76)*2)+((G76*H76)*2))/20)*COSTE!$G$4 | V76: =T76*20% | W76: =(((F76+H76)*2)+((G76+H76)*2)+(H76*F76)+(G76*H76))*COSTE!$G$41 | X76: =((((F76*G76)*2)+((G76*F76)*2)+(H76*F76)+(G76*H76))/18)*COSTE!$G$4 | Y76: =W76*20% | Z76: =(I76/4)*COSTE!$G$4 | AA76: =(I76/50)*COSTE!$G$4 | AB76: =ROUNDUP(I76/50,0)*((COSTE!$G$20/3)+(COSTE!$G$45*1)+(COSTE!$G$4/6)+(0.5)) | AC76: =I76*0.01
A77: Backlights | B77: Backlights | C77: Chopo + Pino | D77: Backlights Elevado: Bastidor Pino + Lateral y trasera Chopo 10mm (G. Estandar 0,3m) | F77: 0 | G77: 0 | H77: 0 | I77: =F77*G77 | J77: 0 | K77: 220 | L77: =IFERROR(ROUNDUP((Q77/I77)/0.5,0)*0.5,0) | M77: =IF(I77=0,J77*K77,I77*J77*K77) | N77: =$N$78 | O77: =SUM(M77*N77)+M77 | P77: =SUM(O77-M77) | Q77: =R77+S77 | R77: =J77*(MAX(1, ROUNDUP(I77/50, 0) * 5) *COSTE!$G$3) | S77: =SUM(T77:AU77) | T77: =((F77*G77)+((F77*H77)*2)+((G77*H77)*2))*COSTE!$G$33 | U77: =(((F77*G77)+((F77*H77)*2)+((G77*H77)*2))/20)*COSTE!$G$4 | V77: =T77*20% | W77: =(((F77+H77)*2)+((G77+H77)*2)+(H77*F77)+(G77*H77))*COSTE!$G$41 | X77: =((((F77*G77)*2)+((G77*F77)*2)+(H77*F77)+(G77*H77))/18)*COSTE!$G$4 | Y77: =W77*20% | Z77: =(I77/4)*COSTE!$G$4 | AA77: =(I77/50)*COSTE!$G$4 | AB77: =ROUNDUP(I77/50,0)*((COSTE!$G$20/3)+(COSTE!$G$45*1)+(COSTE!$G$4/6)+(0.5)) | AC77: =I77*0.01
K78: TOTAL LUMINOSOS | M78: =SUM(M76:M77) | N78: =$N$2 | O78: =SUM(O76:O77) | P78: =SUM(P75:P77) | Q78: =SUM(Q75:Q77) | S78: =SUM(S75:S77)
A79: FAMILIA | B79: SUB F. | C79: MATERIAL | D79: LISTONES | E79: COMENTARIOS | F79: Largo | G79: Altura | H79: Grosor | I79: ml | J79: UDS | K79: €/ml | L79: €/ml Real | M79: €/Empresa | N79: Markup % | O79: € TOTAL | P79: BEN.EMP | Q79: COSTE TOT | R79: Diseño (20ml/0,5h) | S79: COSTE MAT | T79: Listones | U79: (18ml/h) Corte | V79: Merma 20% | W79: (20ml/h) T. Fabricación | X79: (100ml/h) T. Paletizacion | Y79: Palets | Z79: Tornilleria | AA79: Material | AB79: Merma 20%
A80: Liston | B80: Liston | C80: Pino | D80: Liston Flandes 45*45 | I80: 0 | J80: 0 | K80: 1.5075 | L80: =IFERROR(ROUNDUP((Q80/I80)/0.5,0)*0.5,0) | M80: =IF(I80=0,J80*K80,I80*J80*K80) | N80: =$N$87 | O80: =SUM(M80*N80)+M80 | P80: =SUM(O80-M80) | Q80: =R80+S80 | R80: =J80*(MAX(0.5, ROUNDUP(I80/20, 0) * 0.5) *COSTE!$G$3) | S80: =SUM(T80:AU80) | T80: =I80*COSTE!$G$42 | U80: =(I80/18)*COSTE!$G$4 | V80: =T80*20% | W80: =(I80/20)*COSTE!$G$4 | X80: =(I80/100)*COSTE!$G$4 | Y80: =ROUNDUP(I80/100,0)*((COSTE!$G$20/3)+(COSTE!$G$45*1)+(COSTE!$G$4/6)+(0.5)) | Z80: =I80*0.01
A81: Liston | B81: Liston | C81: Pino | D81: Liston Flandes 45*70 | I81: 0 | J81: 0 | K81: 1.8 | L81: =IFERROR(ROUNDUP((Q81/I81)/0.5,0)*0.5,0) | M81: =IF(I81=0,J81*K81,I81*J81*K81) | N81: =$N$87 | O81: =SUM(M81*N81)+M81 | P81: =SUM(O81-M81) | Q81: =R81+S81 | R81: =J81*(MAX(0.5, ROUNDUP(I81/20, 0) * 0.5) *COSTE!$G$3) | S81: =SUM(T81:AU81) | T81: =I81*COSTE!$G$43 | U81: =(I81/18)*COSTE!$G$4 | V81: =T81*20% | W81: =(I81/20)*COSTE!$G$4 | X81: =(I81/100)*COSTE!$G$4 | Y81: =ROUNDUP(I81/100,0)*((COSTE!$G$20/3)+(COSTE!$G$45*1)+(COSTE!$G$4/6)+(0.5)) | Z81: =I81*0.01
A82: Liston | B82: Liston | C82: Abeto | D82: Liston Abeto 120*60 | I82: 0 | J82: 0 | K82: 11.5 | L82: =IFERROR(ROUNDUP((Q82/I82)/0.5,0)*0.5,0) | M82: =IF(I82=0,J82*K82,I82*J82*K82) | N82: =$N$87 | O82: =SUM(M82*N82)+M82 | P82: =SUM(O82-M82) | Q82: =R82+S82 | R82: =J82*(MAX(0.5, ROUNDUP(I82/20, 0) * 0.5) *COSTE!$G$3) | S82: =SUM(T82:AU82) | T82: =I82*COSTE!$G$45 | U82: =(I82/18)*COSTE!$G$4 | V82: =T82*20% | W82: =(I82/20)*COSTE!$G$4 | X82: =(I82/100)*COSTE!$G$4 | Y82: =ROUNDUP(I82/100,0)*((COSTE!$G$20/3)+(COSTE!$G$45*1)+(COSTE!$G$4/6)+(0.5)) | Z82: =I82*0.01
A83: Liston | B83: Liston | C83: Abeto | D83: Liston Abeto 120*120 | I83: 0 | J83: 0 | K83: 82 | L83: =IFERROR(ROUNDUP((Q83/I83)/0.5,0)*0.5,0) | M83: =IF(I83=0,J83*K83,I83*J83*K83) | N83: =$N$87 | O83: =SUM(M83*N83)+M83 | P83: =SUM(O83-M83) | Q83: =R83+S83 | R83: =J83*(MAX(0.5, ROUNDUP(I83/20, 0) * 0.5) *COSTE!$G$3) | S83: =SUM(T83:AU83) | T83: =I83*COSTE!$G$46 | U83: =(I83/18)*COSTE!$G$4 | V83: =T83*20% | W83: =(I83/20)*COSTE!$G$4 | X83: =(I83/100)*COSTE!$G$4 | Y83: =ROUNDUP(I83/100,0)*((COSTE!$G$20/3)+(COSTE!$G$45*1)+(COSTE!$G$4/6)+(0.5)) | Z83: =I83*0.01
A84: Perfil | B84: Perfil | C84: Aluminio | D84: Pletina 20*3 Negro Brillante | E84: *New | I84: 0 | J84: 0 | K84: 5 | L84: =IFERROR(ROUNDUP((Q84/I84)/0.5,0)*0.5,0) | M84: =IF(I84=0,J84*K84,I84*J84*K84) | N84: =$N$87 | O84: =SUM(M84*N84)+M84 | P84: =SUM(O84-M84) | Q84: =R84+S84 | R84: =J84*(MAX(0.5, ROUNDUP(I84/20, 0) * 0.5) *COSTE!$G$3) | S84: =SUM(T84:AU84) | AA84: =I84*COSTE!$G$57 | AB84: =AA84*20%
A85: Perfil | B85: Perfil | C85: Aluminio | D85: Para Textiles Silicona | I85: 0 | J85: 0 | K85: 5 | L85: =IFERROR(ROUNDUP((Q85/I85)/0.5,0)*0.5,0) | M85: =IF(I85=0,J85*K85,I85*J85*K85) | N85: =$N$87 | O85: =SUM(M85*N85)+M85 | P85: =SUM(O85-M85) | Q85: =R85+S85 | R85: =J85*(MAX(0.5, ROUNDUP(I85/20, 0) * 0.5) *COSTE!$G$3) | S85: =SUM(T85:AU85) | AA85: =I85*COSTE!$G$58 | AB85: =AA85*20%
A86: Perfil | B86: Perfil | C86: Aluminio | D86: Perfil en U aluminio | I86: 0 | J86: 0 | K86: 5.77 | L86: =IFERROR(ROUNDUP((Q86/I86)/0.5,0)*0.5,0) | M86: =IF(I86=0,J86*K86,I86*J86*K86) | N86: =$N$87 | O86: =SUM(M86*N86)+M86 | P86: =SUM(O86-M86) | Q86: =R86+S86 | R86: =J86*(MAX(0.5, ROUNDUP(I86/20, 0) * 0.5) *COSTE!$G$3) | S86: =SUM(T86:AU86) | AA86: =I86*COSTE!$G$59 | AB86: =AA86*20%
K87: TOTAL LISTONES Y PERFILES | M87: =SUM(M80:M86) | N87: =$N$2 | O87: =SUM(O80:O86) | P87: =SUM(P80:P86) | Q87: =SUM(Q80:Q86) | S87: =SUM(S80:S86)
A88: FAMILIA | B88: SUB F. | C88: MATERIAL | D88: MOSTRADOR | E88: COMENTARIOS | F88: Largo | G88: Ancho | H88: Alto | I88: m3 | J88: UDS | K88: €/ml | L88: €/m3 Real | M88: €/Empresa | N88: Markup % | O88: € TOTAL | P88: BEN.EMP | Q88: COSTE TOT | R88: Diseño (1,5m3/2-6h) | S88: COSTE MAT | T88: Tableros | U88: (10m2/h) Corte | V88: Merma 30% | W88: ( m3/h) T. Fabricación | X88: (5m2/h) T. Paletizacion | Y88: Palets | Z88: Tornilleria | AA88: Lacado(Color) | AB88: Logistica Lacado | AC88: Mat. Curva | AD88: CNC
A89: Mostrador | B89: Recto | C89: Aglomerado | D89: Con Puertas | F89: 0 | G89: 0 | H89: 0 | I89: =F89*G89*H89 | J89: 0 | K89: 102.62509 | L89: =IFERROR(ROUNDUP((Q89/I89)/0.5,0)*0.5,0) | M89: =IF(I89=0,J89*K89,I89*J89*K89) | N89: =$N$111 | O89: =SUM(M89*N89)+M89 | P89: =SUM(O89-M89) | Q89: =R89+S89 | R89: =J89*(MAX(1, ROUNDUP(I89/1.5, 0) * 2) *COSTE!$G$3) | S89: =SUM(T89:AU89) | T89: =(((F89*H89)*2)+((F89*G89)*3)+((G89*H89)*2))*COSTE!$G$20 | U89: =((((F89*H89)*2)+((F89*G89)*3)+((G89*H89)*2))/10)*COSTE!$G$4 | V89: =T89*30% | W89: =(I89/0.75)*COSTE!$G$4 | X89: =(I89/5)*COSTE!$G$4 | Y89: =ROUNDUP(I89/50,0)*((COSTE!$G$20/3)+(COSTE!$G$45*1)+(COSTE!$G$4/6)+(0.5)) | Z89: =(ROUNDUP(I89,0)*(3+15+2 + (10*4)))*0.5
A90: Mostrador | B90: Recto | C90: Aglomerado | D90: Abierto | F90: 0 | G90: 0 | H90: 0 | I90: =F90*G90*H90 | J90: 0 | K90: 82.085088 | L90: =IFERROR(ROUNDUP((Q90/I90)/0.5,0)*0.5,0) | M90: =IF(I90=0,J90*K90,I90*J90*K90) | N90: =$N$111 | O90: =SUM(M90*N90)+M90 | P90: =SUM(O90-M90) | Q90: =R90+S90 | R90: =J90*(MAX(1, ROUNDUP(I90/1.5, 0) * 2) *COSTE!$G$3) | S90: =SUM(T90:AU90) | T90: =((F90*H90)+((F90*G90)*3)+((G90*H90)*2))*COSTE!$G$20 | U90: =(((F90*H90)+((F90*G90)*3)+((G90*H90)*2))/10)*COSTE!$G$4 | V90: =T90*30% | W90: =(I90/1)*COSTE!$G$4 | X90: =(I90/5)*COSTE!$G$4 | Y90: =ROUNDUP(I90/50,0)*((COSTE!$G$20/3)+(COSTE!$G$45*1)+(COSTE!$G$4/6)+(0.5)) | Z90: =(ROUNDUP(I90,0)*(3+15+2))*0.5
A91: Mostrador | B91: Recto | C91: Lacado | D91: Con Puertas | E91: *New | F91: 0 | G91: 0 | H91: 0 | I91: =F91*G91*H91 | J91: 0 | K91: 660 | L91: =IFERROR(ROUNDUP((Q91/I91)/0.5,0)*0.5,0) | M91: =IF(I91=0,J91*K91,I91*J91*K91) | N91: =$N$111 | O91: =SUM(M91*N91)+M91 | P91: =SUM(O91-M91) | Q91: =R91+S91 | R91: =J91*(MAX(1, ROUNDUP(I91/1.5, 0) * 2) *COSTE!$G$3) | S91: =SUM(T91:AU91) | T91: =(((F91*H91)*2)+((F91*G91)*3)+((G91*H91)*2))*COSTE!$G$20 | U91: =((((F91*H91)*2)+((F91*G91)*3)+((G91*H91)*2))/10)*COSTE!$G$4 | V91: =T91*30% | W91: =(I91/0.75)*COSTE!$G$4 | X91: =(I91/5)*COSTE!$G$4 | Y91: =ROUNDUP(I91/50,0)*((COSTE!$G$20/3)+(COSTE!$G$45*1)+(COSTE!$G$4/6)+(0.5)) | Z91: =(ROUNDUP(I91,0)*(3+15+2 + (10*4)))*0.5 | AA91: =(((((F91*H91)*2)+((F91*G91)*3)+((G91*H91)*2)))*2)*COSTE!$G$90 | AB91: =(2*COSTE!$G$4)*J91
A92: Mostrador | B92: Recto | C92: Lacado | D92: Abierto | E92: *New | F92: 0 | G92: 0 | H92: 0 | I92: =F92*G92*H92 | J92: 0 | K92: 540 | L92: =IFERROR(ROUNDUP((Q92/I92)/0.5,0)*0.5,0) | M92: =IF(I92=0,J92*K92,I92*J92*K92) | N92: =$N$111 | O92: =SUM(M92*N92)+M92 | P92: =SUM(O92-M92) | Q92: =R92+S92 | R92: =J92*(MAX(1, ROUNDUP(I92/1.5, 0) * 2) *COSTE!$G$3) | S92: =SUM(T92:AU92) | T92: =((F92*H92)+((F92*G92)*3)+((G92*H92)*2))*COSTE!$G$20 | U92: =(((F92*H92)+((F92*G92)*3)+((G92*H92)*2))/10)*COSTE!$G$4 | V92: =T92*30% | W92: =(I92/1)*COSTE!$G$4 | X92: =(I92/5)*COSTE!$G$4 | Y92: =ROUNDUP(I92/50,0)*((COSTE!$G$20/3)+(COSTE!$G$45*1)+(COSTE!$G$4/6)+(0.5)) | Z92: =(ROUNDUP(I92,0)*(3+15+2))*0.5 | AA92: =(((F92*H92)+((F92*G92)*3)+((G92*H92)*2))*2)*COSTE!$G$90 | AB92: =(2*COSTE!$G$4)*J92
A93: Mostrador | B93: Recto | C93: Melamina Blanca / Negra | D93: Con Puertas | F93: 0 | G93: 0 | H93: 0 | I93: =F93*G93*H93 | J93: 0 | K93: 158.1393 | L93: =IFERROR(ROUNDUP((Q93/I93)/0.5,0)*0.5,0) | M93: =IF(I93=0,J93*K93,I93*J93*K93) | N93: =$N$111 | O93: =SUM(M93*N93)+M93 | P93: =SUM(O93-M93) | Q93: =R93+S93 | R93: =J93*(MAX(1, ROUNDUP(I93/1.5, 0) * 2) *COSTE!$G$3) | S93: =SUM(T93:AU93) | T93: =(((F93*H93)*2)+((F93*G93)*3)+((G93*H93)*2))*COSTE!$G$13 | U93: =((((F93*H93)*2)+((F93*G93)*3)+((G93*H93)*2))/10)*COSTE!$G$4 | V93: =T93*30% | W93: =(I93/0.75)*COSTE!$G$4 | X93: =(I93/5)*COSTE!$G$4 | Y93: =ROUNDUP(I93/50,0)*((COSTE!$G$20/3)+(COSTE!$G$45*1)+(COSTE!$G$4/6)+(0.5)) | Z93: =(ROUNDUP(I93,0)*(3+15+2 + (10*4)))*0.5
A94: Mostrador | B94: Recto | C94: Melamina Blanca / Negra | D94: Abierto | F94: 0 | G94: 0 | H94: 0 | I94: =F94*G94*H94 | J94: 0 | K94: 137.5993 | L94: =IFERROR(ROUNDUP((Q94/I94)/0.5,0)*0.5,0) | M94: =IF(I94=0,J94*K94,I94*J94*K94) | N94: =$N$111 | O94: =SUM(M94*N94)+M94 | P94: =SUM(O94-M94) | Q94: =R94+S94 | R94: =J94*(MAX(1, ROUNDUP(I94/1.5, 0) * 2) *COSTE!$G$3) | S94: =SUM(T94:AU94) | T94: =((F94*H94)+((F94*G94)*3)+((G94*H94)*2))*COSTE!$G$13 | U94: =(((F94*H94)+((F94*G94)*3)+((G94*H94)*2))/10)*COSTE!$G$4 | V94: =T94*30% | W94: =(I94/1)*COSTE!$G$4 | X94: =(I94/5)*COSTE!$G$4 | Y94: =ROUNDUP(I94/50,0)*((COSTE!$G$20/3)+(COSTE!$G$45*1)+(COSTE!$G$4/6)+(0.5)) | Z94: =(ROUNDUP(I94,0)*(3+15+2))*0.5
A95: Mostrador | B95: Recto | C95: Melamina Color | D95: Con Puertas | E95: *New | F95: 0 | G95: 0 | H95: 0 | I95: =F95*G95*H95 | J95: 0 | K95: 290 | L95: =IFERROR(ROUNDUP((Q95/I95)/0.5,0)*0.5,0) | M95: =IF(I95=0,J95*K95,I95*J95*K95) | N95: =$N$111 | O95: =SUM(M95*N95)+M95 | P95: =SUM(O95-M95) | Q95: =R95+S95 | R95: =J95*(MAX(1, ROUNDUP(I95/1.5, 0) * 2) *COSTE!$G$3) | S95: =SUM(T95:AU95) | T95: =(((F95*H95)*2)+((F95*G95)*3)+((G95*H95)*2))*COSTE!$G$16 | U95: =((((F95*H95)*2)+((F95*G95)*3)+((G95*H95)*2))/10)*COSTE!$G$4 | V95: =T95*30% | W95: =(I95/0.75)*COSTE!$G$4 | X95: =(I95/5)*COSTE!$G$4 | Y95: =ROUNDUP(I95/50,0)*((COSTE!$G$20/3)+(COSTE!$G$45*1)+(COSTE!$G$4/6)+(0.5)) | Z95: =(ROUNDUP(I95,0)*(3+15+2 + (10*4)))*0.5
A96: Mostrador | B96: Recto | C96: Melamina Color | D96: Abierto | E96: *New | F96: 0 | G96: 0 | H96: 0 | I96: =F96*G96*H96 | J96: 0 | K96: 260 | L96: =IFERROR(ROUNDUP((Q96/I96)/0.5,0)*0.5,0) | M96: =IF(I96=0,J96*K96,I96*J96*K96) | N96: =$N$111 | O96: =SUM(M96*N96)+M96 | P96: =SUM(O96-M96) | Q96: =R96+S96 | R96: =J96*(MAX(1, ROUNDUP(I96/1.5, 0) * 2) *COSTE!$G$3) | S96: =SUM(T96:AU96) | T96: =((F96*H96)+((F96*G96)*3)+((G96*H96)*2))*COSTE!$G$16 | U96: =(((F96*H96)+((F96*G96)*3)+((G96*H96)*2))/10)*COSTE!$G$4 | V96: =T96*30% | W96: =(I96/1)*COSTE!$G$4 | X96: =(I96/5)*COSTE!$G$4 | Y96: =ROUNDUP(I96/50,0)*((COSTE!$G$20/3)+(COSTE!$G$45*1)+(COSTE!$G$4/6)+(0.5)) | Z96: =(ROUNDUP(I96,0)*(3+15+2))*0.5
A97: Mostrador | B97: Curvo | C97: Aglomerado | D97: Con Puertas | F97: 0 | G97: 0 | H97: 0 | I97: =F97*G97*H97 | J97: 0 | K97: 216.57433 | L97: =IFERROR(ROUNDUP((Q97/I97)/0.5,0)*0.5,0) | M97: =IF(I97=0,J97*K97,I97*J97*K97) | N97: =$N$111 | O97: =SUM(M97*N97)+M97 | P97: =SUM(O97-M97) | Q97: =R97+S97 | R97: =J97*(MAX(1, ROUNDUP(I97/1.5, 0) * 6) *COSTE!$G$3) | S97: =SUM(T97:AU97) | T97: =(((F97*H97)*2)+((F97*G97)*3)+((G97*H97)*2))*COSTE!$G$20 | U97: =((((F97*H97)*2)+((F97*G97)*3)+((G97*H97)*2))/10)*COSTE!$G$4 | V97: =T97*30% | W97: =(I97/0.2)*COSTE!$G$4 | X97: =(I97/5)*COSTE!$G$4 | Y97: =ROUNDUP(I97/50,0)*((COSTE!$G$20/3)+(COSTE!$G$45*1)+(COSTE!$G$4/6)+(0.5)) | Z97: =(ROUNDUP(I97,0)*(3+15+2 + (10*4)))*0.5 | AC97: =((((F97*H97)*2)+((F97*G97)*3)+((G97*H97)*2))*COSTE!$G$31)*0.25 | AD97: =I97*COSTE!$G$11
A98: Mostrador | B98: Curvo | C98: Aglomerado | D98: Abierto | F98: 0 | G98: 0 | H98: 0 | I98: =F98*G98*H98 | J98: 0 | K98: 167.47903 | L98: =IFERROR(ROUNDUP((Q98/I98)/0.5,0)*0.5,0) | M98: =IF(I98=0,J98*K98,I98*J98*K98) | N98: =$N$111 | O98: =SUM(M98*N98)+M98 | P98: =SUM(O98-M98) | Q98: =R98+S98 | R98: =J98*(MAX(1, ROUNDUP(I98/1.5, 0) * 6) *COSTE!$G$3) | S98: =SUM(T98:AU98) | T98: =((F98*H98)+((F98*G98)*3)+((G98*H98)*2))*COSTE!$G$20 | U98: =(((F98*H98)+((F98*G98)*3)+((G98*H98)*2))/10)*COSTE!$G$4 | V98: =T98*30% | W98: =(I98/0.25)*COSTE!$G$4 | X98: =(I98/5)*COSTE!$G$4 | Y98: =ROUNDUP(I98/50,0)*((COSTE!$G$20/3)+(COSTE!$G$45*1)+(COSTE!$G$4/6)+(0.5)) | Z98: =(ROUNDUP(I98,0)*(3+15+2))*0.5 | AC98: =((((F98*H98)*2)+((F98*G98)*3)+((G98*H98)*2))*COSTE!$G$31)*0.25 | AD98: =I98*COSTE!$G$11
A99: Mostrador | B99: Curvo | C99: Lacado | D99: Con Puertas | E99: *New | F99: 0 | G99: 0 | H99: 0 | I99: =F99*G99*H99 | J99: 0 | K99: 762 | L99: =IFERROR(ROUNDUP((Q99/I99)/0.5,0)*0.5,0) | M99: =IF(I99=0,J99*K99,I99*J99*K99) | N99: =$N$111 | O99: =SUM(M99*N99)+M99 | P99: =SUM(O99-M99) | Q99: =R99+S99 | R99: =J99*(MAX(1, ROUNDUP(I99/1.5, 0) * 6) *COSTE!$G$3) | S99: =SUM(T99:AU99) | T99: =(((F99*H99)*2)+((F99*G99)*3)+((G99*H99)*2))*COSTE!$G$20 | U99: =((((F99*H99)*2)+((F99*G99)*3)+((G99*H99)*2))/10)*COSTE!$G$4 | V99: =T99*30% | W99: =(I99*COSTE!$G$4)*8 | X99: =(I99/5)*COSTE!$G$4 | Y99: =ROUNDUP(I99/50,0)*((COSTE!$G$20/3)+(COSTE!$G$45*1)+(COSTE!$G$4/6)+(0.5)) | Z99: =(ROUNDUP(I99,0)*(3+15+2 + (10*4)))*0.5 | AA99: =((((F99*H99)*2)+((F99*G99)*3)+((G99*H99)*2))*2)*COSTE!$G$90 | AB99: =(2*COSTE!$G$4)*J99 | AC99: =((((F99*H99)*2)+((F99*G99)*3)+((G99*H99)*2))*COSTE!$G$31)*0.25 | AD99: =I99*COSTE!$G$11
A100: Mostrador | B100: Curvo | C100: Lacado | D100: Abierto | E100: *New | F100: 0 | G100: 0 | H100: 0 | I100: =F100*G100*H100 | J100: 0 | K100: 630 | L100: =IFERROR(ROUNDUP((Q100/I100)/0.5,0)*0.5,0) | M100: =IF(I100=0,J100*K100,I100*J100*K100) | N100: =$N$111 | O100: =SUM(M100*N100)+M100 | P100: =SUM(O100-M100) | Q100: =R100+S100 | R100: =J100*(MAX(1, ROUNDUP(I100/1.5, 0) * 6) *COSTE!$G$3) | S100: =SUM(T100:AU100) | T100: =((F100*H100)+((F100*G100)*3)+((G100*H100)*2))*COSTE!$G$20 | U100: =(((F100*H100)+((F100*G100)*3)+((G100*H100)*2))/10)*COSTE!$G$4 | V100: =T100*30% | W100: =(I100*COSTE!$G$4)*6 | X100: =(I100/5)*COSTE!$G$4 | Y100: =ROUNDUP(I100/50,0)*((COSTE!$G$20/3)+(COSTE!$G$45*1)+(COSTE!$G$4/6)+(0.5)) | Z100: =(ROUNDUP(I100,0)*(3+15+2))*0.5 | AA100: =(((F100*H100)+((F100*G100)*3)+((G100*H100)*2))*2)*COSTE!$G$90 | AB100: =(2*COSTE!$G$4)*J100 | AC100: =((((F100*H100)*2)+((F100*G100)*3)+((G100*H100)*2))*COSTE!$G$31)*0.25 | AD100: =I100*COSTE!$G$11
A101: Mostrador | B101: Curvo | C101: Formica | D101: Con Puertas | F101: 0 | G101: 0 | H101: 0 | I101: =F101*G101*H101 | J101: 0 | K101: 305.67837 | L101: =IFERROR(ROUNDUP((Q101/I101)/0.5,0)*0.5,0) | M101: =IF(I101=0,J101*K101,I101*J101*K101) | N101: =$N$111 | O101: =SUM(M101*N101)+M101 | P101: =SUM(O101-M101) | Q101: =R101+S101 | R101: =J101*(MAX(1, ROUNDUP(I101/1.5, 0) * 6) *COSTE!$G$3) | S101: =SUM(T101:AU101) | T101: =(((F101*H101)*2)+((F101*G101)*3)+((G101*H101)*2))*COSTE!$G$20 | U101: =((((F101*H101)*2)+((F101*G101)*3)+((G101*H101)*2))/10)*COSTE!$G$4 | V101: =T101*30% | W101: =(I101*COSTE!$G$4)*8 | X101: =(I101/5)*COSTE!$G$4 | Y101: =ROUNDUP(I101/50,0)*((COSTE!$G$20/3)+(COSTE!$G$45*1)+(COSTE!$G$4/6)+(0.5)) | Z101: =(ROUNDUP(I101,0)*(3+15+2 + (10*4)))*0.5 | AC101: =(((F101*H101)*2)+((F101*G101)*3)+((G101*H101)*2))*COSTE!$G$18 | AD101: =I101*COSTE!$G$11
...

Sheet COSTE
J1: EXTRAS
A2: FAMILIA | B2: SUB.FAMILIA MATERIAL | C2: DESCRIPICON | D2: X (mm) | E2: Y (mm) | F2: Grosor (mm) | G2: PRECIO | H2: UNI | I2: PROVEEDOR | J2: € | K2: Concepto | L2: € | M2: Concepto | N2: € | O2: Concepto | P2: €/Tablero
A3: Personal | B3: Diseño | G3: =COMPARATIVA!G3 | H3: €/h | I3: ESWood
A4: Personal | B4: Fabricación | G4: =COMPARATIVA!G4 | H4: €/h | I4: ESWood | J4: 23.7 | K4: H. Extra | L4: 13.52 | M4: 1/2Dieta | N4: 67 | O4: Dieta completa
A5: Personal | B5: Montaje | G5: =COMPARATIVA!G5 | H5: €/h | I5: ESWood | J5: 23.7 | K5: H. Extra | L5: 13.52 | M5: 1/2Dieta | N5: 67 | O5: Dieta completa
A6: Personal | B6: Desmontaje | G6: =COMPARATIVA!G6 | H6: €/h | I6: ESWood | J6: 23.7 | K6: H. Extra | L6: 13.52 | M6: 1/2Dieta | N6: 67 | O6: Dieta completa
A7: Personal | B7: Externo | C7: Montaje / Desmontaje Externo al dia | G7: =COMPARATIVA!G7 | H7: dia | I7: German
A8: Personal | B8: Coordinador Externo | C8: Montaje / Desmontaje Coordinador Externo al dia | G8: =COMPARATIVA!G8 | H8: dia | I8: German
A9: Personal | B9: Externo+Herrameintas | G9: =COMPARATIVA!G9 | H9: dia
A10: Personal | B10: Externo+Herrameintas | G10: =COMPARATIVA!G10 | H10: dia
A11: CNC | B11: Corte | G11: =COMPARATIVA!G11 | H11: Tablero | I11: ESWood
A13: Tablero | B13: Mel. Blanca | C13: Melamina Blanco K-110 PE 2/c Sef 16 mm | D13: 2800 | E13: 2070 | F13: 16 | G13: =COMPARATIVA!G13 | H13: €/m2 | I13: =COMPARATIVA!I13 | J13: =COMPARATIVA!J13 | K13: Corte (+/-m2) | L13: =COMPARATIVA!L13 | M13: Cadel | P13: =((D13/1000)*(E13/1000))*G13
A14: Tablero | B14: Mel. Negra | C14: Melamina Negra U-190 VL 16 mm | D14: 2800 | E14: 2070 | F14: 16 | G14: =COMPARATIVA!G17 | H14: €/m2 | I14: =COMPARATIVA!I17 | J14: =COMPARATIVA!J17 | K14: Corte (+/-m2) | L14: =COMPARATIVA!L17 | M14: Cadel | P14: =((D14/1000)*(E14/1000))*G14
A15: Tablero | B15: Mel. Velvet | C15: Melamina Velvet Oak D-2693 MW 16 mm | D15: 2800 | E15: 2070 | F15: 16 | G15: 10 | H15: €/m2 | I15: Mausa | J15: =COMPARATIVA!J20 | K15: Corte (+/-m2) | L15: 1.35 | M15: Cadel | P15: =((D15/1000)*(E15/1000))*G15
A16: Tablero | B16: Mel. Niagra | C16: Melamina Niagara Oak D-2240 VL 16 mm | D16: 2800 | E16: 2070 | F16: 16 | G16: =COMPARATIVA!G21 | H16: €/m2 | I16: =COMPARATIVA!I21 | J16: =COMPARATIVA!J21 | K16: Corte (+/-m2) | L16: 1.35 | M16: Cadel | P16: =((D16/1000)*(E16/1000))*G16
A17: Tablero | B17: Mel. Epecial | D17: 2800 | E17: 2070 | F17: 16 | G17: 13 | H17: €/m2 | I17: =COMPARATIVA!I22 | J17: =COMPARATIVA!J22 | K17: Corte (+/-m2) | L17: 1.35 | M17: Cadel | P17: =((D17/1000)*(E17/1000))*G17
A18: Formica | B18: Blanca | C18: Formica HPL | F18: 0.8 | G18: 15 | H18: €/m2 | I18: Gabarro | P18: =((D18/1000)*(E18/1000))*G18
A20: Tablero | B20: Aglomerado | C20: Aglomerado 1a standard 16mm | D20: 2800 | E20: 2070 | F20: 16 | G20: =COMPARATIVA!G24 | H20: €/m2 | I20: =COMPARATIVA!I24 | J20: =COMPARATIVA!J24 | K20: Corte (+/-m2) | L20: =COMPARATIVA!L24 | M20: Cadel | P20: =((D20/1000)*(E20/1000))*G20
A21: Tablero | B21: Aglomerado | C21: Aglomerado 1a standard 19mm | D21: 2800 | E21: 2070 | F21: 19 | G21: =COMPARATIVA!G35 | H21: €/m2 | I21: =COMPARATIVA!I35 | J21: =COMPARATIVA!J35 | K21: Corte (+/-m2) | L21: =COMPARATIVA!L35 | M21: Cadel | P21: =((D21/1000)*(E21/1000))*G21
A23: Tablero | B23: MDF | C23: Tablex Blanco 5mm (Zocalo) | D23: 2440 | E23: 1220 | F23: 5 | G23: =COMPARATIVA!G37 | H23: €/m2 | I23: =COMPARATIVA!I37 | J23: =COMPARATIVA!J37 | K23: Corte (+/-m2) | P23: =((D23/1000)*(E23/1000))*G23
A24: Tablero | B24: MDF | C24: Tablex Negro 5mm (Zocalo) | D24: 2440 | E24: 1220 | F24: 5 | G24: =COMPARATIVA!G39 | H24: €/m2 | I24: =COMPARATIVA!I39 | J24: =COMPARATIVA!J39 | K24: Corte (+/-m2) | P24: =((D24/1000)*(E24/1000))*G24
A25: Tablero | B25: MDF | C25: MDF Standard 3 mm | D25: 2440 | E25: 1220 | F25: 3 | G25: =COMPARATIVA!G41 | H25: €/m2 | I25: =COMPARATIVA!I41 | J25: =COMPARATIVA!J41 | K25: Corte (+/-m2) | P25: =((D25/1000)*(E25/1000))*G25
A26: Tablero | B26: MDF | C26: MDF Standard 5 mm | D26: 2440 | E26: 1220 | F26: 5 | G26: =COMPARATIVA!G42 | H26: €/m2 | I26: =COMPARATIVA!I42 | J26: =COMPARATIVA!J42 | K26: Corte (+/-m2) | P26: =((D26/1000)*(E26/1000))*G26
A27: Tablero | B27: MDF | C27: MDF Standard 16 mm | D27: 3660 | E27: 2070 | F27: 16 | G27: =COMPARATIVA!G46 | H27: €/m2 | I27: =COMPARATIVA!I46 | J27: =COMPARATIVA!J46 | K27: Corte (+/-m2) | L27: =COMPARATIVA!L46 | M27: Cadel | P27: =((D27/1000)*(E27/1000))*G27
A28: Tablero | B28: MDF | C28: MDF Standard 19 mm | D28: 3660 | E28: 2070 | F28: 19 | G28: =COMPARATIVA!G51 | H28: €/m2 | I28: =COMPARATIVA!I51 | J28: =COMPARATIVA!J51 | K28: Corte (+/-m2) | L28: =COMPARATIVA!L51 | M28: Cadel | P28: =((D28/1000)*(E28/1000))*G28
A30: Tablero | B30: Chopo | C30: BB/BB | D30: 2500 | E30: 1220 | F30: 5 | G30: =COMPARATIVA!G57 | H30: €/m2 | I30: =COMPARATIVA!I57 | P30: =((D30/1000)*(E30/1000))*G30
A31: Tablero | B31: Chopo Felx. | C31: Tablero Fromager flexible 5 mm (mostrador) | D31: 1220 | E31: 2500 | F31: 5 | G31: =COMPARATIVA!G62 | H31: €/m2 | I31: =COMPARATIVA!I62 | P31: =((D31/1000)*(E31/1000))*G31
A32: Tablero | B32: Chopo Felx. | C32: Tablero Fromager flexible 5 mm (Columna) | D32: 1220 | E32: 2500 | F32: 5 | G32: =COMPARATIVA!G66 | H32: €/m2 | I32: =COMPARATIVA!I66 | P32: =((D32/1000)*(E32/1000))*G32
A33: Tablero | B33: Chopo | C33: BB/BB | D33: 2500 | E33: 1220 | F33: 10 | G33: =COMPARATIVA!G69 | H33: €/m2 | I33: =COMPARATIVA!I69 | P33: =((D33/1000)*(E33/1000))*G33
A34: Tablero | B34: Chopo | C34: BB/BB | D34: 2500 | E34: 1220 | F34: 15 | G34: =COMPARATIVA!G70 | H34: €/m2 | I34: =COMPARATIVA!I70 | P34: =((D34/1000)*(E34/1000))*G34
A36: Tablero | B36: OSB | C36: Tablero OSB 3 XOP | D36: 2500 | E36: 1250 | F36: 9 | G36: =COMPARATIVA!G75 | H36: €/m2 | I36: =COMPARATIVA!I75
A37: Tablero | B37: OSB | C37: Tablero OSB 3 XOP | D37: 2500 | E37: 1250 | F37: 15 | G37: =COMPARATIVA!G76 | H37: €/m2 | I37: =COMPARATIVA!I76
A38: Tablero | B38: OSB | C38: Tablero OSB 3 XOP | D38: 2500 | E38: 1250 | F38: 18 | G38: =COMPARATIVA!G77 | H38: €/m2 | I38: =COMPARATIVA!I77
A39: Tablero | B39: OSB | C39: Tablero OSB 3 XOP | D39: 2500 | E39: 1250 | F39: 22 | G39: =COMPARATIVA!G78 | H39: €/m2 | I39: =COMPARATIVA!I78
A41: Liston | B41: Pino | C41: Liston Flandes 45*21 | D41: 4500 | E41: 45 | F41: 21 | G41: =COMPARATIVA!G80 | H41: €/ml | I41: Forestal Vic
A42: Liston | B42: Pino | C42: Liston Flandes 45*45 | D42: 4500 | E42: 45 | F42: 45 | G42: =COMPARATIVA!G84 | H42: €/ml | I42: Forestal Vic
A43: Liston | B43: Pino | C43: Liston Flandes 45*70 | D43: 4500 | E43: 45 | F43: 70 | G43: =COMPARATIVA!G87 | H43: €/ml | I43: Forestal Vic
A44: Liston | B44: Pino | C44: Liston Flandes 20*90 | D44: 4200 | E44: 20 | F44: 90 | G44: =COMPARATIVA!G90 | H44: €/ml | I44: Forestal Vic
A45: Liston | B45: Aveto | C45: Liston Aveto 120*60 | D45: 6500 | E45: 120 | F45: 60 | G45: =COMPARATIVA!G92 | H45: €/ml | I45: Forestal Vic
A46: Liston | B46: Aveto | C46: Liston Aveto 120*120 | D46: 6500 | E46: 120 | F46: 120 | G46: =COMPARATIVA!G94 | H46: €/ml | I46: Forestal Vic
A48: Canto | B48: Haya | C48: Canto xapa 22*5mm Haya Natural | E48: 22 | F48: 5 | G48: =COMPARATIVA!G96 | H48: €/ml | I48: Closa
A49: Canto | B49: Blanco | C49: Canto SEFT 22 X 0,8 MM | E49: 22 | F49: 0.8 | G49: =COMPARATIVA!G100 | H49: €/ml | I49: =COMPARATIVA!I100
A50: Canto | B50: Negro | C50: Canto ABS Negro U-190 23*0,8 | E50: 23 | F50: 0.8 | G50: =COMPARATIVA!G98 | H50: €/ml | I50: =COMPARATIVA!I98
A51: Canto | B51: Velvet Oak | C51: Canto Velvet Oak | E51: 22 | F51: 0.8 | G51: =COMPARATIVA!G101 | H51: €/ml | I51: M&M Cantos
A52: Canto | B52: Niagara Oak | C52: Canto Niagara Oak | E52: 22 | F52: 0.8 | G52: =COMPARATIVA!G102 | H52: €/ml | I52: M&M Cantos
A53: Canto | B53: Papaya | C53: Canto Papaya | E53: 22 | F53: 0.8 | G53: =COMPARATIVA!G103 | H53: €/ml | I53: M&M Cantos
A55: Perfil | B55: Aluminio Negro | C55: Perfil 40*20 Negro Brillante | D55: 6000 | E55: 40 | F55: 20 | G55: 2.541 | H55: €/ml | I55: Provedal
A56: Perfil | B56: Aluminio Blanco | C56: Perfil 40*20 Blanco Brillante | D56: 6000 | E56: 40 | F56: 20 | G56: 2.36 | H56: €/ml | I56: Provedal
A57: Pletina | B57: Aluminio Negro | C57: Pletina 20*3 Negro Brillante | D57: 6000 | E57: 20 | F57: 3 | G57: 2.39 | H57: €/ml | I57: Provedal
A58: Perfil | B58: Textil | C58: Para Textiles Silicona | G58: =COMPARATIVA!G108 | H58: €/ml
A59: Perfil | B59: Aluminio | C59: Perfil en U aluminio (?Cristal?) | G59: =COMPARATIVA!G109 | H59: €/ml
A61: Cristal | B61: Cristal | C61: Cristal a medida | G61: =(6.49)+(67.28)+(30) | H61: €/m2 | I61: Mascarell
A62: Cristal | B62: Puerta | C62: Puerta + Tarja a medida | G62: 500 | H62: uni | I62: Mascarell
A64: Muro | B64: Bmatrix | C64: Alquiler Muro Bmatrix | G64: =COMPARATIVA!G111 | H64: €/m2 | I64: =COMPARATIVA!I111
A66: Plastico | B66: Plastico | C66: Plastico galga 400 (6 x 100 m) | D66: 100 | E66: 6 | F66: 0.01 | G66: 0.0974 | H66: €/ml | I66: ??
A67: Aislante | B67: Lana Roca | C67: Lana roca | D67: 1.35 | E67: 0.6 | F67: 0.04 | G67: 4.05 | H67: €/m2 | I67: Leroy merlin | Q67: https://www.leroymerlin.es/productos/12-uds-de-paneles-lana-de-roca-isover-geowall-37-espesor-40mm-1-35x0-6m-r-1-09-15929354.html
A69: Logistica | B69: 1 Trailer | C69: ESWood - Feria BCN (13,6 Largo *2,4 Ancho *2,6 Alto) | G69: 390 | H69: Viaje | I69: Sertrans | J69: 200 | K69: Festivo | L69: 150 | M69: Dia siguente
A70: Logistica | B70: 1/2 Trailer | C70: ESWood - Feria BCN | G70: 250 | H70: Viaje | I70: Sertrans | K70: Festivo | M70: Dia siguente
A71: Logistica | B71: 1 Trailer | C71: ESWood - Madrid | G71: 1050 | H71: Viaje | I71: Sertrans
A72: Logistica | B72: 1/2 Trailer | C72: ESWood - Vigo | G72: 1150 | H72: Viaje | I72: Sertrans | J72: 250 | K72: Sabado | L72: 375 | M72: Domingo
A73: Logistica | B73: 1 Trailer | C73: ESWood - Vigo | G73: 1700 | H73: Viaje | I73: Sertrans | J73: 250 | K73: Sabado | L73: 375 | M73: Domingo
A74: Logistica | B74: 1/2 Trailer | C74: ESWood - Londres | H74: Viaje | I74: Sertrans
A75: Logistica | B75: 1 Trailer | C75: ESWood - Londres | G75: 3850 | H75: Viaje | I75: Sertrans | J75: 80 | K75: ATA
A76: Logistica | B76: 1 Trailer | C76: Londres - ESWood | G76: 2350 | H76: Viaje | I76: Sertrans | J76: 80 | K76: ATA
A78: Logistica | B78: Toro | C78: 1h con conductor Feria Granvia Resa | G78: 86 | H78: €/1h | I78: Resa Expo | L78: 0.1 | M78: 10 dias antelacion
A79: Logistica | B79: Toro | C79: 1 dia Sin conductor Feria Granvia Resa | G79: =163+150 | H79: €/1dia | I79: Resa Expo | L79: 0.1 | M79: 10 dias antelacion
A80: Logistica | B80: Toro | C80: 1h con conductor Feria Granvia Resa (MWC) | H80: €/1h | I80: Resa Expo | L80: 0.1 | M80: 10 dias antelacion
A81: Logistica | B81: Toro | C81: 1 dia Sin conductor Feria Granvia Resa (MWC) | H81: €/1dia | I81: Resa Expo | L81: 0.1 | M81: 10 dias antelacion
A83: Logistica | B83: Reciclado | C83: 1 Container reciclado | G83: 300 | H83: €/Uni
A85: Pintor | B85: Blanca | G85: 7 | H85: €/m2 | I85: Guayaba
A86: Pintor | B86: Color | G86: 10 | H86: €/m2 | I86: Guayaba
A87: Pintor | B87: 1 Capa | C87: Almacen y Vinilo | G87: 4.5 | H87: €/m2 | I87: Guayaba
A88: Pintor | B88: Barniz | G88: 11.5 | H88: €/m2 | I88: Guayaba
A89: Lacado | B89: Blanco | C89: Lacado blanco mueble montado | G89: =COMPARATIVA!G127 | H89: €/m2 | I89: Gopecosa
A90: Lacado | B90: Color | C90: Lacado Color mueble montado | G90: =COMPARATIVA!G128 | H90: €/m2 | I90: Gopecosa

Sheet COMPARATIVA
J1: EXTRAS
A2: FAMILIA | B2: SUB.FAMILIA MATERIAL | C2: DESCRIPICON | D2: X (mm) | E2: Y (mm) | F2: Grosor (mm) | G2: PRECIO | H2: UNI | I2: PROVEEDOR | J2: € | K2: Concepto | L2: € | M2: Concepto | N2: € | O2: Concepto | P2: €/Tablero
A3: Personal | B3: Diseño | G3: 21.26 | H3: €/h | I3: ESWood
A4: Personal | B4: Fabricación | G4: 22.4 | H4: €/h | I4: ESWood | J4: 23.7 | K4: H. Extra | L4: 13.52 | M4: 1/2Dieta | N4: 67 | O4: Dieta completa
A5: Personal | B5: Montaje | G5: 19.23 | H5: €/h | I5: ESWood | J5: 23.7 | K5: H. Extra | L5: 13.52 | M5: 1/2Dieta | N5: 67 | O5: Dieta completa
A6: Personal | B6: Desmontaje | G6: 19.23 | H6: €/h | I6: ESWood | J6: 23.7 | K6: H. Extra | L6: 13.52 | M6: 1/2Dieta | N6: 67 | O6: Dieta completa
A7: Personal | B7: Externo | C7: Montaje / Desmontaje Externo al dia (German) | G7: 250 | H7: dia | I7: German
A8: Personal | B8: Coordinador Externo | C8: Montaje / Desmontaje Coordinador Externo al dia (German) | G8: 300 | H8: dia | I8: German
A9: Personal | B9: Externo+Herrameintas
A10: Personal | B10: Externo+Herrameintas
A11: CNC | B11: Corte | G11: 23 | H11: Tablero | I11: ESWood
A13: Tablero | B13: Mel. Blanca | C13: Melamina Blanca 8685 BS KRONOS | D13: 2800 | E13: 2070 | F13: 16 | G13: 4.79 | H13: €/m2 | I13: Closa | J13: 0.58 | K13: Corte (+/-m2) | L13: 1.35 | M13: Cadel (+/-m2) | P13: =((D13/1000)*(E13/1000))*G13
A14: Tablero | B14: Mel. Blanca | C14: Melamina Blanco K-110 PE 2/c Sef 16 mm | D14: 2800 | E14: 2070 | F14: 16 | G14: 6.35 | H14: €/m2 | I14: Mausa | J14: 1.98 | K14: Corte (+/-m2) | P14: =((D14/1000)*(E14/1000))*G14
A15: Tablero | B15: Mel. Branca | C15: Melamina Blanca TIZA W908 ST7 | D15: 2800 | E15: 2070 | F15: 16 | G15: 5.35 | H15: €/m2 | I15: Albertch | N15: 5.16 | O15: Paquete | P15: =((D15/1000)*(E15/1000))*G15
A16: Tablero | B16: Mel. Blanca | C16: Melamina Blanca 8685 BS KRONOS | D16: 2800 | E16: 2070 | F16: 16 | G16: 5.07 | H16: €/m2 | I16: Albertch | N16: 4.9 | O16: Paquete | P16: =((D16/1000)*(E16/1000))*G16
A17: Tablero | B17: Mel. Negra | C17: Melamina Negra 16mm | D17: 2800 | E17: 2070 | F17: 16 | G17: 4.79 | H17: €/m2 | I17: Closa | J17: 0.58 | K17: Corte (+/-m2) | L17: 1.35 | M17: Cadel (+/-m2) | P17: =((D17/1000)*(E17/1000))*G17
A18: Tablero | B18: Mel. Negra | C18: Melamina Negra U-190 VL 16 mm | D18: 2800 | E18: 2070 | F18: 16 | H18: €/m2 | I18: Mausa | J18: 1.98 | K18: Corte (+/-m2) | P18: =((D18/1000)*(E18/1000))*G18
A19: Tablero | B19: Mel. Negra | C19: Melamina Negra 0190 BS KRONOS | D19: 2850 | E19: 2100 | F19: 16 | G19: 5.07 | H19: €/m2 | I19: Albertch | N19: 4.9 | O19: Paquete | P19: =((D19/1000)*(E19/1000))*G19
A20: Tablero | B20: Mel. Velvet | C20: Melamina Velvet Oak D-2693 MW 16 mm | D20: 2800 | E20: 2070 | F20: 16 | H20: €/m2 | I20: Mausa | J20: 1.98 | K20: Corte (+/-m2) | P20: =((D20/1000)*(E20/1000))*G20
A21: Tablero | B21: Mel. Niagra | C21: Melamina Niagara Oak D-2240 VL 16 mm | D21: 2800 | E21: 2070 | F21: 16 | G21: 9.8 | H21: €/m2 | I21: Mausa | J21: 1.98 | K21: Corte (+/-m2) | P21: =((D21/1000)*(E21/1000))*G21
A22: Tablero | B22: Mel. Papaya | C22: Melamina Monument Papaya Luxor 19 mm | D22: 2850 | E22: 2100 | F22: 19 | H22: €/m2 | I22: Mausa | J22: 1.98 | K22: Corte (+/-m2) | P22: =((D22/1000)*(E22/1000))*G22
A24: Tablero | B24: Aglomerado | C24: Aglomerado 1a standard 16mm | D24: 2800 | E24: 2070 | F24: 16 | G24: 3.78 | H24: €/m2 | I24: Closa | J24: 0.58 | K24: Corte (+/-m2) | L24: 1.35 | M24: Cadel (+/-m2) | P24: =((D24/1000)*(E24/1000))*G24
A25: Tablero | B25: Aglomerado | C25: Aglomerado 1a standard 16mm | D25: 2800 | E25: 2070 | F25: 16 | G25: 3.69 | H25: €/m2 | I25: Albaertch | N25: 3.57 | O25: Paquete | P25: =((D25/1000)*(E25/1000))*G25
A26: Tablero | B26: Aglomerado | C26: Aglomerado 1a standard 16mm | D26: 2800 | E26: 2070 | F26: 16 | G26: 4.02 | H26: €/m2 | I26: Gabarro | J26: =425.35/235 | K26: Corte (+/-m2) | L26: =428.61/296 | M26: Cadel (+/-m2) | P26: =((D26/1000)*(E26/1000))*G26
A27: Tablero | B27: Aglomerado | C27: Aglomerado 1a standard 16mm | D27: 2800 | E27: 2070 | F27: 16 | G27: 4.65 | H27: €/m2 | I27: Mausa | J27: 1.98 | K27: Corte (+/-m2) | P27: =((D27/1000)*(E27/1000))*G27
A28: Tablero | B28: Aglomerado | C28: Aglomerado 1a standard 16mm | D28: 3660 | E28: 2070 | F28: 16 | G28: 3.78 | H28: €/m2 | I28: Closa | J28: 0.58 | K28: Corte (+/-m2) | L28: 1.35 | M28: Cadel (+/-m2) | P28: =((D28/1000)*(E28/1000))*G28
A29: Tablero | B29: Aglomerado | C29: Aglomerado 1a standard 16mm | D29: 3660 | E29: 2070 | F29: 16 | G29: 4.02 | H29: €/m2 | I29: Gabarro | J29: =425.35/235 | K29: Corte (+/-m2) | L29: =428.61/296 | M29: Cadel (+/-m2) | P29: =((D29/1000)*(E29/1000))*G29
A30: Tablero | B30: Aglomerado | C30: Aglomerado 1a standard 16mm | D30: 3660 | E30: 2070 | F30: 16 | G30: 4.65 | H30: €/m2 | I30: Mausa | J30: 1.98 | K30: Corte (+/-m2) | P30: =((D30/1000)*(E30/1000))*G30
A31: Tablero | B31: Aglomerado | C31: Aglomerado 1a standard 16mm | D31: 3050 | E31: 2070 | F31: 16 | G31: 4.61 | H31: €/m2 | I31: Gabarro | J31: =425.35/235 | K31: Corte (+/-m2) | L31: =428.61/296 | M31: Cadel (+/-m2) | P31: =((D31/1000)*(E31/1000))*G31
A32: Tablero | B32: Aglomerado | C32: Aglomerado 1a standard 16mm | D32: 3050 | E32: 2070 | F32: 16 | G32: 3.69 | H32: €/m2 | I32: Albaertch | N32: 3.57 | O32: Paquete | P32: =((D32/1000)*(E32/1000))*G32
A33: Tablero | B33: Aglomerado | C33: Aglomerado 1a standard 16mm | D33: 4000 | E33: 2070 | F33: 16 | G33: 4.61 | H33: €/m2 | I33: Gabarro | J33: =425.35/235 | K33: Corte (+/-m2) | L33: =428.61/296 | M33: Cadel (+/-m2) | P33: =((D33/1000)*(E33/1000))*G33
A34: Tablero | B34: Aglomerado | C34: Aglomerado 1a standard 16mm | D34: 4000 | E34: 2070 | F34: 16 | G34: 3.69 | H34: €/m2 | I34: Albaertch | N34: 3.57 | O34: Paquete | P34: =((D34/1000)*(E34/1000))*G34
A35: Tablero | B35: Aglomerado | C35: Aglomerado 1a standard 19mm | D35: 2800 | E35: 2070 | F35: 19 | G35: 4.53 | H35: €/m2 | I35: Closa | J35: 0.58 | K35: Corte (+/-m2) | L35: 1.35 | M35: Cadel (+/-m2) | P35: =((D35/1000)*(E35/1000))*G35
A37: Tablero | B37: MDF Blanco | C37: MDF Lacado Blanco 1/Cara | D37: 244 | E37: 122 | F37: 5 | G37: 5.07 | H37: €/m2 | I37: Closa | J37: 0.58 | K37: Corte (+/- m2) | P37: =((D37/1000)*(E37/1000))*G37
A38: Tablero | B38: MDF | C38: Tablex Blanco 5mm (Zocalo) | D38: 2440 | E38: 1220 | F38: 5 | H38: €/m2 | I38: Mausa | P38: =((D38/1000)*(E38/1000))*G38
A39: Tablero | B39: MDF | C39: Tablex Negro 5mm (Zocalo) | D39: 2440 | E39: 1220 | F39: 5 | G39: 7 | H39: €/m2 | I39: Closa | J39: 0.58 | K39: Corte (+/- m2) | P39: =((D39/1000)*(E39/1000))*G39
A40: Tablero | B40: MDF | C40: Tablex Negro 5mm (Zocalo) | D40: 2440 | E40: 1220 | F40: 5 | H40: €/m2 | I40: Mausa | P40: =((D40/1000)*(E40/1000))*G40
A41: Tablero | B41: MDF | C41: MDF Standard 3 mm | D41: 2440 | E41: 1220 | F41: 3 | G41: 3 | H41: €/m2 | I41: Closa | J41: 0.58 | K41: Corte (+/-m2) | P41: =((D41/1000)*(E41/1000))*G41
A42: Tablero | B42: MDF | C42: MDF Standard 5 mm | D42: 2440 | E42: 1220 | F42: 5 | G42: 2.4 | H42: €/m2 | I42: Closa | J42: 0.58 | K42: Corte (+/-m2) | P42: =((D42/1000)*(E42/1000))*G42
A43: Tablero | B43: MDF | C43: MDF Standard 5 mm | D43: 2440 | E43: 1220 | F43: 5 | G43: 3.05 | H43: €/m2 | I43: Gabarro | J43: =425.35/235 | K43: Corte (+/-m2) | L43: =428.61/296 | M43: Cadel (+/-m2) | P43: =((D43/1000)*(E43/1000))*G43
A44: Tablero | B44: MDF | C44: MDF Standard 5 mm | D44: 2440 | E44: 1220 | F44: 5 | G44: 3.03 | H44: €/m2 | I44: Mausa | P44: =((D44/1000)*(E44/1000))*G44
A45: Tablero | B45: MDF | C45: MDF Standard 5 mm | D45: 2440 | E45: 1220 | F45: 5 | G45: 2.58 | H45: €/m2 | I45: Albaertch | N45: 2.5 | O45: Paquete | P45: =((D45/1000)*(E45/1000))*G45
A46: Tablero | B46: MDF | C46: MDF Standard 16 mm | D46: 2800 | E46: 2070 | F46: 16 | G46: 6.36 | H46: €/m2 | I46: Closa | J46: 0.58 | K46: Corte (+/-m2) | L46: 1.35 | M46: Cadel (+/-m2) | P46: =((D46/1000)*(E46/1000))*G46
A47: Tablero | B47: MDF | C47: MDF Standard 16 mm | D47: 2800 | E47: 2070 | F47: 16 | G47: 5.94 | H47: €/m2 | I47: Albaertch | N47: 5.74 | O47: Paquete | P47: =((D47/1000)*(E47/1000))*G47
A48: Tablero | B48: MDF | C48: MDF Standard 16 mm | D48: 3660 | E48: 2070 | F48: 16 | G48: 6.5 | H48: €/m2 | I48: Gabarro | J48: =425.35/235 | K48: Corte (+/-m2) | L48: =428.61/296 | M48: Cadel (+/-m2) | P48: =((D48/1000)*(E48/1000))*G48
A49: Tablero | B49: MDF | C49: MDF Standard 16 mm | D49: 3660 | E49: 2070 | F49: 16 | G49: 5.94 | H49: €/m2 | I49: Albaertch | N49: 5.74 | O49: Paquete | P49: =((D49/1000)*(E49/1000))*G49
A50: Tablero | B50: MDF | C50: MDF Standard 16 mm | D50: 3660 | E50: 2070 | F50: 16 | G50: 6.581 | H50: €/m2 | I50: Mausa | P50: =((D50/1000)*(E50/1000))*G50
A51: Tablero | B51: MDF | C51: MDF Standard 19 mm | D51: 2800 | E51: 2070 | F51: 19 | G51: 7.58 | H51: €/m2 | I51: Closa | J51: 0.58 | K51: Corte (+/-m2) | L51: 1.35 | M51: Cadel (+/-m2) | P51: =((D51/1000)*(E51/1000))*G51
A52: Tablero | B52: MDF | C52: MDF Standard 19 mm | D52: 2800 | E52: 2070 | F52: 19 | G52: 7.08 | H52: €/m2 | I52: Albaertch | N52: 6.84 | O52: Paquete | P52: =((D52/1000)*(E52/1000))*G52
A53: Tablero | B53: MDF | C53: MDF Standard 19 mm | D53: 3660 | E53: 2070 | F53: 19 | G53: 7.81 | H53: €/m2 | I53: Gabarro | J53: =425.35/235 | K53: Corte (+/-m2) | L53: =428.61/296 | M53: Cadel (+/-m2) | P53: =((D53/1000)*(E53/1000))*G53
A54: Tablero | B54: MDF | C54: MDF Standard 19 mm | D54: 3660 | E54: 2070 | F54: 19 | G54: 8.36 | H54: €/m2 | I54: Mausa | P54: =((D54/1000)*(E54/1000))*G54
A55: Tablero | B55: MDF | C55: MDF Standard 19 mm | D55: 3660 | E55: 2070 | F55: 19 | G55: 7.08 | H55: €/m2 | I55: Albaertch | N55: 6.84 | O55: Paquete | P55: =((D55/1000)*(E55/1000))*G55
A57: Tablero | B57: Chopo | C57: BB/BB | D57: 2440 | E57: 1220 | F57: 5 | G57: 5.77 | H57: €/m2 | I57: Closa | J57: 0.58 | K57: Corte (+/-m2) | P57: =((D57/1000)*(E57/1000))*G57
A58: Tablero | B58: Chopo | C58: BB/BB | D58: 2500 | E58: 1220 | F58: 4 | G58: 5.97 | H58: €/m2 | I58: Gabarro | J58: =425.35/235 | K58: Corte (+/-m2) | L58: =428.61/296 | M58: Cadel (+/-m2) | P58: =((D58/1000)*(E58/1000))*G58
A59: Tablero | B59: Chopo | C59: BB/BB | D59: 2500 | E59: 1220 | F59: 4 | G59: 5.4 | H59: €/m2 | I59: Albaertch | N59: 5.22 | O59: Paquete | P59: =((D59/1000)*(E59/1000))*G59
A60: Tablero | B60: Chopo | C60: BB/BB | D60: 2500 | E60: 1220 | F60: 5 | G60: 7.64 | H60: €/m2 | I60: Mausa | P60: =((D60/1000)*(E60/1000))*G60
A61: Tablero | B61: Chopo | C61: BB/BB | D61: 2500 | E61: 1220 | F61: 5 | G61: 6.18 | H61: €/m2 | I61: Albaertch | N61: 5.98 | O61: Paquete | P61: =((D61/1000)*(E61/1000))*G61
A62: Tablero | B62: Chopo Felx. | C62: Tablero Fromager flexible 5 mm (mostrador) | D62: 1220 | E62: 2500 | F62: 5 | G62: 8.18 | H62: €/m2 | I62: Closa | P62: =((D62/1000)*(E62/1000))*G62
A63: Tablero | B63: Chopo Felx. | C63: Tablero Fromager flexible 5 mm (mostrador) | D63: 1220 | E63: 2500 | F63: 5 | H63: €/m2 | I63: Gabarro | P63: =((D63/1000)*(E63/1000))*G63
A64: Tablero | B64: Chopo Felx. | C64: Tablero Fromager flexible 5 mm (mostrador) | D64: 1220 | E64: 2500 | F64: 5 | G64: 9.6 | H64: €/m2 | I64: Albaertch | N64: 9.6 | O64: Paquete | P64: =((D64/1000)*(E64/1000))*G64
A65: Tablero | B65: Chopo Felx. | C65: Tablero Fromager flexible 5 mm (mostrador) | D65: 1220 | E65: 2500 | F65: 5 | H65: €/m2 | I65: Mausa
A66: Tablero | B66: Chopo Felx. | C66: Tablero Fromager flexible 5 mm (Columna) | D66: 1220 | E66: 2500 | F66: 5 | G66: 8.18 | H66: €/m2 | I66: Closa | P66: =((D66/1000)*(E66/1000))*G66
A67: Tablero | B67: Chopo Felx. | C67: Tablero Fromager flexible 5 mm (Columna) | D67: 1220 | E67: 2500 | F67: 5 | H67: €/m2 | I67: Gabarro | P67: =((D67/1000)*(E67/1000))*G67
A68: Tablero | B68: Chopo Felx. | C68: Tablero Fromager flexible 5 mm (Columna) | D68: 1220 | E68: 2500 | F68: 5 | H68: €/m2 | I68: Mausa
A69: Tablero | B69: Chopo | C69: BB/BB | D69: 2440 | E69: 1220 | F69: 10 | G69: 9.46 | H69: €/m2 | I69: Closa | J69: 0.58 | K69: Corte (+/-m2) | P69: =((D69/1000)*(E69/1000))*G69
A70: Tablero | B70: Chopo | C70: BB/BB | D70: 2440 | E70: 1220 | F70: 15 | G70: 13.25 | H70: €/m2 | I70: Closa | J70: 0.58 | K70: Corte (+/-m2) | P70: =((D70/1000)*(E70/1000))*G70
A71: Tablero | B71: Chopo | C71: BB/BB | D71: 2500 | E71: 1220 | F71: 15 | G71: 14.27 | H71: €/m2 | I71: Gabarro | J71: =425.35/235 | K71: Corte (+/-m2) | P71: =((D71/1000)*(E71/1000))*G71
A72: Tablero | B72: Chopo | C72: BB/BB | D72: 2500 | E72: 1220 | F72: 15 | G72: 13.5 | H72: €/m2 | I72: Albaertch | N72: 13.05 | O72: Paquete | P72: =((D72/1000)*(E72/1000))*G72
A73: Tablero | B73: Chopo | C73: BB/BB | D73: 2500 | E73: 1220 | F73: 15 | G73: 20.3 | H73: €/m2 | I73: Mausa | P73: =((D73/1000)*(E73/1000))*G73
A75: Tablero | B75: OSB | C75: Tablero OSB 3 XOP | D75: 2500 | E75: 1250 | F75: 9 | G75: 4.16 | H75: €/m2 | I75: Closa | N75: 3.91 | O75: Paquete
A76: Tablero | B76: OSB | C76: Tablero OSB 3 XOP | D76: 2500 | E76: 1250 | F76: 15 | G76: 6.18 | H76: €/m2 | I76: Closa | N76: 5.82 | O76: Paquete
A77: Tablero | B77: OSB | C77: Tablero OSB 3 XOP | D77: 2500 | E77: 1250 | F77: 18 | G77: 7.88 | H77: €/m2 | I77: Closa | N77: 7.41 | O77: Paquete
A78: Tablero | B78: OSB | C78: Tablero OSB 3 XOP | D78: 2500 | E78: 1250 | F78: 22 | G78: 9.86 | H78: €/m2 | I78: Closa | N78: 9.27 | O78: Paquete
A80: Liston | B80: Pino | C80: Liston Flandes 45*21 | D80: 4500 | E80: 45 | F80: 21 | G80: 0.66 | H80: €/ml | I80: Forestal Vic
A81: Liston | B81: Pino | C81: Liston Flandes 45*21 | D81: 4500 | E81: 45 | F81: 21 | G81: 0.73 | H81: €/ml | I81: Albaertch
A82: Liston | B82: Pino | C82: Liston Flandes 45*21 | D82: 4500 | E82: 45 | F82: 21 | G82: 0.9 | H82: €/ml | I82: Mausa
A83: Liston | B83: Pino | C83: Liston Flandes 45*20 | D83: 4500 | E83: 45 | F83: 20 | G83: 1.02 | H83: €/ml | I83: Closa | N83: 0.97 | O83: Paquete
A84: Liston | B84: Pino | C84: Liston Flandes 45*45 | D84: 4500 | E84: 45 | F84: 45 | G84: 1.33 | H84: €/ml | I84: Forestal Vic
A85: Liston | B85: Pino | C85: Liston Flandes 45*45 (SON DE 12MTS, LES PODEM VENDRE A 3000,4000,5000,6000,70000) | D85: 4500 | E85: 45 | F85: 45 | G85: 1.1 | H85: €/ml | I85: Albaertch
A86: Liston | B86: Pino | C86: Liston Flandes 45*45 | D86: 4500 | E86: 45 | F86: 45 | G86: 1.67 | H86: €/ml | I86: Closa | N86: 1.67 | O86: Paquete
A87: Liston | B87: Pino | C87: Liston Flandes 45*70 | D87: 4500 | E87: 45 | F87: 70 | G87: 1.99 | H87: €/ml | I87: Forestal Vic
A88: Liston | B88: Pino | C88: Liston Flandes 45*70 (SON DE 12MTS, LES PODEM VENDRE A 3000,4000,5000,6000,70000) | D88: 4500 | E88: 45 | F88: 70 | G88: 1.45 | H88: €/ml | I88: Albaertch
A89: Liston | B89: Pino | C89: Liston Flandes 45*70 | D89: 4500 | E89: 45 | F89: 70 | G89: 2.37 | H89: €/ml | I89: Closa | N89: 2.25 | O89: Paquete
A90: Liston | B90: Pino | C90: Liston Flandes 20*90 | D90: 4200 | E90: 20 | F90: 90 | G90: 1.95 | H90: €/ml | I90: Forestal Vic
A91: Liston | B91: Pino | C91: Liston Flandes 22*96 | D91: 3900 | E91: 22 | F91: 96 | G91: 1.45 | H91: €/ml | I91: Albertch
A92: Liston | B92: Aveto | C92: Biga laminada avet GL24H | D92: 6500 | E92: 120 | F92: 60 | G92: 5.84 | H92: €/ml | I92: Forestal Vic
A93: Liston | B93: Aveto | C93: Biga laminada avet GL24H (SON DE 12MTS, LES PODEM VENDRE A 3000,4000,5000,6000,70000) | D93: 6500 | E93: 120 | F93: 60 | G93: 4.92 | H93: €/ml | I93: Albaertch
A94: Liston | B94: Aveto | C94: Biga laminada avet 120*120 | D94: 6500 | E94: 120 | F94: 120 | G94: 12 | H94: €/ml | I94: Forestal Vic
A96: Canto | B96: Haya | C96: Canto xapa 22*0,8 mm Haya Natural (Es natural??) | E96: 22 | F96: 5 | G96: 0.42 | H96: €/ml | I96: Closa
A97: Canto | B97: Haya | C97: Canto xapa 22*5mm Haya Natural | E97: 22 | F97: 5 | G97: 0.35 | H97: €/ml | I97: M&M Cantos
A98: Canto | B98: Negro | C98: CANTELL NEGRE 22 X 0,8 | E98: 22 | F98: 0.8 | G98: 0.38 | H98: €/ml | I98: Closa
A99: Canto | B99: Negro | C99: Canto ABS Negro U-190 23*0,8 | E99: 23 | F99: 0.8 | G99: 0.68 | H99: €/ml | I99: Mausa
A100: Canto | B100: Blanco | C100: CANTELL Blanco 22 X 0,8 | E100: 22 | F100: 0.8 | G100: 0.18 | H100: €/ml | I100: Closa
A101: Canto | B101: Velvet Oak | C101: Canto Velvet Oak | E101: 22 | F101: 0.8 | G101: =35.217/100 | H101: €/ml | I101: M&M Cantos
A102: Canto | B102: Niagara Oak | C102: Canto Niagara Oak | E102: 22 | F102: 0.8 | G102: =35.217/100 | H102: €/ml | I102: M&M Cantos
A103: Canto | B103: Papaya | C103: Canto Papaya | E103: 22 | F103: 0.8 | G103: =35.217/100 | H103: €/ml | I103: M&M Cantos
A105: Perfil | B105: Aluminio Negro | C105: Perfil 40*20 Negro Brillante | D105: 6000 | E105: 40 | F105: 20 | G105: 2.541 | H105: €/ml | I105: Provedal
A106: Perfil | B106: Aluminio Blanco | C106: Perfil 40*20 Blanco Brillante | D106: 6000 | E106: 40 | F106: 20 | G106: 2.36 | H106: €/ml | I106: Provedal
A107: Pletina | B107: Aluminio Negro | C107: Pletina 20*3 Negro Brillante | D107: 6000 | E107: 20 | F107: 3 | G107: 2.39 | H107: €/ml | I107: Provedal
A108: Perfil | B108: Textil | C108: Para Textiles Silicona | G108: 5 | H108: €/ml | I108: ?
...

Sheet CALCULADORA 
A1: CALCULAR €/m2 DE TABLERO
A2: Largo m | B2: Ancho m | C2: m2 | D2: € Tablero | E2: €/m2
A3: 2.8 | B3: 2.07 | C3: =A3*B3 | D3: 106.2 | E3: =D3/C3 | G3: 6.89 | H3: 33 | I3: 4.61
A5: CALCULAR €/m2 DE CORTE
A6: Tableros | B6: Largo m | C6: Ancho m | D6: m2 | E6: m2 TOT | F6: € TOT Corte | G6: €/m2
A7: 8 | B7: 2.44 | C7: 1.22 | D7: =B7*C7 | E7: =D7*A7 | F7: 25 | G7: =F7/E7
A9: CALCULAR € TABLERO
A10: Largo m | B10: Ancho m | C10: m2 | D10: € Tablero | E10: €/m2
A11: 2.8 | B11: 2.07 | C11: =A11*B11 | D11: =C11*E11 | E11: 5.07

Sheet README_IMPORT
A1: ARCHIVO SEGURO PARA IMPORTACIÓN
A2: Este libro conserva intactas las hojas originales y añade hojas planas para lectura segura por scripts o bases de datos.
A3: Hojas originales conservadas | B3: PRESUPUESTO, COSTE, COMPARATIVA, CALCULADORA
A4: Hoja recomendada para tu app | B4: CATALOGO_IMPORT
A5: Qué contiene CATALOGO_IMPORT | B5: Una fila por partida/opción del PRESUPUESTO, sin celdas combinadas y con columnas fijas.
A6: Precio recomendado para importar | B6: unit_price_base
A7: Clave de familia recomendada | B7: family_key
A8: Clave única de item recomendada | B8: item_key
A9: Trazabilidad | B9: Cada fila guarda source_sheet y source_row para volver al origen exacto.
A10: Notas | B10: Las fórmulas del original se mantienen en sus hojas. Las hojas *_IMPORT usan valores planos para que la lectura sea robusta.

Sheet CATALOGO_IMPORT
A1: CATÁLOGO NORMALIZADO DESDE PRESUPUESTO
A2: source_sheet | B2: source_row | C2: section_header_row | D2: section_title | E2: family_key | F2: item_key | G2: family | H2: subfamily | I2: material | J2: item_name | K2: comments | L2: input1_label | M2: input2_label | N2: input3_label | O2: measure_unit | P2: quantity_label | Q2: price_label | R2: unit_price_base | S2: unit_price_raw | T2: measure_current | U2: measure_formula | V2: qty_current | W2: real_price_current | X2: real_price_formula | Y2: company_cost_current | Z2: company_cost_formula | AA2: markup_current | AB2: markup_formula | AC2: total_current | AD2: total_formula
A3: PRESUPUESTO | B3: 5 | C3: 4 | D3: TARIMA | E3: tarima | F3: tarima_suelo_aglomerado_reciclado_tarima_con_moqueta | G3: Tarima | H3: Suelo | I3: Aglomerado Reciclado | J3: Tarima con Moqueta | L3: Largo | M3: Ancho | O3: m2 | P3: UDS | Q3: €/m2 | R3: 7.77 | S3: 7.77 | T3: 0 | U3: =F5*G5 | V3: 0 | W3: 0 | X3: =IFERROR(ROUNDUP((Q5/I5)/0.5,0)*0.5,0) | Y3: 0 | Z3: =IF(I5=0,J5*K5,I5*J5*K5) | AA3: 1 | AB3: =$N$14 | AC3: 0 | AD3: =SUM(M5*N5)+M5
A4: PRESUPUESTO | B4: 6 | C4: 4 | D4: TARIMA | E4: tarima | F4: tarima_suelo_melamina_reciclado_tarima_melamina_reciclada | G4: Tarima | H4: Suelo | I4: Melamina Reciclado | J4: Tarima Melamina Reciclada | L4: Largo | M4: Ancho | O4: m2 | P4: UDS | Q4: €/m2 | R4: 22 | S4: 22 | T4: 0 | U4: =F6*G6 | V4: 0 | W4: 0 | X4: =IFERROR(ROUNDUP((Q6/I6)/0.5,0)*0.5,0) | Y4: 0 | Z4: =IF(I6=0,J6*K6,I6*J6*K6) | AA4: 1 | AB4: =$N$14 | AC4: 0 | AD4: =SUM(M6*N6)+M6
A5: PRESUPUESTO | B5: 7 | C5: 4 | D5: TARIMA | E5: tarima | F5: tarima_suelo_melamina_tarima_melamina_nueva | G5: Tarima | H5: Suelo | I5: Melamina | J5: Tarima Melamina Nueva | K5: *New | L5: Largo | M5: Ancho | O5: m2 | P5: UDS | Q5: €/m2 | R5: 30 | S5: 30 | T5: 0 | U5: =F7*G7 | V5: 0 | W5: 0 | X5: =IFERROR(ROUNDUP((Q7/I7)/0.5,0)*0.5,0) | Y5: 0 | Z5: =IF(I7=0,J7*K7,I7*J7*K7) | AA5: 1 | AB5: =$N$14 | AC5: 0 | AD5: =SUM(M7*N7)+M7
A6: PRESUPUESTO | B6: 8 | C6: 4 | D6: TARIMA | E6: tarima | F6: tarima_suelo_melamina_especial_tarima_melamina_especial | G6: Tarima | H6: Suelo | I6: Melamina Especial | J6: Tarima Melamina Especial | L6: Largo | M6: Ancho | O6: m2 | P6: UDS | Q6: €/m2 | R6: 32.58 | S6: 32.58 | T6: 0 | U6: =F8*G8 | V6: 0 | W6: 0 | X6: =IFERROR(ROUNDUP((Q8/I8)/0.5,0)*0.5,0) | Y6: 0 | Z6: =IF(I8=0,J8*K8,I8*J8*K8) | AA6: 1 | AB6: =$N$14 | AC6: 0 | AD6: =SUM(M8*N8)+M8
A7: PRESUPUESTO | B7: 10 | C7: 9 | D7: TARIMA - RAMPA | E7: tarima | F7: tarima_rampa_tarima_rampa_estandar_1x1 | G7: Tarima | H7: Rampa | I7: Tarima | J7: Rampa (Estandar 1x1) | K7: *El coste rampa lo pondria siempre igual por m2 ya que el valor del material esta en la tarima | L7: Fondo | M7: Ancho | O7: m2 | P7: UDS | Q7: €/m2 | R7: 28 | S7: 28 | T7: 0 | U7: =F10*G10 | V7: 0 | W7: 0 | X7: =IFERROR(ROUNDUP((Q10/I10)/0.5,0)*0.5,0) | Y7: 0 | Z7: =IF(I10=0,J10*K10,I10*J10*K10) | AA7: 1 | AB7: =$N$14 | AC7: 0 | AD7: =SUM(M10*N10)+M10
A8: PRESUPUESTO | B8: 12 | C8: 11 | D8: TARIMA - REGATA LED | E8: tarima | F8: tarima_proceso_regata_regata_led_recta | G8: Tarima | H8: Proceso | I8: Regata | J8: Regata Led Recta | O8: ml | P8: UDS | Q8: €/ml | R8: 5 | S8: 5 | T8: 0 | V8: 0 | W8: 0 | X8: =IFERROR(ROUNDUP((Q12/I12)/0.5,0)*0.5,0) | Y8: 0 | Z8: =IF(I12=0,J12*K12,I12*J12*K12) | AA8: 1 | AB8: =$N$14 | AC8: 0 | AD8: =SUM(M12*N12)+M12
A9: PRESUPUESTO | B9: 13 | C9: 11 | D9: TARIMA - REGATA LED | E9: tarima | F9: tarima_proceso_regata_regata_led_diagonal_o_curva | G9: Tarima | H9: Proceso | I9: Regata | J9: Regata Led Diagonal o Curva | O9: ml | P9: UDS | Q9: €/ml | R9: 10 | S9: 10 | T9: 0 | V9: 0 | W9: 0 | X9: =IFERROR(ROUNDUP((Q13/I13)/0.5,0)*0.5,0) | Y9: 0 | Z9: =IF(I13=0,J13*K13,I13*J13*K13) | AA9: 1 | AB9: =$N$14 | AC9: 0 | AD9: =SUM(M13*N13)+M13
A10: PRESUPUESTO | B10: 16 | C10: 15 | D10: MURO | E10: muro | F10: muro_paredes_aglomerado_1_cara_grosor_estandar_0_1m_altura_2_75m | G10: Muro | H10: Paredes | I10: Aglomerado | J10: 1 Cara (Grosor Estandar 0,1m / Altura 2,75m) | K10: *El grosor se pone en el excel | L10: Largo | M10: Altura | N10: Grosor | O10: m2 | P10: UDS | Q10: €/m2 | R10: 14 | S10: 14 | T10: 0 | U10: =F16*G16 | V10: 0 | W10: 0 | X10: =IFERROR(ROUNDUP((Q16/I16)/0.5,0)*0.5,0) | Y10: 0 | Z10: =IF(I16=0,J16*K16,I16*J16*K16) | AA10: 1 | AB10: =$N$46 | AC10: 0 | AD10: =SUM(M16*N16)+M16
A11: PRESUPUESTO | B11: 17 | C11: 15 | D11: MURO | E11: muro | F11: muro_paredes_aglomerado_2_cara_grosor_estandar_0_1m_altura_2_75m | G11: Muro | H11: Paredes | I11: Aglomerado | J11: 2 Cara (Grosor Estandar 0,1m / Altura 2,75m) | K11: *El grosor se pone en el excel | L11: Largo | M11: Altura | N11: Grosor | O11: m2 | P11: UDS | Q11: €/m2 | R11: 22 | S11: 22 | T11: 0 | U11: =F17*G17 | V11: 0 | W11: 0 | X11: =IFERROR(ROUNDUP((Q17/I17)/0.5,0)*0.5,0) | Y11: 0 | Z11: =IF(I17=0,J17*K17,I17*J17*K17) | AA11: 1 | AB11: =$N$46 | AC11: 0 | AD11: =SUM(M17*N17)+M17
A12: PRESUPUESTO | B12: 18 | C12: 15 | D12: MURO | E12: muro | F12: muro_paredes_mdf_1_cara_grosor_estandar_0_1m_altura_2_75m | G12: Muro | H12: Paredes | I12: MDF | J12: 1 Cara (Grosor Estandar 0,1m / Altura 2,75m) | K12: *El grosor se pone en el excel | L12: Largo | M12: Altura | N12: Grosor | O12: m2 | P12: UDS | Q12: €/m2 | R12: 21 | S12: 21 | T12: 0 | U12: =F18*G18 | V12: 0 | W12: 0 | X12: =IFERROR(ROUNDUP((Q18/I18)/0.5,0)*0.5,0) | Y12: 0 | Z12: =IF(I18=0,J18*K18,I18*J18*K18) | AA12: 1 | AB12: =$N$46 | AC12: 0 | AD12: =SUM(M18*N18)+M18
A13: PRESUPUESTO | B13: 19 | C13: 15 | D13: MURO | E13: muro | F13: muro_paredes_mdf_2_cara_grosor_estandar_0_1m_altura_2_75m | G13: Muro | H13: Paredes | I13: MDF | J13: 2 Cara (Grosor Estandar 0,1m/ Altura 2,75m) | K13: *El grosor se pone en el excel | L13: Largo | M13: Altura | N13: Grosor | O13: m2 | P13: UDS | Q13: €/m2 | R13: 34 | S13: 34 | T13: 0 | U13: =F19*G19 | V13: 0 | W13: 0 | X13: =IFERROR(ROUNDUP((Q19/I19)/0.5,0)*0.5,0) | Y13: 0 | Z13: =IF(I19=0,J19*K19,I19*J19*K19) | AA13: 1 | AB13: =$N$46 | AC13: 0 | AD13: =SUM(M19*N19)+M19
A14: PRESUPUESTO | B14: 20 | C14: 15 | D14: MURO | E14: muro | F14: muro_paredes_melamina_1_cara_grosor_estandar_0_1m_altura_2_75m | G14: Muro | H14: Paredes | I14: Melamina | J14: 1 Cara (Grosor Estandar 0,1m / Altura 2,75m) | K14: *El grosor se pone en el excel | L14: Largo | M14: Altura | N14: Grosor | O14: m2 | P14: UDS | Q14: €/m2 | R14: 15 | S14: 15 | T14: 0 | U14: =F20*G20 | V14: 0 | W14: 0 | X14: =IFERROR(ROUNDUP((Q20/I20)/0.5,0)*0.5,0) | Y14: 0 | Z14: =IF(I20=0,J20*K20,I20*J20*K20) | AA14: 1 | AB14: =$N$46 | AC14: 0 | AD14: =SUM(M20*N20)+M20
A15: PRESUPUESTO | B15: 21 | C15: 15 | D15: MURO | E15: muro | F15: muro_paredes_melamina_2_cara_grosor_estandar_0_1m_altura_2_75m | G15: Muro | H15: Paredes | I15: Melamina | J15: 2 Cara (Grosor Estandar 0,1m / Altura 2,75m) | K15: *El grosor se pone en el excel | L15: Largo | M15: Altura | N15: Grosor | O15: m2 | P15: UDS | Q15: €/m2 | R15: 25 | S15: 25 | T15: 0 | U15: =F21*G21 | V15: 0 | W15: 0 | X15: =IFERROR(ROUNDUP((Q21/I21)/0.5,0)*0.5,0) | Y15: 0 | Z15: =IF(I21=0,J21*K21,I21*J21*K21) | AA15: 1 | AB15: =$N$46 | AC15: 0 | AD15: =SUM(M21*N21)+M21
A16: PRESUPUESTO | B16: 22 | C16: 15 | D16: MURO | E16: muro | F16: muro_paredes_melamina_especial_chopo_1_cara_grosor_estandar_0_1m_altura_2_75m | G16: Muro | H16: Paredes | I16: Melamina Especial / Chopo | J16: 1 Cara (Grosor Estandar 0,1m/ Altura 2,75m) | K16: *El grosor se pone en el excel | L16: Largo | M16: Altura | N16: Grosor | O16: m2 | P16: UDS | Q16: €/m2 | R16: 21 | S16: 21 | T16: 0 | U16: =F22*G22 | V16: 0 | W16: 0 | X16: =IFERROR(ROUNDUP((Q22/I22)/0.5,0)*0.5,0) | Y16: 0 | Z16: =IF(I22=0,J22*K22,I22*J22*K22) | AA16: 1 | AB16: =$N$46 | AC16: 0 | AD16: =SUM(M22*N22)+M22
A17: PRESUPUESTO | B17: 23 | C17: 15 | D17: MURO | E17: muro | F17: muro_paredes_melamina_especial_chopo_2_cara_grosor_estandar_0_1m_altura_2_75m | G17: Muro | H17: Paredes | I17: Melamina Especial / Chopo | J17: 2 Cara (Grosor Estandar 0,1m/ Altura 2,75m) | K17: *El grosor se pone en el excel | L17: Largo | M17: Altura | N17: Grosor | O17: m2 | P17: UDS | Q17: €/m2 | R17: 36 | S17: 36 | T17: 0 | U17: =F23*G23 | V17: 0 | W17: 0 | X17: =IFERROR(ROUNDUP((Q23/I23)/0.5,0)*0.5,0) | Y17: 0 | Z17: =IF(I23=0,J23*K23,I23*J23*K23) | AA17: 1 | AB17: =$N$46 | AC17: 0 | AD17: =SUM(M23*N23)+M23
A18: PRESUPUESTO | B18: 25 | C18: 24 | D18: MURO - BMATRIX | E18: muro | F18: muro_paredes_bmatrix_alquiler_muro_bmatrix | G18: Muro | H18: Paredes | I18: Bmatrix | J18: Alquiler Muro Bmatrix | K18: *Modificar coste?? | L18: Largo | M18: Altura | N18: Grosor | O18: m2 | P18: UDS | Q18: €/m2 | R18: 50 | S18: 50 | T18: 0 | U18: =F25*G25 | V18: 0 | W18: 0 | X18: =IFERROR(ROUNDUP((Q25/I25)/0.5,0)*0.5,0) | Y18: 0 | Z18: =IF(I25=0,J25*K25,I25*J25*K25) | AA18: 1 | AB18: =$N$46 | AC18: 0 | AD18: =SUM(M25*N25)+M25
A19: PRESUPUESTO | B19: 27 | C19: 26 | D19: MURO - PUERTA | E19: muro | F19: muro_puerta_pintar_puerta_maneta_codigo | G19: Muro | H19: Puerta | I19: Pintar | J19: Puerta + Maneta Codigo | P19: UDS | Q19: €/Uni | R19: 85 | S19: 85 | V19: 0 | W19: 0 | X19: =IFERROR(ROUNDUP((Q27/J27)/0.5,0)*0.5,0) | Y19: 0 | Z19: =IF(J27=0,J27*K27,J27*K27) | AA19: 1 | AB19: =$N$46 | AC19: 0 | AD19: =SUM(M27*N27)+M27
A20: PRESUPUESTO | B20: 28 | C20: 26 | D20: MURO - PUERTA | E20: muro | F20: muro_puerta_pintar_puerta_maneta_normal | G20: Muro | H20: Puerta | I20: Pintar | J20: Puerta + Maneta Normal | P20: UDS | Q20: €/Uni | R20: 65 | S20: 65 | V20: 0 | W20: 0 | X20: =IFERROR(ROUNDUP((Q28/J28)/0.5,0)*0.5,0) | Y20: 0 | Z20: =IF(J28=0,J28*K28,J28*K28) | AA20: 1 | AB20: =$N$46 | AC20: 0 | AD20: =SUM(M28*N28)+M28
A21: PRESUPUESTO | B21: 29 | C21: 26 | D21: MURO - PUERTA | E21: muro | F21: muro_puerta_blanco_lacado_puerta_melamina_1_cara_maneta_codigo | G21: Muro | H21: Puerta | I21: Blanco Lacado | J21: Puerta Melamina 1 cara + Maneta Codigo | P21: UDS | Q21: €/Uni | R21: 300 | S21: 300 | V21: 0 | W21: 0 | X21: =IFERROR(ROUNDUP((Q29/J29)/0.5,0)*0.5,0) | Y21: 0 | Z21: =IF(J29=0,J29*K29,J29*K29) | AA21: 1 | AB21: =$N$46 | AC21: 0 | AD21: =SUM(M29*N29)+M29
A22: PRESUPUESTO | B22: 30 | C22: 26 | D22: MURO - PUERTA | E22: muro | F22: muro_puerta_blanco_lacado_puerta_melamina_1_cara_maneta_normal | G22: Muro | H22: Puerta | I22: Blanco Lacado | J22: Puerta Melamina 1 cara + Maneta Normal | P22: UDS | Q22: €/Uni | R22: 300 | S22: 300 | V22: 0 | W22: 0 | X22: =IFERROR(ROUNDUP((Q30/J30)/0.5,0)*0.5,0) | Y22: 0 | Z22: =IF(J30=0,J30*K30,J30*K30) | AA22: 1 | AB22: =$N$46 | AC22: 0 | AD22: =SUM(M30*N30)+M30
A23: PRESUPUESTO | B23: 31 | C23: 26 | D23: MURO - PUERTA | E23: muro | F23: muro_puerta_chopo_puerta_para_pintar_a_medida_maneta_codigo | G23: Muro | H23: Puerta | I23: Chopo | J23: Puerta para Pintar a Medida + Maneta Codigo | K23: *New | P23: UDS | Q23: €/Uni | R23: 257 | S23: 257 | V23: 0 | W23: 0 | X23: =IFERROR(ROUNDUP((Q31/J31)/0.5,0)*0.5,0) | Y23: 0 | Z23: =IF(J31=0,J31*K31,J31*K31) | AA23: 1 | AB23: =$N$46 | AC23: 0 | AD23: =SUM(M31*N31)+M31
A24: PRESUPUESTO | B24: 32 | C24: 26 | D24: MURO - PUERTA | E24: muro | F24: muro_puerta_chopo_puerta_para_pintar_a_medida_maneta_normal | G24: Muro | H24: Puerta | I24: Chopo | J24: Puerta para Pintar a Medida + Maneta Normal | K24: *New | P24: UDS | Q24: €/Uni | R24: 233 | S24: 233 | V24: 0 | W24: 0 | X24: =IFERROR(ROUNDUP((Q32/J32)/0.5,0)*0.5,0) | Y24: 0 | Z24: =IF(J32=0,J32*K32,J32*K32) | AA24: 1 | AB24: =$N$46 | AC24: 0 | AD24: =SUM(M32*N32)+M32
A25: PRESUPUESTO | B25: 33 | C25: 26 | D25: MURO - PUERTA | E25: muro | F25: muro_puerta_melamina_puerta_melamina_a_medida_maneta_codigo | G25: Muro | H25: Puerta | I25: Melamina | J25: Puerta Melamina a Medida + Maneta Codigo | K25: *New | P25: UDS | Q25: €/Uni | R25: 251 | S25: 251 | V25: 0 | W25: 0 | X25: =IFERROR(ROUNDUP((Q33/J33)/0.5,0)*0.5,0) | Y25: 0 | Z25: =IF(J33=0,J33*K33,J33*K33) | AA25: 1 | AB25: =$N$46 | AC25: 0 | AD25: =SUM(M33*N33)+M33
A26: PRESUPUESTO | B26: 34 | C26: 26 | D26: MURO - PUERTA | E26: muro | F26: muro_puerta_melamina_puerta_melamina_a_medida_maneta_normal | G26: Muro | H26: Puerta | I26: Melamina | J26: Puerta Melamina a Medida + Maneta Normal | K26: *New | P26: UDS | Q26: €/Uni | R26: 227 | S26: 227 | V26: 0 | W26: 0 | X26: =IFERROR(ROUNDUP((Q34/J34)/0.5,0)*0.5,0) | Y26: 0 | Z26: =IF(J34=0,J34*K34,J34*K34) | AA26: 1 | AB26: =$N$46 | AC26: 0 | AD26: =SUM(M34*N34)+M34
A27: PRESUPUESTO | B27: 35 | C27: 26 | D27: MURO - PUERTA | E27: muro | F27: muro_puerta_cristal_alquiler_puerta_2_68m_con_tarja_alquiler | G27: Muro | H27: Puerta | I27: Cristal Alquiler | J27: Puerta (2,68m con Tarja) Alquiler | P27: UDS | Q27: €/Uni | R27: 209 | S27: 209 | V27: 0 | W27: 0 | X27: =IFERROR(ROUNDUP((Q35/J35)/0.5,0)*0.5,0) | Y27: 0 | Z27: =IF(J35=0,J35*K35,J35*K35) | AA27: 1 | AB27: =$N$46 | AC27: 0 | AD27: =SUM(M35*N35)+M35
A28: PRESUPUESTO | B28: 37 | C28: 36 | D28: MURO - CRISTALES | E28: muro | F28: muro_paredes_cristal_semimuro_compra | G28: Muro | H28: Paredes | I28: Cristal | J28: Semimuro Compra | L28: Largo | M28: Altura | O28: m2 | P28: UDS | Q28: €/m2 | R28: 70 | S28: 70 | T28: 0 | U28: =F37*G37 | V28: 0 | W28: 0 | X28: =IFERROR(ROUNDUP((Q37/I37)/0.5,0)*0.5,0) | Y28: 0 | Z28: =IF(I37=0,J37*K37,I37*J37*K37) | AA28: 1 | AB28: =$N$46 | AC28: 0 | AD28: =SUM(M37*N37)+M37
A29: PRESUPUESTO | B29: 38 | C29: 36 | D29: MURO - CRISTALES | E29: muro | F29: muro_paredes_cristal_alquiler_pared_2_68m_altura_alquiler | G29: Muro | H29: Paredes | I29: Cristal Alquiler | J29: Pared (2,68m Altura) Alquiler | L29: Largo | M29: Altura | O29: m2 | P29: UDS | Q29: €/m2 | R29: 25 | S29: 25 | T29: 0 | U29: =F38*G38 | V29: 0 | W29: 0 | X29: =IFERROR(ROUNDUP((Q38/I38)/0.5,0)*0.5,0) | Y29: 0 | Z29: =IF(I38=0,J38*K38,I38*J38*K38) | AA29: 1 | AB29: =$N$46 | AC29: 0 | AD29: =SUM(M38*N38)+M38
A30: PRESUPUESTO | B30: 40 | C30: 39 | D30: MURO - CURVAS / REGATA LED / AISLANTE MURO | E30: muro | F30: muro_curvas_chopo_para_pintar_chopo_5mm_a_1_caras_minimo_1m2_por_tira | G30: Muro | H30: Curvas | I30: Chopo | J30: Para Pintar Chopo 5mm a 1 caras (Minimo 1m2 por tira) | L30: Ancho | M30: Fondo | N30: Altura | O30: ml / m2 | P30: UDS | Q30: €/ml m2 | R30: 44 | S30: 44 | T30: 0 | U30: =F40*G40 | V30: 0 | W30: 0 | X30: =IFERROR(ROUNDUP((Q40/I40)/0.5,0)*0.5,0) | Y30: 0 | Z30: =IF(I40=0,J40*K40,I40*J40*K40) | AA30: 1 | AB30: =$N$126 | AC30: 0 | AD30: =SUM(M40*N40)+M40
A31: PRESUPUESTO | B31: 41 | C31: 39 | D31: MURO - CURVAS / REGATA LED / AISLANTE MURO | E31: muro | F31: muro_curvas_chopo_para_pintar_chopo_5mm_a_2_caras_minimo_1m2_por_tira | G31: Muro | H31: Curvas | I31: Chopo | J31: Para Pintar Chopo 5mm a 2 caras (Minimo 1m2 por tira) | L31: Ancho | M31: Fondo | N31: Altura | O31: ml / m2 | P31: UDS | Q31: €/ml m2 | R31: 58 | S31: 58 | T31: 0 | U31: =F41*G41 | V31: 0 | W31: 0 | X31: =IFERROR(ROUNDUP((Q41/I41)/0.5,0)*0.5,0) | Y31: 0 | Z31: =IF(I41=0,J41*K41,I41*J41*K41) | AA31: 1 | AB31: =$N$126 | AC31: 0 | AD31: =SUM(M41*N41)+M41
A32: PRESUPUESTO | B32: 42 | C32: 39 | D32: MURO - CURVAS / REGATA LED / AISLANTE MURO | E32: muro | F32: muro_tapetas_mdf_5mm_minimo_1m2_por_tira | G32: Muro | H32: Tapetas | I32: MDF | J32: 5mm (Minimo 1m2 por tira) | L32: Ancho | M32: Fondo | N32: Altura | O32: ml / m2 | P32: UDS | Q32: €/ml m2 | R32: 5 | S32: 5 | T32: 0 | U32: =F42*G42 | V32: 0 | W32: 0 | X32: =IFERROR(ROUNDUP((Q42/I42)/0.5,0)*0.5,0) | Y32: 0 | Z32: =IF(I42=0,J42*K42,I42*J42*K42) | AA32: 1 | AB32: =$N$64 | AC32: 0 | AD32: =SUM(M42*N42)+M42
A33: PRESUPUESTO | B33: 43 | C33: 39 | D33: MURO - CURVAS / REGATA LED / AISLANTE MURO | E33: muro | F33: muro_proceso_regata_regata_led_recta | G33: Muro | H33: Proceso | I33: Regata | J33: Regata Led Recta | L33: Ancho | M33: Fondo | N33: Altura | O33: ml / m2 | P33: UDS | Q33: €/ml m2 | R33: 5 | S33: 5 | T33: 0 | V33: 0 | W33: 0 | X33: =IFERROR(ROUNDUP((Q43/I43)/0.5,0)*0.5,0) | Y33: 0 | Z33: =IF(I43=0,J43*K43,I43*J43*K43) | AA33: 1 | AB33: =$N$14 | AC33: 0 | AD33: =SUM(M43*N43)+M43
A34: PRESUPUESTO | B34: 44 | C34: 39 | D34: MURO - CURVAS / REGATA LED / AISLANTE MURO | E34: muro | F34: muro_proceso_regata_regata_led_diagonal_o_curva | G34: Muro | H34: Proceso | I34: Regata | J34: Regata Led Diagonal o Curva | L34: Ancho | M34: Fondo | N34: Altura | O34: ml / m2 | P34: UDS | Q34: €/ml m2 | R34: 10 | S34: 10 | T34: 0 | V34: 0 | W34: 0 | X34: =IFERROR(ROUNDUP((Q44/I44)/0.5,0)*0.5,0) | Y34: 0 | Z34: =IF(I44=0,J44*K44,I44*J44*K44) | AA34: 1 | AB34: =$N$14 | AC34: 0 | AD34: =SUM(M44*N44)+M44
A35: PRESUPUESTO | B35: 45 | C35: 39 | D35: MURO - CURVAS / REGATA LED / AISLANTE MURO | E35: muro | F35: muro_aislante_lana_roca_panel_acustico | G35: Muro | H35: Aislante | I35: Lana Roca | J35: Panel acustico | L35: Ancho | M35: Fondo | N35: Altura | O35: ml / m2 | P35: UDS | Q35: €/ml m2 | R35: 3 | S35: 3 | T35: 0 | U35: =F45*G45 | V35: 0 | W35: 0 | X35: =IFERROR(ROUNDUP((Q45/I45)/0.5,0)*0.5,0) | Y35: 0 | Z35: =IF(I45=0,J45*K45,I45*J45*K45) | AA35: 1 | AB35: =$N$46 | AC35: 0 | AD35: =SUM(M45*N45)+M45
A36: PRESUPUESTO | B36: 48 | C36: 47 | D36: BANNER | E36: banner | F36: banner_banner_chopo_banner_1_cara_chopo_5mm_estructura_pino_grosor_estandar_0_05m | G36: Banner | H36: Banner | I36: Chopo | J36: Banner 1 cara Chopo 5mm + Estructura Pino (Grosor Estandar 0,05m) | L36: Largo | M36: Altura | N36: Grosor | O36: m2 | P36: UDS | Q36: €/m2 | R36: 23 | S36: 23 | T36: 0 | U36: =F48*G48 | V36: 0 | W36: 0 | X36: =IFERROR(ROUNDUP((Q48/I48)/0.5,0)*0.5,0) | Y36: 0 | Z36: =IF(I48=0,J48*K48,I48*J48*K48) | AA36: 1 | AB36: =$N$54 | AC36: 0 | AD36: =SUM(M48*N48)+M48
A37: PRESUPUESTO | B37: 49 | C37: 47 | D37: BANNER | E37: banner | F37: banner_banner_chopo_banner_2_caras_chopo_5mm_estructura_pino_grosor_estandar_0_055m | G37: Banner | H37: Banner | I37: Chopo | J37: Banner 2 caras Chopo 5mm + Estructura Pino (Grosor Estandar 0,055m) | L37: Largo | M37: Altura | N37: Grosor | O37: m2 | P37: UDS | Q37: €/m2 | R37: 37 | S37: 37 | T37: 0 | U37: =F49*G49 | V37: 0 | W37: 0 | X37: =IFERROR(ROUNDUP((Q49/I49)/0.5,0)*0.5,0) | Y37: 0 | Z37: =IF(I49=0,J49*K49,I49*J49*K49) | AA37: 1 | AB37: =$N$54 | AC37: 0 | AD37: =SUM(M49*N49)+M49
A38: PRESUPUESTO | B38: 50 | C38: 47 | D38: BANNER | E38: banner | F38: banner_banner_chopo_banner_2_caras_chopo_5mm_estructura_pino_grosor_0_055mm | G38: Banner | H38: Banner | I38: Chopo | J38: Banner 2 caras Chopo 5mm + Estructura Pino (Grosor <0,055mm) | L38: Largo | M38: Altura | N38: Grosor | O38: m2 | P38: UDS | Q38: €/m2 | R38: 37 | S38: 37 | T38: 0 | U38: =F50*G50 | V38: 0 | W38: 0 | X38: =IFERROR(ROUNDUP((Q50/I50)/0.5,0)*0.5,0) | Y38: 0 | Z38: =IF(I50=0,J50*K50,I50*J50*K50) | AA38: 1 | AB38: =$N$54 | AC38: 0 | AD38: =SUM(M50*N50)+M50
A39: PRESUPUESTO | B39: 52 | C39: 51 | D39: BANNER - CURVAS / REGATA LED / AISLANTE MURO | E39: banner | F39: banner_curvas_chopo_para_pintar_chopo_5mm_a_1_caras_minimo_1m2_por_tira | G39: Banner | H39: Curvas | I39: Chopo | J39: Para Pintar Chopo 5mm a 1 caras (Minimo 1m2 por tira) | L39: Ancho | M39: Fondo | N39: Altura | O39: m2 | P39: UDS | Q39: €/Um2 | R39: 44 | S39: 44 | T39: 0 | U39: =F52*G52 | V39: 0 | W39: 0 | X39: =IFERROR(ROUNDUP((Q52/I52)/0.5,0)*0.5,0) | Y39: 0 | Z39: =IF(I52=0,J52*K52,I52*J52*K52) | AA39: 1 | AB39: =$N$126 | AC39: 0 | AD39: =SUM(M52*N52)+M52
A40: PRESUPUESTO | B40: 53 | C40: 51 | D40: BANNER - CURVAS / REGATA LED / AISLANTE MURO | E40: banner | F40: banner_curvas_chopo_para_pintar_chopo_5mm_a_2_caras_minimo_1m2_por_tira | G40: Banner | H40: Curvas | I40: Chopo | J40: Para Pintar Chopo 5mm a 2 caras (Minimo 1m2 por tira) | L40: Ancho | M40: Fondo | N40: Altura | O40: m2 | P40: UDS | Q40: €/Um2 | R40: 58 | S40: 58 | T40: 0 | U40: =F53*G53 | V40: 0 | W40: 0 | X40: =IFERROR(ROUNDUP((Q53/I53)/0.5,0)*0.5,0) | Y40: 0 | Z40: =IF(I53=0,J53*K53,I53*J53*K53) | AA40: 1 | AB40: =$N$126 | AC40: 0 | AD40: =SUM(M53*N53)+M53
A41: PRESUPUESTO | B41: 56 | C41: 55 | D41: VIGA | E41: viga | F41: viga_viga_aglomerado_viga_en_u_estandar_0_15m | G41: Viga | H41: Viga | I41: Aglomerado | J41: Viga en U (Estandar 0,15m) | L41: Largo | M41: Ancho | N41: Alto | O41: m2 | P41: UDS | Q41: €/m2 | R41: 110 | S41: 110 | T41: 0 | U41: =(F56*G56)+((F56*H56)*2) | V41: 0 | W41: 0 | X41: =IFERROR(ROUNDUP((Q56/I56)/0.5,0)*0.5,0) | Y41: 0 | Z41: =IF(I56=0,J56*K56,I56*J56*K56) | AA41: 1 | AB41: =$N$69 | AC41: 0 | AD41: =SUM(M56*N56)+M56
A42: PRESUPUESTO | B42: 57 | C42: 55 | D42: VIGA | E42: viga | F42: viga_viga_melamina_viga_en_u_estandar_0_15m | G42: Viga | H42: Viga | I42: Melamina | J42: Viga en U (Estandar 0,15m) | L42: Largo | M42: Ancho | N42: Alto | O42: m2 | P42: UDS | Q42: €/m2 | R42: 145 | S42: 145 | T42: 0 | U42: =(F57*G57)+((F57*H57)*2) | V42: 0 | W42: 0 | X42: =IFERROR(ROUNDUP((Q57/I57)/0.5,0)*0.5,0) | Y42: 0 | Z42: =IF(I57=0,J57*K57,I57*J57*K57) | AA42: 1 | AB42: =$N$69 | AC42: 0 | AD42: =SUM(M57*N57)+M57
A43: PRESUPUESTO | B43: 58 | C43: 55 | D43: VIGA | E43: viga | F43: viga_viga_mel_especial_chopo_viga_en_u_estandar_0_15m | G43: Viga | H43: Viga | I43: Mel. Especial / Chopo | J43: Viga en U (Estandar 0,15m) | L43: Largo | M43: Ancho | N43: Alto | O43: m2 | P43: UDS | Q43: €/m2 | R43: 150 | S43: 150 | T43: 0 | U43: =(F58*G58)+((F58*H58)*2) | V43: 0 | W43: 0 | X43: =IFERROR(ROUNDUP((Q58/I58)/0.5,0)*0.5,0) | Y43: 0 | Z43: =IF(I58=0,J58*K58,I58*J58*K58) | AA43: 1 | AB43: =$N$69 | AC43: 0 | AD43: =SUM(M58*N58)+M58
A44: PRESUPUESTO | B44: 61 | C44: 60 | D44: PILAR | E44: pilar | F44: pilar_pilar_aglomerado_pilar_estandar_0_15m | G44: Pilar | H44: Pilar | I44: Aglomerado | J44: Pilar (Estandar 0,15m) | L44: Largo | M44: Ancho | N44: Alto | O44: m2 | P44: UDS | Q44: €/m2 | R44: 110 | S44: 110 | T44: 0 | U44: =((F61*G61)*2)+((F61*H61)*2) | V44: 0 | W44: 0 | X44: =IFERROR(ROUNDUP((Q61/I61)/0.5,0)*0.5,0) | Y44: 0 | Z44: =IF(I61=0,J61*K61,I61*J61*K61) | AA44: 1 | AB44: =$N$69 | AC44: 0 | AD44: =SUM(M61*N61)+M61
A45: PRESUPUESTO | B45: 62 | C45: 60 | D45: PILAR | E45: pilar | F45: pilar_pilar_melamina_pilar_estandar_0_15m | G45: Pilar | H45: Pilar | I45: Melamina | J45: Pilar (Estandar 0,15m) | L45: Largo | M45: Ancho | N45: Alto | O45: m2 | P45: UDS | Q45: €/m2 | R45: 130 | S45: 130 | T45: 0 | U45: =((F62*G62)*2)+((F62*H62)*2) | V45: 0 | W45: 0 | X45: =IFERROR(ROUNDUP((Q62/I62)/0.5,0)*0.5,0) | Y45: 0 | Z45: =IF(I62=0,J62*K62,I62*J62*K62) | AA45: 1 | AB45: =$N$69 | AC45: 0 | AD45: =SUM(M62*N62)+M62
A46: PRESUPUESTO | B46: 63 | C46: 60 | D46: PILAR | E46: pilar | F46: pilar_pilar_mel_especial_chopo_pilar_estandar_0_15m | G46: Pilar | H46: Pilar | I46: Mel. Especial / Chopo | J46: Pilar (Estandar 0,15m) | L46: Largo | M46: Ancho | N46: Alto | O46: m2 | P46: UDS | Q46: €/m2 | R46: 150 | S46: 150 | T46: 0 | U46: =((F63*G63)*2)+((F63*H63)*2) | V46: 0 | W46: 0 | X46: =IFERROR(ROUNDUP((Q63/I63)/0.5,0)*0.5,0) | Y46: 0 | Z46: =IF(I63=0,J63*K63,I63*J63*K63) | AA46: 1 | AB46: =$N$69 | AC46: 0 | AD46: =SUM(M63*N63)+M63
A47: PRESUPUESTO | B47: 66 | C47: 65 | D47: PODIUM | E47: podium | F47: podium_podium_aglomerado_podium | G47: Podium | H47: Podium | I47: Aglomerado | J47: Podium | K47: *Lo paso a m3 el precio | L47: Largo | M47: Ancho | N47: Alto | O47: m3 | P47: UDS | Q47: €/m3 | R47: 220 | S47: 220 | T47: 0 | U47: =F66*G66*H66 | V47: 0 | W47: 0 | X47: =IFERROR(ROUNDUP((Q66/I66)/0.5,0)*0.5,0) | Y47: 0 | Z47: =IF(I66=0,J66*K66,I66*J66*K66) | AA47: 1 | AB47: =$N$69 | AC47: 0 | AD47: =SUM(M66*N66)+M66
A48: PRESUPUESTO | B48: 67 | C48: 65 | D48: PODIUM | E48: podium | F48: podium_podium_melamina_podium | G48: Podium | H48: Podium | I48: Melamina | J48: Podium | K48: *Lo paso a m3 el precio | L48: Largo | M48: Ancho | N48: Alto | O48: m3 | P48: UDS | Q48: €/m3 | R48: 250 | S48: 250 | T48: 0 | U48: =F67*G67*H67 | V48: 0 | W48: 0 | X48: =IFERROR(ROUNDUP((Q67/I67)/0.5,0)*0.5,0) | Y48: 0 | Z48: =IF(I67=0,J67*K67,I67*J67*K67) | AA48: 1 | AB48: =$N$69 | AC48: 0 | AD48: =SUM(M67*N67)+M67
A49: PRESUPUESTO | B49: 68 | C49: 65 | D49: PODIUM | E49: podium | F49: podium_podium_mel_especial_chopo_podium | G49: Podium | H49: Podium | I49: Mel. Especial / Chopo | J49: Podium | K49: *Lo paso a m3 el precio | L49: Largo | M49: Ancho | N49: Alto | O49: m3 | P49: UDS | Q49: €/m3 | R49: 300 | S49: 300 | T49: 0 | U49: =F68*G68*H68 | V49: 0 | W49: 0 | X49: =IFERROR(ROUNDUP((Q68/I68)/0.5,0)*0.5,0) | Y49: 0 | Z49: =IF(I68=0,J68*K68,I68*J68*K68) | AA49: 1 | AB49: =$N$69 | AC49: 0 | AD49: =SUM(M68*N68)+M68
A50: PRESUPUESTO | B50: 71 | C50: 70 | D50: TECHOS | E50: techos | F50: techos_techos_chopo_pino_techo_bastidor_pino_chopo_5mm | G50: Techos | H50: Techos | I50: Chopo + Pino | J50: Techo Bastidor pino Chopo 5mm | L50: Largo | M50: Ancho | N50: Alto | O50: m2 | P50: UDS | Q50: €/m3 | R50: 28 | S50: 28 | T50: 0 | U50: =F71*G71 | V50: 0 | W50: 0 | X50: =IFERROR(ROUNDUP((Q71/I71)/0.5,0)*0.5,0) | Y50: 0 | Z50: =IF(I71=0,J71*K71,I71*J71*K71) | AA50: 1 | AB50: =$N$74 | AC50: 0 | AD50: =SUM(M71*N71)+M71
A51: PRESUPUESTO | B51: 72 | C51: 70 | D51: TECHOS | E51: techos | F51: techos_techos_chopo_chopo_de_15mm_chopo_de_5mm | G51: Techos | H51: Techos | I51: Chopo | J51: Chopo de 15mm + Chopo de 5mm | L51: Largo | M51: Ancho | N51: Alto | O51: m2 | P51: UDS | Q51: €/m3 | R51: 25 | S51: 25 | T51: 0 | U51: =F72*G72 | V51: 0 | W51: 0 | X51: =IFERROR(ROUNDUP((Q72/I72)/0.5,0)*0.5,0) | Y51: 0 | Z51: =IF(I72=0,J72*K72,I72*J72*K72) | AA51: 1 | AB51: =$N$74 | AC51: 0 | AD51: =SUM(M72*N72)+M72
A52: PRESUPUESTO | B52: 73 | C52: 70 | D52: TECHOS | E52: techos | F52: techos_aislante_lana_roca_panel_acustico | G52: Techos | H52: Aislante | I52: Lana Roca | J52: Panel acustico | L52: Largo | M52: Ancho | N52: Alto | O52: m2 | P52: UDS | Q52: €/m3 | R52: 3 | S52: 3 | T52: 0 | U52: =F73*G73 | V52: 0 | W52: 0 | X52: =IFERROR(ROUNDUP((Q73/I73)/0.5,0)*0.5,0) | Y52: 0 | Z52: =IF(I73=0,J73*K73,I73*J73*K73) | AA52: 1 | AB52: =$N$46 | AC52: 0 | AD52: =SUM(M73*N73)+M73
A53: PRESUPUESTO | B53: 76 | C53: 75 | D53: BACKLIGHTS | E53: backlights | F53: backlights_backlights_chopo_pino_aglo_backlights_bastidor_pino_lateral_chopo10mm_trasera_aglo_16mm_g_estandar_0_3m | G53: Backlights | H53: Backlights | I53: Chopo + Pino + Aglo. | J53: Backlights: Bastidor Pino+Lateral Chopo10mm+Trasera Aglo.16mm (G. Estandar 0,3m) | L53: Largo | M53: Altura | N53: Grosor | O53: m2 | P53: UDS | Q53: €/m2 | R53: 220 | S53: 220 | T53: 0 | U53: =F76*G76 | V53: 0 | W53: 0 | X53: =IFERROR(ROUNDUP((Q76/I76)/0.5,0)*0.5,0) | Y53: 0 | Z53: =IF(I76=0,J76*K76,I76*J76*K76) | AA53: 1 | AB53: =$N$78 | AC53: 0 | AD53: =SUM(M76*N76)+M76
A54: PRESUPUESTO | B54: 77 | C54: 75 | D54: BACKLIGHTS | E54: backlights | F54: backlights_backlights_chopo_pino_backlights_elevado_bastidor_pino_lateral_y_trasera_chopo_10mm_g_estandar_0_3m | G54: Backlights | H54: Backlights | I54: Chopo + Pino | J54: Backlights Elevado: Bastidor Pino + Lateral y trasera Chopo 10mm (G. Estandar 0,3m) | L54: Largo | M54: Altura | N54: Grosor | O54: m2 | P54: UDS | Q54: €/m2 | R54: 220 | S54: 220 | T54: 0 | U54: =F77*G77 | V54: 0 | W54: 0 | X54: =IFERROR(ROUNDUP((Q77/I77)/0.5,0)*0.5,0) | Y54: 0 | Z54: =IF(I77=0,J77*K77,I77*J77*K77) | AA54: 1 | AB54: =$N$78 | AC54: 0 | AD54: =SUM(M77*N77)+M77
A55: PRESUPUESTO | B55: 80 | C55: 79 | D55: LISTONES | E55: liston | F55: liston_liston_pino_liston_flandes_45_45 | G55: Liston | H55: Liston | I55: Pino | J55: Liston Flandes 45*45 | L55: Largo | M55: Altura | N55: Grosor | O55: ml | P55: UDS | Q55: €/ml | R55: 1.5075 | S55: 1.5075 | T55: 0 | V55: 0 | W55: 0 | X55: =IFERROR(ROUNDUP((Q80/I80)/0.5,0)*0.5,0) | Y55: 0 | Z55: =IF(I80=0,J80*K80,I80*J80*K80) | AA55: 1 | AB55: =$N$87 | AC55: 0 | AD55: =SUM(M80*N80)+M80
A56: PRESUPUESTO | B56: 81 | C56: 79 | D56: LISTONES | E56: liston | F56: liston_liston_pino_liston_flandes_45_70 | G56: Liston | H56: Liston | I56: Pino | J56: Liston Flandes 45*70 | L56: Largo | M56: Altura | N56: Grosor | O56: ml | P56: UDS | Q56: €/ml | R56: 1.8 | S56: 1.8 | T56: 0 | V56: 0 | W56: 0 | X56: =IFERROR(ROUNDUP((Q81/I81)/0.5,0)*0.5,0) | Y56: 0 | Z56: =IF(I81=0,J81*K81,I81*J81*K81) | AA56: 1 | AB56: =$N$87 | AC56: 0 | AD56: =SUM(M81*N81)+M81
A57: PRESUPUESTO | B57: 82 | C57: 79 | D57: LISTONES | E57: liston | F57: liston_liston_abeto_liston_abeto_120_60 | G57: Liston | H57: Liston | I57: Abeto | J57: Liston Abeto 120*60 | L57: Largo | M57: Altura | N57: Grosor | O57: ml | P57: UDS | Q57: €/ml | R57: 11.5 | S57: 11.5 | T57: 0 | V57: 0 | W57: 0 | X57: =IFERROR(ROUNDUP((Q82/I82)/0.5,0)*0.5,0) | Y57: 0 | Z57: =IF(I82=0,J82*K82,I82*J82*K82) | AA57: 1 | AB57: =$N$87 | AC57: 0 | AD57: =SUM(M82*N82)+M82
A58: PRESUPUESTO | B58: 83 | C58: 79 | D58: LISTONES | E58: liston | F58: liston_liston_abeto_liston_abeto_120_120 | G58: Liston | H58: Liston | I58: Abeto | J58: Liston Abeto 120*120 | L58: Largo | M58: Altura | N58: Grosor | O58: ml | P58: UDS | Q58: €/ml | R58: 82 | S58: 82 | T58: 0 | V58: 0 | W58: 0 | X58: =IFERROR(ROUNDUP((Q83/I83)/0.5,0)*0.5,0) | Y58: 0 | Z58: =IF(I83=0,J83*K83,I83*J83*K83) | AA58: 1 | AB58: =$N$87 | AC58: 0 | AD58: =SUM(M83*N83)+M83
A59: PRESUPUESTO | B59: 84 | C59: 79 | D59: LISTONES | E59: perfil | F59: perfil_perfil_aluminio_pletina_20_3_negro_brillante | G59: Perfil | H59: Perfil | I59: Aluminio | J59: Pletina 20*3 Negro Brillante | K59: *New | L59: Largo | M59: Altura | N59: Grosor | O59: ml | P59: UDS | Q59: €/ml | R59: 5 | S59: 5 | T59: 0 | V59: 0 | W59: 0 | X59: =IFERROR(ROUNDUP((Q84/I84)/0.5,0)*0.5,0) | Y59: 0 | Z59: =IF(I84=0,J84*K84,I84*J84*K84) | AA59: 1 | AB59: =$N$87 | AC59: 0 | AD59: =SUM(M84*N84)+M84
A60: PRESUPUESTO | B60: 85 | C60: 79 | D60: LISTONES | E60: perfil | F60: perfil_perfil_aluminio_para_textiles_silicona | G60: Perfil | H60: Perfil | I60: Aluminio | J60: Para Textiles Silicona | L60: Largo | M60: Altura | N60: Grosor | O60: ml | P60: UDS | Q60: €/ml | R60: 5 | S60: 5 | T60: 0 | V60: 0 | W60: 0 | X60: =IFERROR(ROUNDUP((Q85/I85)/0.5,0)*0.5,0) | Y60: 0 | Z60: =IF(I85=0,J85*K85,I85*J85*K85) | AA60: 1 | AB60: =$N$87 | AC60: 0 | AD60: =SUM(M85*N85)+M85
A61: PRESUPUESTO | B61: 86 | C61: 79 | D61: LISTONES | E61: perfil | F61: perfil_perfil_aluminio_perfil_en_u_aluminio | G61: Perfil | H61: Perfil | I61: Aluminio | J61: Perfil en U aluminio | L61: Largo | M61: Altura | N61: Grosor | O61: ml | P61: UDS | Q61: €/ml | R61: 5.77 | S61: 5.77 | T61: 0 | V61: 0 | W61: 0 | X61: =IFERROR(ROUNDUP((Q86/I86)/0.5,0)*0.5,0) | Y61: 0 | Z61: =IF(I86=0,J86*K86,I86*J86*K86) | AA61: 1 | AB61: =$N$87 | AC61: 0 | AD61: =SUM(M86*N86)+M86
A62: PRESUPUESTO | B62: 89 | C62: 88 | D62: MOSTRADOR | E62: mostrador | F62: mostrador_recto_aglomerado_con_puertas | G62: Mostrador | H62: Recto | I62: Aglomerado | J62: Con Puertas | L62: Largo | M62: Ancho | N62: Alto | O62: m3 | P62: UDS | Q62: €/ml | R62: 102.62509 | S62: 102.62509 | T62: 0 | U62: =F89*G89*H89 | V62: 0 | W62: 0 | X62: =IFERROR(ROUNDUP((Q89/I89)/0.5,0)*0.5,0) | Y62: 0 | Z62: =IF(I89=0,J89*K89,I89*J89*K89) | AA62: 1 | AB62: =$N$111 | AC62: 0 | AD62: =SUM(M89*N89)+M89
A63: PRESUPUESTO | B63: 90 | C63: 88 | D63: MOSTRADOR | E63: mostrador | F63: mostrador_recto_aglomerado_abierto | G63: Mostrador | H63: Recto | I63: Aglomerado | J63: Abierto | L63: Largo | M63: Ancho | N63: Alto | O63: m3 | P63: UDS | Q63: €/ml | R63: 82.085088 | S63: 82.085088 | T63: 0 | U63: =F90*G90*H90 | V63: 0 | W63: 0 | X63: =IFERROR(ROUNDUP((Q90/I90)/0.5,0)*0.5,0) | Y63: 0 | Z63: =IF(I90=0,J90*K90,I90*J90*K90) | AA63: 1 | AB63: =$N$111 | AC63: 0 | AD63: =SUM(M90*N90)+M90
A64: PRESUPUESTO | B64: 91 | C64: 88 | D64: MOSTRADOR | E64: mostrador | F64: mostrador_recto_lacado_con_puertas | G64: Mostrador | H64: Recto | I64: Lacado | J64: Con Puertas | K64: *New | L64: Largo | M64: Ancho | N64: Alto | O64: m3 | P64: UDS | Q64: €/ml | R64: 660 | S64: 660 | T64: 0 | U64: =F91*G91*H91 | V64: 0 | W64: 0 | X64: =IFERROR(ROUNDUP((Q91/I91)/0.5,0)*0.5,0) | Y64: 0 | Z64: =IF(I91=0,J91*K91,I91*J91*K91) | AA64: 1 | AB64: =$N$111 | AC64: 0 | AD64: =SUM(M91*N91)+M91
A65: PRESUPUESTO | B65: 92 | C65: 88 | D65: MOSTRADOR | E65: mostrador | F65: mostrador_recto_lacado_abierto | G65: Mostrador | H65: Recto | I65: Lacado | J65: Abierto | K65: *New | L65: Largo | M65: Ancho | N65: Alto | O65: m3 | P65: UDS | Q65: €/ml | R65: 540 | S65: 540 | T65: 0 | U65: =F92*G92*H92 | V65: 0 | W65: 0 | X65: =IFERROR(ROUNDUP((Q92/I92)/0.5,0)*0.5,0) | Y65: 0 | Z65: =IF(I92=0,J92*K92,I92*J92*K92) | AA65: 1 | AB65: =$N$111 | AC65: 0 | AD65: =SUM(M92*N92)+M92
A66: PRESUPUESTO | B66: 93 | C66: 88 | D66: MOSTRADOR | E66: mostrador | F66: mostrador_recto_melamina_blanca_negra_con_puertas | G66: Mostrador | H66: Recto | I66: Melamina Blanca / Negra | J66: Con Puertas | L66: Largo | M66: Ancho | N66: Alto | O66: m3 | P66: UDS | Q66: €/ml | R66: 158.1393 | S66: 158.1393 | T66: 0 | U66: =F93*G93*H93 | V66: 0 | W66: 0 | X66: =IFERROR(ROUNDUP((Q93/I93)/0.5,0)*0.5,0) | Y66: 0 | Z66: =IF(I93=0,J93*K93,I93*J93*K93) | AA66: 1 | AB66: =$N$111 | AC66: 0 | AD66: =SUM(M93*N93)+M93
A67: PRESUPUESTO | B67: 94 | C67: 88 | D67: MOSTRADOR | E67: mostrador | F67: mostrador_recto_melamina_blanca_negra_abierto | G67: Mostrador | H67: Recto | I67: Melamina Blanca / Negra | J67: Abierto | L67: Largo | M67: Ancho | N67: Alto | O67: m3 | P67: UDS | Q67: €/ml | R67: 137.5993 | S67: 137.5993 | T67: 0 | U67: =F94*G94*H94 | V67: 0 | W67: 0 | X67: =IFERROR(ROUNDUP((Q94/I94)/0.5,0)*0.5,0) | Y67: 0 | Z67: =IF(I94=0,J94*K94,I94*J94*K94) | AA67: 1 | AB67: =$N$111 | AC67: 0 | AD67: =SUM(M94*N94)+M94
A68: PRESUPUESTO | B68: 95 | C68: 88 | D68: MOSTRADOR | E68: mostrador | F68: mostrador_recto_melamina_color_con_puertas | G68: Mostrador | H68: Recto | I68: Melamina Color | J68: Con Puertas | K68: *New | L68: Largo | M68: Ancho | N68: Alto | O68: m3 | P68: UDS | Q68: €/ml | R68: 290 | S68: 290 | T68: 0 | U68: =F95*G95*H95 | V68: 0 | W68: 0 | X68: =IFERROR(ROUNDUP((Q95/I95)/0.5,0)*0.5,0) | Y68: 0 | Z68: =IF(I95=0,J95*K95,I95*J95*K95) | AA68: 1 | AB68: =$N$111 | AC68: 0 | AD68: =SUM(M95*N95)+M95
A69: PRESUPUESTO | B69: 96 | C69: 88 | D69: MOSTRADOR | E69: mostrador | F69: mostrador_recto_melamina_color_abierto | G69: Mostrador | H69: Recto | I69: Melamina Color | J69: Abierto | K69: *New | L69: Largo | M69: Ancho | N69: Alto | O69: m3 | P69: UDS | Q69: €/ml | R69: 260 | S69: 260 | T69: 0 | U69: =F96*G96*H96 | V69: 0 | W69: 0 | X69: =IFERROR(ROUNDUP((Q96/I96)/0.5,0)*0.5,0) | Y69: 0 | Z69: =IF(I96=0,J96*K96,I96*J96*K96) | AA69: 1 | AB69: =$N$111 | AC69: 0 | AD69: =SUM(M96*N96)+M96
A70: PRESUPUESTO | B70: 97 | C70: 88 | D70: MOSTRADOR | E70: mostrador | F70: mostrador_curvo_aglomerado_con_puertas | G70: Mostrador | H70: Curvo | I70: Aglomerado | J70: Con Puertas | L70: Largo | M70: Ancho | N70: Alto | O70: m3 | P70: UDS | Q70: €/ml | R70: 216.57433 | S70: 216.57433 | T70: 0 | U70: =F97*G97*H97 | V70: 0 | W70: 0 | X70: =IFERROR(ROUNDUP((Q97/I97)/0.5,0)*0.5,0) | Y70: 0 | Z70: =IF(I97=0,J97*K97,I97*J97*K97) | AA70: 1 | AB70: =$N$111 | AC70: 0 | AD70: =SUM(M97*N97)+M97
A71: PRESUPUESTO | B71: 98 | C71: 88 | D71: MOSTRADOR | E71: mostrador | F71: mostrador_curvo_aglomerado_abierto | G71: Mostrador | H71: Curvo | I71: Aglomerado | J71: Abierto | L71: Largo | M71: Ancho | N71: Alto | O71: m3 | P71: UDS | Q71: €/ml | R71: 167.47903 | S71: 167.47903 | T71: 0 | U71: =F98*G98*H98 | V71: 0 | W71: 0 | X71: =IFERROR(ROUNDUP((Q98/I98)/0.5,0)*0.5,0) | Y71: 0 | Z71: =IF(I98=0,J98*K98,I98*J98*K98) | AA71: 1 | AB71: =$N$111 | AC71: 0 | AD71: =SUM(M98*N98)+M98
A72: PRESUPUESTO | B72: 99 | C72: 88 | D72: MOSTRADOR | E72: mostrador | F72: mostrador_curvo_lacado_con_puertas | G72: Mostrador | H72: Curvo | I72: Lacado | J72: Con Puertas | K72: *New | L72: Largo | M72: Ancho | N72: Alto | O72: m3 | P72: UDS | Q72: €/ml | R72: 762 | S72: 762 | T72: 0 | U72: =F99*G99*H99 | V72: 0 | W72: 0 | X72: =IFERROR(ROUNDUP((Q99/I99)/0.5,0)*0.5,0) | Y72: 0 | Z72: =IF(I99=0,J99*K99,I99*J99*K99) | AA72: 1 | AB72: =$N$111 | AC72: 0 | AD72: =SUM(M99*N99)+M99
A73: PRESUPUESTO | B73: 100 | C73: 88 | D73: MOSTRADOR | E73: mostrador | F73: mostrador_curvo_lacado_abierto | G73: Mostrador | H73: Curvo | I73: Lacado | J73: Abierto | K73: *New | L73: Largo | M73: Ancho | N73: Alto | O73: m3 | P73: UDS | Q73: €/ml | R73: 630 | S73: 630 | T73: 0 | U73: =F100*G100*H100 | V73: 0 | W73: 0 | X73: =IFERROR(ROUNDUP((Q100/I100)/0.5,0)*0.5,0) | Y73: 0 | Z73: =IF(I100=0,J100*K100,I100*J100*K100) | AA73: 1 | AB73: =$N$111 | AC73: 0 | AD73: =SUM(M100*N100)+M100
A74: PRESUPUESTO | B74: 101 | C74: 88 | D74: MOSTRADOR | E74: mostrador | F74: mostrador_curvo_formica_con_puertas | G74: Mostrador | H74: Curvo | I74: Formica | J74: Con Puertas | L74: Largo | M74: Ancho | N74: Alto | O74: m3 | P74: UDS | Q74: €/ml | R74: 305.67837 | S74: 305.67837 | T74: 0 | U74: =F101*G101*H101 | V74: 0 | W74: 0 | X74: =IFERROR(ROUNDUP((Q101/I101)/0.5,0)*0.5,0) | Y74: 0 | Z74: =IF(I101=0,J101*K101,I101*J101*K101) | AA74: 1 | AB74: =$N$111 | AC74: 0 | AD74: =SUM(M101*N101)+M101
A75: PRESUPUESTO | B75: 102 | C75: 88 | D75: MOSTRADOR | E75: mostrador | F75: mostrador_curvo_formica_abierto | G75: Mostrador | H75: Curvo | I75: Formica | J75: Abierto | L75: Largo | M75: Ancho | N75: Alto | O75: m3 | P75: UDS | Q75: €/ml | R75: 244.85197 | S75: 244.85197 | T75: 0 | U75: =F102*G102*H102 | V75: 0 | W75: 0 | X75: =IFERROR(ROUNDUP((Q102/I102)/0.5,0)*0.5,0) | Y75: 0 | Z75: =IF(I102=0,J102*K102,I102*J102*K102) | AA75: 1 | AB75: =$N$111 | AC75: 0 | AD75: =SUM(M102*N102)+M102
A76: PRESUPUESTO | B76: 104 | C76: 103 | D76: MESA | E76: mesa | F76: mesa_u_aglomerado | G76: Mesa | H76: U | I76: Aglomerado | L76: Largo | M76: Ancho | N76: Alto Falda | O76: m2 | P76: UDS | Q76: €/m2 | R76: 35 | S76: 35 | T76: 0 | U76: =F104*G104 | V76: 0 | W76: 0 | X76: =IFERROR(ROUNDUP((Q104/I104)/0.5,0)*0.5,0) | Y76: 0 | Z76: =IF(I104=0,J104*K104,I104*J104*K104) | AA76: 1 | AB76: =$N$111 | AC76: 0 | AD76: =SUM(M104*N104)+M104
A77: PRESUPUESTO | B77: 105 | C77: 103 | D77: MESA | E77: mesa | F77: mesa_u_melamina | G77: Mesa | H77: U | I77: Melamina | L77: Largo | M77: Ancho | N77: Alto Falda | O77: m2 | P77: UDS | Q77: €/m2 | R77: 50 | S77: 50 | T77: 0 | U77: =F105*G105 | V77: 0 | W77: 0 | X77: =IFERROR(ROUNDUP((Q105/I105)/0.5,0)*0.5,0) | Y77: 0 | Z77: =IF(I105=0,J105*K105,I105*J105*K105) | AA77: 1 | AB77: =$N$111 | AC77: 0 | AD77: =SUM(M105*N105)+M105
A78: PRESUPUESTO | B78: 106 | C78: 103 | D78: MESA | E78: mesa | F78: mesa_u_melamina_especial | G78: Mesa | H78: U | I78: Melamina Especial | L78: Largo | M78: Ancho | N78: Alto Falda | O78: m2 | P78: UDS | Q78: €/m2 | R78: 75 | S78: 75 | T78: 0 | U78: =F106*G106 | V78: 0 | W78: 0 | X78: =IFERROR(ROUNDUP((Q106/I106)/0.5,0)*0.5,0) | Y78: 0 | Z78: =IF(I106=0,J106*K106,I106*J106*K106) | AA78: 1 | AB78: =$N$111 | AC78: 0 | AD78: =SUM(M106*N106)+M106
A79: PRESUPUESTO | B79: 108 | C79: 107 | D79: JARDINERA | E79: jardinera | F79: jardinera_jardinera_aglomerado | G79: Jardinera | H79: Jardinera | I79: Aglomerado | L79: Largo | M79: Ancho | N79: Alto | O79: ml | P79: UDS | Q79: €/ml | R79: 15.01624 | S79: 15.01624 | T79: 0 | U79: =F108 | V79: 0 | W79: 0 | X79: =IFERROR(ROUNDUP((Q108/I108)/0.5,0)*0.5,0) | Y79: 0 | Z79: =IF(I108=0,J108*K108,I108*J108*K108) | AA79: 1 | AB79: =$N$111 | AC79: 0 | AD79: =SUM(M108*N108)+M108
A80: PRESUPUESTO | B80: 109 | C80: 107 | D80: JARDINERA | E80: jardinera | F80: jardinera_jardinera_melamina | G80: Jardinera | H80: Jardinera | I80: Melamina | L80: Largo | M80: Ancho | N80: Alto | O80: ml | P80: UDS | Q80: €/ml | R80: 17.099212 | S80: 17.099212 | T80: 0 | U80: =F109 | V80: 0 | W80: 0 | X80: =IFERROR(ROUNDUP((Q109/I109)/0.5,0)*0.5,0) | Y80: 0 | Z80: =IF(I109=0,J109*K109,I109*J109*K109) | AA80: 1 | AB80: =$N$111 | AC80: 0 | AD80: =SUM(M109*N109)+M109
A81: PRESUPUESTO | B81: 110 | C81: 107 | D81: JARDINERA | E81: jardinera | F81: jardinera_jardinera_melamina_especial | G81: Jardinera | H81: Jardinera | I81: Melamina Especial | L81: Largo | M81: Ancho | N81: Alto | O81: ml | P81: UDS | Q81: €/ml | R81: 19.617967 | S81: 19.617967 | T81: 0 | U81: =F110 | V81: 0 | W81: 0 | X81: =IFERROR(ROUNDUP((Q110/I110)/0.5,0)*0.5,0) | Y81: 0 | Z81: =IF(I110=0,J110*K110,I110*J110*K110) | AA81: 1 | AB81: =$N$111 | AC81: 0 | AD81: =SUM(M110*N110)+M110
A82: PRESUPUESTO | B82: 113 | C82: 112 | D82: PANEL | E82: panel | F82: panel_panel_melamina_blanca_negra_panel_decorativo_estante_lama_16mm | G82: Panel | H82: Panel | I82: Melamina Blanca /Negra | J82: Panel decorativo/ Estante /Lama 16mm | L82: Largo | M82: Ancho | O82: m2 | P82: UDS | Q82: €/m2 | R82: 12 | S82: 12 | T82: 0 | U82: =F113*G113 | V82: 0 | W82: 0 | X82: =IFERROR(ROUNDUP((Q113/I113)/0.5,0)*0.5,0) | Y82: 0 | Z82: =IF(I113=0,J113*K113,I113*J113*K113) | AA82: 1 | AB82: =$N$119 | AC82: 0 | AD82: =SUM(M113*N113)+M113
A83: PRESUPUESTO | B83: 114 | C83: 112 | D83: PANEL | E83: panel | F83: panel_panel_melamina_color_panel_decorativo_estante_lama_16mm | G83: Panel | H83: Panel | I83: Melamina Color | J83: Panel decorativo/ Estante /Lama 16mm | K83: *New | L83: Largo | M83: Ancho | O83: m2 | P83: UDS | Q83: €/m2 | R83: 17 | S83: 17 | T83: 0 | U83: =F114*G114 | V83: 0 | W83: 0 | X83: =IFERROR(ROUNDUP((Q114/I114)/0.5,0)*0.5,0) | Y83: 0 | Z83: =IF(I114=0,J114*K114,I114*J114*K114) | AA83: 1 | AB83: =$N$119 | AC83: 0 | AD83: =SUM(M114*N114)+M114
A84: PRESUPUESTO | B84: 115 | C84: 112 | D84: PANEL | E84: panel | F84: panel_panel_melamina_color_especial_panel_decorativo_estante_lama_16mm_19mm | G84: Panel | H84: Panel | I84: Melamina Color Especial | J84: Panel decorativo/ Estante /Lama 16mm 19mm | K84: *New | L84: Largo | M84: Ancho | O84: m2 | P84: UDS | Q84: €/m2 | R84: 22 | S84: 22 | T84: 0 | U84: =F115*G115 | V84: 0 | W84: 0 | X84: =IFERROR(ROUNDUP((Q115/I115)/0.5,0)*0.5,0) | Y84: 0 | Z84: =IF(I115=0,J115*K115,I115*J115*K115) | AA84: 1 | AB84: =$N$119 | AC84: 0 | AD84: =SUM(M115*N115)+M115
A85: PRESUPUESTO | B85: 116 | C85: 112 | D85: PANEL | E85: panel | F85: panel_panel_aglomerado_panel_decorativo_estante_lama_16mm_o_19mm | G85: Panel | H85: Panel | I85: Aglomerado | J85: Panel decorativo/ Estante /Lama 16mm o 19mm | L85: Largo | M85: Ancho | O85: m2 | P85: UDS | Q85: €/m2 | R85: 10 | S85: 10 | T85: 0 | U85: =F116*G116 | V85: 0 | W85: 0 | X85: =IFERROR(ROUNDUP((Q116/I116)/0.5,0)*0.5,0) | Y85: 0 | Z85: =IF(I116=0,J116*K116,I116*J116*K116) | AA85: 1 | AB85: =$N$119 | AC85: 0 | AD85: =SUM(M116*N116)+M116
A86: PRESUPUESTO | B86: 117 | C86: 112 | D86: PANEL | E86: panel | F86: panel_panel_chopo_15mm_panel_decorativo_estante_lama_15mm | G86: Panel | H86: Panel | I86: Chopo 15mm | J86: Panel decorativo/ Estante /Lama 15mm | L86: Largo | M86: Ancho | O86: m2 | P86: UDS | Q86: €/m2 | R86: 14.5 | S86: 14.5 | T86: 0 | U86: =F117*G117 | V86: 0 | W86: 0 | X86: =IFERROR(ROUNDUP((Q117/I117)/0.5,0)*0.5,0) | Y86: 0 | Z86: =IF(I117=0,J117*K117,I117*J117*K117) | AA86: 1 | AB86: =$N$119 | AC86: 0 | AD86: =SUM(M117*N117)+M117
A87: PRESUPUESTO | B87: 118 | C87: 112 | D87: PANEL | E87: panel | F87: panel_panel_mdf_panel_decorativo_estante_lama_30mm | G87: Panel | H87: Panel | I87: MDF | J87: Panel decorativo/ Estante /Lama 30mm | L87: Largo | M87: Ancho | O87: m2 | P87: UDS | Q87: €/m2 | R87: 30 | S87: 30 | T87: 0 | U87: =F118*G118 | V87: 0 | W87: 0 | X87: =IFERROR(ROUNDUP((Q118/I118)/0.5,0)*0.5,0) | Y87: 0 | Z87: =IF(I118=0,J118*K118,I118*J118*K118) | AA87: 1 | AB87: =$N$119 | AC87: 0 | AD87: =SUM(M118*N118)+M118
A88: PRESUPUESTO | B88: 121 | C88: 120 | D88: TAPETAS | E88: tapetas | F88: tapetas_tapetas_mdf_5mm_minimo_1m2_por_tira | G88: Tapetas | H88: Tapetas | I88: MDF | J88: 5mm (Minimo 1m2 por tira) | L88: Largo | M88: Ancho | O88: m2 | P88: UDS | Q88: €/m2 | R88: 5 | S88: 5 | T88: 0 | U88: =F121*G121 | V88: 0 | W88: 0 | X88: =IFERROR(ROUNDUP((Q121/I121)/0.5,0)*0.5,0) | Y88: 0 | Z88: =IF(I121=0,J121*K121,I121*J121*K121) | AA88: 1 | AB88: =$N$64 | AC88: 0 | AD88: =SUM(M121*N121)+M121
A89: PRESUPUESTO | B89: 124 | C89: 123 | D89: CURVAS | E89: curvas | F89: curvas_curvas_chopo_para_pintar_chopo_5mm_a_1_caras_minimo_1m2_por_tira | G89: Curvas | H89: Curvas | I89: Chopo | J89: Para Pintar Chopo 5mm a 1 caras (Minimo 1m2 por tira) | L89: Ancho | M89: Fondo | N89: Alto | O89: m2 | P89: UDS | Q89: €/m2 | R89: 44 | S89: 44 | T89: 0 | U89: =F124*G124 | V89: 0 | W89: 0 | X89: =IFERROR(ROUNDUP((Q124/I124)/0.5,0)*0.5,0) | Y89: 0 | Z89: =IF(I124=0,J124*K124,I124*J124*K124) | AA89: 1 | AB89: =$N$126 | AC89: 0 | AD89: =SUM(M124*N124)+M124
A90: PRESUPUESTO | B90: 125 | C90: 123 | D90: CURVAS | E90: curvas | F90: curvas_curvas_chopo_para_pintar_chopo_5mm_a_2_caras_minimo_1m2_por_tira | G90: Curvas | H90: Curvas | I90: Chopo | J90: Para Pintar Chopo 5mm a 2 caras (Minimo 1m2 por tira) | L90: Ancho | M90: Fondo | N90: Alto | O90: m2 | P90: UDS | Q90: €/m2 | R90: 58 | S90: 58 | T90: 0 | U90: =F125*G125 | V90: 0 | W90: 0 | X90: =IFERROR(ROUNDUP((Q125/I125)/0.5,0)*0.5,0) | Y90: 0 | Z90: =IF(I125=0,J125*K125,I125*J125*K125) | AA90: 1 | AB90: =$N$126 | AC90: 0 | AD90: =SUM(M125*N125)+M125
A91: PRESUPUESTO | B91: 128 | C91: 127 | D91: CNC | E91: mecanizados | F91: mecanizados_cnc_cnc | G91: Mecanizados | H91: CNC | J91: Cnc | K91: Verificar precio | P91: UDS | Q91: €/Uds | R91: 23 | S91: 23 | V91: 0 | W91: 0 | X91: =IFERROR(ROUNDUP((Q128/J128)/0.5,0)*0.5,0) | Y91: 0 | Z91: =IF(I128=0,J128*K128,I128*J128*K128) | AA91: 1 | AB91: =$N$132 | AC91: 0 | AD91: =SUM(M128*N128)+M128
A92: PRESUPUESTO | B92: 130 | C92: 129 | D92: LED | E92: mecanizados | F92: mecanizados_led_regata_regata_led_recta | G92: Mecanizados | H92: Led | I92: Regata | J92: Regata Led Recta | O92: ml | P92: UDS | Q92: €/ml | R92: 5 | S92: 5 | T92: 0 | V92: 0 | W92: 0 | X92: =IFERROR(ROUNDUP((Q130/I130)/0.5,0)*0.5,0) | Y92: 0 | Z92: =IF(I130=0,J130*K130,I130*J130*K130) | AA92: 1 | AB92: =$N$14 | AC92: 0 | AD92: =SUM(M130*N130)+M130
A93: PRESUPUESTO | B93: 131 | C93: 129 | D93: LED | E93: mecanizados | F93: mecanizados_led_regata_regata_led_diagonal_o_curva | G93: Mecanizados | H93: Led | I93: Regata | J93: Regata Led Diagonal o Curva | O93: ml | P93: UDS | Q93: €/ml | R93: 10 | S93: 10 | T93: 0 | V93: 0 | W93: 0 | X93: =IFERROR(ROUNDUP((Q131/I131)/0.5,0)*0.5,0) | Y93: 0 | Z93: =IF(I131=0,J131*K131,I131*J131*K131) | AA93: 1 | AB93: =$N$14 | AC93: 0 | AD93: =SUM(M131*N131)+M131
A94: PRESUPUESTO | B94: 134 | C94: 133 | D94: HERRERO | E94: herrero | F94: herrero_herrero_hierro_pintado_estructura_metalica_perfil_pequena_tipo_mesita_noche | G94: Herrero | H94: Herrero | I94: Hierro pintado | J94: Estructura Metalica (Perfil) pequeña tipo mesita noche | K94: *New | P94: UDS | Q94: €/Uni | R94: 450 | S94: 450 | V94: 0 | W94: 0 | X94: =IFERROR(ROUNDUP((Q134/J134)/0.5,0)*0.5,0) | Y94: 0 | Z94: =IF(I134=0,J134*K134,I134*J134*K134) | AA94: 1 | AB94: =$N$111 | AC94: 0 | AD94: =SUM(M134*N134)+M134
A95: PRESUPUESTO | B95: 135 | C95: 133 | D95: HERRERO | E95: herrero | F95: herrero_herrero_hierro_pintado_estructura_metalica_perfil_pequena_tipo_mesa | G95: Herrero | H95: Herrero | I95: Hierro pintado | J95: Estructura Metalica (Perfil) pequeña tipo mesa | K95: *New | P95: UDS | Q95: €/Uni | R95: 650 | S95: 650 | V95: 0 | W95: 0 | X95: =IFERROR(ROUNDUP((Q135/J135)/0.5,0)*0.5,0) | Y95: 0 | Z95: =IF(I135=0,J135*K135,I135*J135*K135) | AA95: 1 | AB95: =$N$111 | AC95: 0 | AD95: =SUM(M135*N135)+M135
A96: PRESUPUESTO | B96: 136 | C96: 133 | D96: HERRERO | E96: herrero | F96: herrero_herrero_hierro_pintado_estructura_metalica_perfil_pequena_tipo_mesa_compleja | G96: Herrero | H96: Herrero | I96: Hierro pintado | J96: Estructura Metalica (Perfil) pequeña tipo mesa compleja | K96: *New | P96: UDS | Q96: €/Uni | R96: 1070 | S96: 1070 | V96: 0 | W96: 0 | X96: =IFERROR(ROUNDUP((Q136/J136)/0.5,0)*0.5,0) | Y96: 0 | Z96: =IF(I136=0,J136*K136,I136*J136*K136) | AA96: 1 | AB96: =$N$111 | AC96: 0 | AD96: =SUM(M136*N136)+M136
A97: PRESUPUESTO | B97: 137 | C97: 133 | D97: HERRERO | E97: herrero | F97: herrero_herrero_hierro_pintado_estructura_metalica_perfil_pequena_tipo_estanteria | G97: Herrero | H97: Herrero | I97: Hierro pintado | J97: Estructura Metalica (Perfil) pequeña tipo estanteria | K97: *New | P97: UDS | Q97: €/Uni | R97: 1270 | S97: 1270 | V97: 0 | W97: 0 | X97: =IFERROR(ROUNDUP((Q137/J137)/0.5,0)*0.5,0) | Y97: 0 | Z97: =IF(I137=0,J137*K137,I137*J137*K137) | AA97: 1 | AB97: =$N$111 | AC97: 0 | AD97: =SUM(M137*N137)+M137
A98: PRESUPUESTO | B98: 138 | C98: 133 | D98: HERRERO | E98: herrero | F98: herrero_herrero_hierro_pintado_estructura_metalica_perfil_pequena_tipo_estanteria_grande | G98: Herrero | H98: Herrero | I98: Hierro pintado | J98: Estructura Metalica (Perfil) pequeña tipo estanteria grande | K98: *New | P98: UDS | Q98: €/Uni | R98: 1870 | S98: 1870 | V98: 0 | W98: 0 | X98: =IFERROR(ROUNDUP((Q138/J138)/0.5,0)*0.5,0) | Y98: 0 | Z98: =IF(I138=0,J138*K138,I138*J138*K138) | AA98: 1 | AB98: =$N$111 | AC98: 0 | AD98: =SUM(M138*N138)+M138
A99: PRESUPUESTO | B99: 139 | C99: 133 | D99: HERRERO | E99: herrero | F99: herrero_herrero_hierro_pintado_estructura_metalica_chapa_laser_soldada_pequena_tipo_estructura_compleja_grande | G99: Herrero | H99: Herrero | I99: Hierro pintado | J99: Estructura Metalica (Chapa laser Soldada) pequeña tipo estructura compleja grande | K99: *New | P99: UDS | Q99: €/Uni | R99: 3130 | S99: 3130 | V99: 0 | W99: 0 | X99: =IFERROR(ROUNDUP((Q139/J139)/0.5,0)*0.5,0) | Y99: 0 | Z99: =IF(I139=0,J139*K139,I139*J139*K139) | AA99: 1 | AB99: =$N$111 | AC99: 0 | AD99: =SUM(M139*N139)+M139
A100: PRESUPUESTO | B100: 140 | C100: 133 | D100: HERRERO | E100: herrero | F100: herrero_herrero_hierro_pintado_estructura_metalica_chapa_laser_soldada_pequena_tipo_estructura_compleja_muy_grande | G100: Herrero | H100: Herrero | I100: Hierro pintado | J100: Estructura Metalica (Chapa laser Soldada) pequeña tipo estructura compleja muy grande | K100: *New | P100: UDS | Q100: €/Uni | R100: 3680 | S100: 3680 | V100: 0 | W100: 0 | X100: =IFERROR(ROUNDUP((Q140/J140)/0.5,0)*0.5,0) | Y100: 0 | Z100: =IF(I140=0,J140*K140,I140*J140*K140) | AA100: 1 | AB100: =$N$111 | AC100: 0 | AD100: =SUM(M140*N140)+M140
...

Sheet COSTE_IMPORT
A1: COSTE NORMALIZADO
A2: source_sheet | B2: source_row | C2: item_key | D2: family | E2: subfamily_material | F2: description | G2: x_mm | H2: y_mm | I2: thickness_mm | J2: price_current | K2: price_raw | L2: unit | M2: provider_current | N2: provider_raw | O2: extra_1_value_current | P2: extra_1_value_raw | Q2: extra_1_label | R2: extra_2_value_current | S2: extra_2_value_raw | T2: extra_2_label | U2: extra_3_value_current | V2: extra_3_value_raw | W2: extra_3_label | X2: notes_or_extra
A3: COSTE | B3: 3 | C3: personal_diseno | D3: Personal | E3: Diseño | J3: 21.26 | K3: =COMPARATIVA!G3 | L3: €/h | M3: ESWood | N3: ESWood
A4: COSTE | B4: 4 | C4: personal_fabricacion | D4: Personal | E4: Fabricación | J4: 22.4 | K4: =COMPARATIVA!G4 | L4: €/h | M4: ESWood | N4: ESWood | O4: 23.7 | P4: 23.7 | Q4: H. Extra | R4: 13.52 | S4: 13.52 | T4: 1/2Dieta | U4: 67 | V4: 67 | W4: Dieta completa
A5: COSTE | B5: 5 | C5: personal_montaje | D5: Personal | E5: Montaje | J5: 19.23 | K5: =COMPARATIVA!G5 | L5: €/h | M5: ESWood | N5: ESWood | O5: 23.7 | P5: 23.7 | Q5: H. Extra | R5: 13.52 | S5: 13.52 | T5: 1/2Dieta | U5: 67 | V5: 67 | W5: Dieta completa
A6: COSTE | B6: 6 | C6: personal_desmontaje | D6: Personal | E6: Desmontaje | J6: 19.23 | K6: =COMPARATIVA!G6 | L6: €/h | M6: ESWood | N6: ESWood | O6: 23.7 | P6: 23.7 | Q6: H. Extra | R6: 13.52 | S6: 13.52 | T6: 1/2Dieta | U6: 67 | V6: 67 | W6: Dieta completa
A7: COSTE | B7: 7 | C7: personal_externo_montaje_desmontaje_externo_al_dia | D7: Personal | E7: Externo | F7: Montaje / Desmontaje Externo al dia | J7: 250 | K7: =COMPARATIVA!G7 | L7: dia | M7: German | N7: German
A8: COSTE | B8: 8 | C8: personal_coordinador_externo_montaje_desmontaje_coordinador_externo_al_dia | D8: Personal | E8: Coordinador Externo | F8: Montaje / Desmontaje Coordinador Externo al dia | J8: 300 | K8: =COMPARATIVA!G8 | L8: dia | M8: German | N8: German
A9: COSTE | B9: 9 | C9: personal_externo_herrameintas | D9: Personal | E9: Externo+Herrameintas | J9: 0 | K9: =COMPARATIVA!G9 | L9: dia
A10: COSTE | B10: 10 | C10: personal_externo_herrameintas | D10: Personal | E10: Externo+Herrameintas | J10: 0 | K10: =COMPARATIVA!G10 | L10: dia
A11: COSTE | B11: 11 | C11: cnc_corte | D11: CNC | E11: Corte | J11: 23 | K11: =COMPARATIVA!G11 | L11: Tablero | M11: ESWood | N11: ESWood
A12: COSTE | B12: 13 | C12: tablero_mel_blanca_melamina_blanco_k_110_pe_2_c_sef_16_mm | D12: Tablero | E12: Mel. Blanca | F12: Melamina Blanco K-110 PE 2/c Sef 16 mm | G12: 2800 | H12: 2070 | I12: 16 | J12: 4.79 | K12: =COMPARATIVA!G13 | L12: €/m2 | M12: Closa | N12: =COMPARATIVA!I13 | O12: 0.58 | P12: =COMPARATIVA!J13 | Q12: Corte (+/-m2) | R12: 1.35 | S12: =COMPARATIVA!L13 | T12: Cadel | X12: =((D13/1000)*(E13/1000))*G13
A13: COSTE | B13: 14 | C13: tablero_mel_negra_melamina_negra_u_190_vl_16_mm | D13: Tablero | E13: Mel. Negra | F13: Melamina Negra U-190 VL 16 mm | G13: 2800 | H13: 2070 | I13: 16 | J13: 4.79 | K13: =COMPARATIVA!G17 | L13: €/m2 | M13: Closa | N13: =COMPARATIVA!I17 | O13: 0.58 | P13: =COMPARATIVA!J17 | Q13: Corte (+/-m2) | R13: 1.35 | S13: =COMPARATIVA!L17 | T13: Cadel | X13: =((D14/1000)*(E14/1000))*G14
A14: COSTE | B14: 15 | C14: tablero_mel_velvet_melamina_velvet_oak_d_2693_mw_16_mm | D14: Tablero | E14: Mel. Velvet | F14: Melamina Velvet Oak D-2693 MW 16 mm | G14: 2800 | H14: 2070 | I14: 16 | J14: 10 | K14: 10 | L14: €/m2 | M14: Mausa | N14: Mausa | O14: 1.98 | P14: =COMPARATIVA!J20 | Q14: Corte (+/-m2) | R14: 1.35 | S14: 1.35 | T14: Cadel | X14: =((D15/1000)*(E15/1000))*G15
A15: COSTE | B15: 16 | C15: tablero_mel_niagra_melamina_niagara_oak_d_2240_vl_16_mm | D15: Tablero | E15: Mel. Niagra | F15: Melamina Niagara Oak D-2240 VL 16 mm | G15: 2800 | H15: 2070 | I15: 16 | J15: 9.8 | K15: =COMPARATIVA!G21 | L15: €/m2 | M15: Mausa | N15: =COMPARATIVA!I21 | O15: 1.98 | P15: =COMPARATIVA!J21 | Q15: Corte (+/-m2) | R15: 1.35 | S15: 1.35 | T15: Cadel | X15: =((D16/1000)*(E16/1000))*G16
A16: COSTE | B16: 17 | C16: tablero_mel_epecial | D16: Tablero | E16: Mel. Epecial | G16: 2800 | H16: 2070 | I16: 16 | J16: 13 | K16: 13 | L16: €/m2 | M16: Mausa | N16: =COMPARATIVA!I22 | O16: 1.98 | P16: =COMPARATIVA!J22 | Q16: Corte (+/-m2) | R16: 1.35 | S16: 1.35 | T16: Cadel | X16: =((D17/1000)*(E17/1000))*G17
A17: COSTE | B17: 18 | C17: formica_blanca_formica_hpl | D17: Formica | E17: Blanca | F17: Formica HPL | I17: 0.8 | J17: 15 | K17: 15 | L17: €/m2 | M17: Gabarro | N17: Gabarro | X17: =((D18/1000)*(E18/1000))*G18
A18: COSTE | B18: 20 | C18: tablero_aglomerado_aglomerado_1a_standard_16mm | D18: Tablero | E18: Aglomerado | F18: Aglomerado 1a standard 16mm | G18: 2800 | H18: 2070 | I18: 16 | J18: 3.78 | K18: =COMPARATIVA!G24 | L18: €/m2 | M18: Closa | N18: =COMPARATIVA!I24 | O18: 0.58 | P18: =COMPARATIVA!J24 | Q18: Corte (+/-m2) | R18: 1.35 | S18: =COMPARATIVA!L24 | T18: Cadel | X18: =((D20/1000)*(E20/1000))*G20
A19: COSTE | B19: 21 | C19: tablero_aglomerado_aglomerado_1a_standard_19mm | D19: Tablero | E19: Aglomerado | F19: Aglomerado 1a standard 19mm | G19: 2800 | H19: 2070 | I19: 19 | J19: 4.53 | K19: =COMPARATIVA!G35 | L19: €/m2 | M19: Closa | N19: =COMPARATIVA!I35 | O19: 0.58 | P19: =COMPARATIVA!J35 | Q19: Corte (+/-m2) | R19: 1.35 | S19: =COMPARATIVA!L35 | T19: Cadel | X19: =((D21/1000)*(E21/1000))*G21
A20: COSTE | B20: 23 | C20: tablero_mdf_tablex_blanco_5mm_zocalo | D20: Tablero | E20: MDF | F20: Tablex Blanco 5mm (Zocalo) | G20: 2440 | H20: 1220 | I20: 5 | J20: 5.07 | K20: =COMPARATIVA!G37 | L20: €/m2 | M20: Closa | N20: =COMPARATIVA!I37 | O20: 0.58 | P20: =COMPARATIVA!J37 | Q20: Corte (+/-m2) | X20: =((D23/1000)*(E23/1000))*G23
A21: COSTE | B21: 24 | C21: tablero_mdf_tablex_negro_5mm_zocalo | D21: Tablero | E21: MDF | F21: Tablex Negro 5mm (Zocalo) | G21: 2440 | H21: 1220 | I21: 5 | J21: 7 | K21: =COMPARATIVA!G39 | L21: €/m2 | M21: Closa | N21: =COMPARATIVA!I39 | O21: 0.58 | P21: =COMPARATIVA!J39 | Q21: Corte (+/-m2) | X21: =((D24/1000)*(E24/1000))*G24
A22: COSTE | B22: 25 | C22: tablero_mdf_mdf_standard_3_mm | D22: Tablero | E22: MDF | F22: MDF Standard 3 mm | G22: 2440 | H22: 1220 | I22: 3 | J22: 3 | K22: =COMPARATIVA!G41 | L22: €/m2 | M22: Closa | N22: =COMPARATIVA!I41 | O22: 0.58 | P22: =COMPARATIVA!J41 | Q22: Corte (+/-m2) | X22: =((D25/1000)*(E25/1000))*G25
A23: COSTE | B23: 26 | C23: tablero_mdf_mdf_standard_5_mm | D23: Tablero | E23: MDF | F23: MDF Standard 5 mm | G23: 2440 | H23: 1220 | I23: 5 | J23: 2.4 | K23: =COMPARATIVA!G42 | L23: €/m2 | M23: Closa | N23: =COMPARATIVA!I42 | O23: 0.58 | P23: =COMPARATIVA!J42 | Q23: Corte (+/-m2) | X23: =((D26/1000)*(E26/1000))*G26
A24: COSTE | B24: 27 | C24: tablero_mdf_mdf_standard_16_mm | D24: Tablero | E24: MDF | F24: MDF Standard 16 mm | G24: 3660 | H24: 2070 | I24: 16 | J24: 6.36 | K24: =COMPARATIVA!G46 | L24: €/m2 | M24: Closa | N24: =COMPARATIVA!I46 | O24: 0.58 | P24: =COMPARATIVA!J46 | Q24: Corte (+/-m2) | R24: 1.35 | S24: =COMPARATIVA!L46 | T24: Cadel | X24: =((D27/1000)*(E27/1000))*G27
A25: COSTE | B25: 28 | C25: tablero_mdf_mdf_standard_19_mm | D25: Tablero | E25: MDF | F25: MDF Standard 19 mm | G25: 3660 | H25: 2070 | I25: 19 | J25: 7.58 | K25: =COMPARATIVA!G51 | L25: €/m2 | M25: Closa | N25: =COMPARATIVA!I51 | O25: 0.58 | P25: =COMPARATIVA!J51 | Q25: Corte (+/-m2) | R25: 1.35 | S25: =COMPARATIVA!L51 | T25: Cadel | X25: =((D28/1000)*(E28/1000))*G28
A26: COSTE | B26: 30 | C26: tablero_chopo_bb_bb | D26: Tablero | E26: Chopo | F26: BB/BB | G26: 2500 | H26: 1220 | I26: 5 | J26: 5.77 | K26: =COMPARATIVA!G57 | L26: €/m2 | M26: Closa | N26: =COMPARATIVA!I57 | X26: =((D30/1000)*(E30/1000))*G30
A27: COSTE | B27: 31 | C27: tablero_chopo_felx_tablero_fromager_flexible_5_mm_mostrador | D27: Tablero | E27: Chopo Felx. | F27: Tablero Fromager flexible 5 mm (mostrador) | G27: 1220 | H27: 2500 | I27: 5 | J27: 8.18 | K27: =COMPARATIVA!G62 | L27: €/m2 | M27: Closa | N27: =COMPARATIVA!I62 | X27: =((D31/1000)*(E31/1000))*G31
A28: COSTE | B28: 32 | C28: tablero_chopo_felx_tablero_fromager_flexible_5_mm_columna | D28: Tablero | E28: Chopo Felx. | F28: Tablero Fromager flexible 5 mm (Columna) | G28: 1220 | H28: 2500 | I28: 5 | J28: 8.18 | K28: =COMPARATIVA!G66 | L28: €/m2 | M28: Closa | N28: =COMPARATIVA!I66 | X28: =((D32/1000)*(E32/1000))*G32
A29: COSTE | B29: 33 | C29: tablero_chopo_bb_bb | D29: Tablero | E29: Chopo | F29: BB/BB | G29: 2500 | H29: 1220 | I29: 10 | J29: 9.46 | K29: =COMPARATIVA!G69 | L29: €/m2 | M29: Closa | N29: =COMPARATIVA!I69 | X29: =((D33/1000)*(E33/1000))*G33
A30: COSTE | B30: 34 | C30: tablero_chopo_bb_bb | D30: Tablero | E30: Chopo | F30: BB/BB | G30: 2500 | H30: 1220 | I30: 15 | J30: 13.25 | K30: =COMPARATIVA!G70 | L30: €/m2 | M30: Closa | N30: =COMPARATIVA!I70 | X30: =((D34/1000)*(E34/1000))*G34
A31: COSTE | B31: 36 | C31: tablero_osb_tablero_osb_3_xop | D31: Tablero | E31: OSB | F31: Tablero OSB 3 XOP | G31: 2500 | H31: 1250 | I31: 9 | J31: 4.16 | K31: =COMPARATIVA!G75 | L31: €/m2 | M31: Closa | N31: =COMPARATIVA!I75
A32: COSTE | B32: 37 | C32: tablero_osb_tablero_osb_3_xop | D32: Tablero | E32: OSB | F32: Tablero OSB 3 XOP | G32: 2500 | H32: 1250 | I32: 15 | J32: 6.18 | K32: =COMPARATIVA!G76 | L32: €/m2 | M32: Closa | N32: =COMPARATIVA!I76
A33: COSTE | B33: 38 | C33: tablero_osb_tablero_osb_3_xop | D33: Tablero | E33: OSB | F33: Tablero OSB 3 XOP | G33: 2500 | H33: 1250 | I33: 18 | J33: 7.88 | K33: =COMPARATIVA!G77 | L33: €/m2 | M33: Closa | N33: =COMPARATIVA!I77
A34: COSTE | B34: 39 | C34: tablero_osb_tablero_osb_3_xop | D34: Tablero | E34: OSB | F34: Tablero OSB 3 XOP | G34: 2500 | H34: 1250 | I34: 22 | J34: 9.86 | K34: =COMPARATIVA!G78 | L34: €/m2 | M34: Closa | N34: =COMPARATIVA!I78
A35: COSTE | B35: 41 | C35: liston_pino_liston_flandes_45_21 | D35: Liston | E35: Pino | F35: Liston Flandes 45*21 | G35: 4500 | H35: 45 | I35: 21 | J35: 0.66 | K35: =COMPARATIVA!G80 | L35: €/ml | M35: Forestal Vic | N35: Forestal Vic
A36: COSTE | B36: 42 | C36: liston_pino_liston_flandes_45_45 | D36: Liston | E36: Pino | F36: Liston Flandes 45*45 | G36: 4500 | H36: 45 | I36: 45 | J36: 1.33 | K36: =COMPARATIVA!G84 | L36: €/ml | M36: Forestal Vic | N36: Forestal Vic
A37: COSTE | B37: 43 | C37: liston_pino_liston_flandes_45_70 | D37: Liston | E37: Pino | F37: Liston Flandes 45*70 | G37: 4500 | H37: 45 | I37: 70 | J37: 1.99 | K37: =COMPARATIVA!G87 | L37: €/ml | M37: Forestal Vic | N37: Forestal Vic
A38: COSTE | B38: 44 | C38: liston_pino_liston_flandes_20_90 | D38: Liston | E38: Pino | F38: Liston Flandes 20*90 | G38: 4200 | H38: 20 | I38: 90 | J38: 1.95 | K38: =COMPARATIVA!G90 | L38: €/ml | M38: Forestal Vic | N38: Forestal Vic
A39: COSTE | B39: 45 | C39: liston_aveto_liston_aveto_120_60 | D39: Liston | E39: Aveto | F39: Liston Aveto 120*60 | G39: 6500 | H39: 120 | I39: 60 | J39: 5.84 | K39: =COMPARATIVA!G92 | L39: €/ml | M39: Forestal Vic | N39: Forestal Vic
A40: COSTE | B40: 46 | C40: liston_aveto_liston_aveto_120_120 | D40: Liston | E40: Aveto | F40: Liston Aveto 120*120 | G40: 6500 | H40: 120 | I40: 120 | J40: 12 | K40: =COMPARATIVA!G94 | L40: €/ml | M40: Forestal Vic | N40: Forestal Vic
A41: COSTE | B41: 48 | C41: canto_haya_canto_xapa_22_5mm_haya_natural | D41: Canto | E41: Haya | F41: Canto xapa 22*5mm Haya Natural | H41: 22 | I41: 5 | J41: 0.42 | K41: =COMPARATIVA!G96 | L41: €/ml | M41: Closa | N41: Closa
A42: COSTE | B42: 49 | C42: canto_blanco_canto_seft_22_x_0_8_mm | D42: Canto | E42: Blanco | F42: Canto SEFT 22 X 0,8 MM | H42: 22 | I42: 0.8 | J42: 0.18 | K42: =COMPARATIVA!G100 | L42: €/ml | M42: Closa | N42: =COMPARATIVA!I100
A43: COSTE | B43: 50 | C43: canto_negro_canto_abs_negro_u_190_23_0_8 | D43: Canto | E43: Negro | F43: Canto ABS Negro U-190 23*0,8 | H43: 23 | I43: 0.8 | J43: 0.38 | K43: =COMPARATIVA!G98 | L43: €/ml | M43: Closa | N43: =COMPARATIVA!I98
A44: COSTE | B44: 51 | C44: canto_velvet_oak_canto_velvet_oak | D44: Canto | E44: Velvet Oak | F44: Canto Velvet Oak | H44: 22 | I44: 0.8 | J44: 0.35217 | K44: =COMPARATIVA!G101 | L44: €/ml | M44: M&M Cantos | N44: M&M Cantos
A45: COSTE | B45: 52 | C45: canto_niagara_oak_canto_niagara_oak | D45: Canto | E45: Niagara Oak | F45: Canto Niagara Oak | H45: 22 | I45: 0.8 | J45: 0.35217 | K45: =COMPARATIVA!G102 | L45: €/ml | M45: M&M Cantos | N45: M&M Cantos
A46: COSTE | B46: 53 | C46: canto_papaya_canto_papaya | D46: Canto | E46: Papaya | F46: Canto Papaya | H46: 22 | I46: 0.8 | J46: 0.35217 | K46: =COMPARATIVA!G103 | L46: €/ml | M46: M&M Cantos | N46: M&M Cantos
A47: COSTE | B47: 55 | C47: perfil_aluminio_negro_perfil_40_20_negro_brillante | D47: Perfil | E47: Aluminio Negro | F47: Perfil 40*20 Negro Brillante | G47: 6000 | H47: 40 | I47: 20 | J47: 2.541 | K47: 2.541 | L47: €/ml | M47: Provedal | N47: Provedal
A48: COSTE | B48: 56 | C48: perfil_aluminio_blanco_perfil_40_20_blanco_brillante | D48: Perfil | E48: Aluminio Blanco | F48: Perfil 40*20 Blanco Brillante | G48: 6000 | H48: 40 | I48: 20 | J48: 2.36 | K48: 2.36 | L48: €/ml | M48: Provedal | N48: Provedal
A49: COSTE | B49: 57 | C49: pletina_aluminio_negro_pletina_20_3_negro_brillante | D49: Pletina | E49: Aluminio Negro | F49: Pletina 20*3 Negro Brillante | G49: 6000 | H49: 20 | I49: 3 | J49: 2.39 | K49: 2.39 | L49: €/ml | M49: Provedal | N49: Provedal
A50: COSTE | B50: 58 | C50: perfil_textil_para_textiles_silicona | D50: Perfil | E50: Textil | F50: Para Textiles Silicona | J50: 5 | K50: =COMPARATIVA!G108 | L50: €/ml
A51: COSTE | B51: 59 | C51: perfil_aluminio_perfil_en_u_aluminio_cristal | D51: Perfil | E51: Aluminio | F51: Perfil en U aluminio (?Cristal?) | J51: 5.77 | K51: =COMPARATIVA!G109 | L51: €/ml
A52: COSTE | B52: 61 | C52: cristal_cristal_cristal_a_medida | D52: Cristal | E52: Cristal | F52: Cristal a medida | J52: 103.77 | K52: =(6.49)+(67.28)+(30) | L52: €/m2 | M52: Mascarell | N52: Mascarell
A53: COSTE | B53: 62 | C53: cristal_puerta_puerta_tarja_a_medida | D53: Cristal | E53: Puerta | F53: Puerta + Tarja a medida | J53: 500 | K53: 500 | L53: uni | M53: Mascarell | N53: Mascarell
A54: COSTE | B54: 64 | C54: muro_bmatrix_alquiler_muro_bmatrix | D54: Muro | E54: Bmatrix | F54: Alquiler Muro Bmatrix | J54: 50 | K54: =COMPARATIVA!G111 | L54: €/m2 | M54: 0 | N54: =COMPARATIVA!I111
A55: COSTE | B55: 66 | C55: plastico_plastico_plastico_galga_400_6_x_100_m | D55: Plastico | E55: Plastico | F55: Plastico galga 400 (6 x 100 m) | G55: 100 | H55: 6 | I55: 0.01 | J55: 0.0974 | K55: 0.0974 | L55: €/ml | M55: ?? | N55: ??
A56: COSTE | B56: 67 | C56: aislante_lana_roca_lana_roca | D56: Aislante | E56: Lana Roca | F56: Lana roca | G56: 1.35 | H56: 0.6 | I56: 0.04 | J56: 4.05 | K56: 4.05 | L56: €/m2 | M56: Leroy merlin | N56: Leroy merlin
A57: COSTE | B57: 69 | C57: logistica_1_trailer_eswood_feria_bcn_13_6_largo_2_4_ancho_2_6_alto | D57: Logistica | E57: 1 Trailer | F57: ESWood - Feria BCN (13,6 Largo *2,4 Ancho *2,6 Alto) | J57: 390 | K57: 390 | L57: Viaje | M57: Sertrans | N57: Sertrans | O57: 200 | P57: 200 | Q57: Festivo | R57: 150 | S57: 150 | T57: Dia siguente
A58: COSTE | B58: 70 | C58: logistica_1_2_trailer_eswood_feria_bcn | D58: Logistica | E58: 1/2 Trailer | F58: ESWood - Feria BCN | J58: 250 | K58: 250 | L58: Viaje | M58: Sertrans | N58: Sertrans | Q58: Festivo | T58: Dia siguente
A59: COSTE | B59: 71 | C59: logistica_1_trailer_eswood_madrid | D59: Logistica | E59: 1 Trailer | F59: ESWood - Madrid | J59: 1050 | K59: 1050 | L59: Viaje | M59: Sertrans | N59: Sertrans
A60: COSTE | B60: 72 | C60: logistica_1_2_trailer_eswood_vigo | D60: Logistica | E60: 1/2 Trailer | F60: ESWood - Vigo | J60: 1150 | K60: 1150 | L60: Viaje | M60: Sertrans | N60: Sertrans | O60: 250 | P60: 250 | Q60: Sabado | R60: 375 | S60: 375 | T60: Domingo
A61: COSTE | B61: 73 | C61: logistica_1_trailer_eswood_vigo | D61: Logistica | E61: 1 Trailer | F61: ESWood - Vigo | J61: 1700 | K61: 1700 | L61: Viaje | M61: Sertrans | N61: Sertrans | O61: 250 | P61: 250 | Q61: Sabado | R61: 375 | S61: 375 | T61: Domingo
A62: COSTE | B62: 74 | C62: logistica_1_2_trailer_eswood_londres | D62: Logistica | E62: 1/2 Trailer | F62: ESWood - Londres | L62: Viaje | M62: Sertrans | N62: Sertrans
A63: COSTE | B63: 75 | C63: logistica_1_trailer_eswood_londres | D63: Logistica | E63: 1 Trailer | F63: ESWood - Londres | J63: 3850 | K63: 3850 | L63: Viaje | M63: Sertrans | N63: Sertrans | O63: 80 | P63: 80 | Q63: ATA
A64: COSTE | B64: 76 | C64: logistica_1_trailer_londres_eswood | D64: Logistica | E64: 1 Trailer | F64: Londres - ESWood | J64: 2350 | K64: 2350 | L64: Viaje | M64: Sertrans | N64: Sertrans | O64: 80 | P64: 80 | Q64: ATA
A65: COSTE | B65: 78 | C65: logistica_toro_1h_con_conductor_feria_granvia_resa | D65: Logistica | E65: Toro | F65: 1h con conductor Feria Granvia Resa | J65: 86 | K65: 86 | L65: €/1h | M65: Resa Expo | N65: Resa Expo | R65: 0.1 | S65: 0.1 | T65: 10 dias antelacion
A66: COSTE | B66: 79 | C66: logistica_toro_1_dia_sin_conductor_feria_granvia_resa | D66: Logistica | E66: Toro | F66: 1 dia Sin conductor Feria Granvia Resa | J66: 313 | K66: =163+150 | L66: €/1dia | M66: Resa Expo | N66: Resa Expo | R66: 0.1 | S66: 0.1 | T66: 10 dias antelacion
A67: COSTE | B67: 80 | C67: logistica_toro_1h_con_conductor_feria_granvia_resa_mwc | D67: Logistica | E67: Toro | F67: 1h con conductor Feria Granvia Resa (MWC) | L67: €/1h | M67: Resa Expo | N67: Resa Expo | R67: 0.1 | S67: 0.1 | T67: 10 dias antelacion
A68: COSTE | B68: 81 | C68: logistica_toro_1_dia_sin_conductor_feria_granvia_resa_mwc | D68: Logistica | E68: Toro | F68: 1 dia Sin conductor Feria Granvia Resa (MWC) | L68: €/1dia | M68: Resa Expo | N68: Resa Expo | R68: 0.1 | S68: 0.1 | T68: 10 dias antelacion
A69: COSTE | B69: 83 | C69: logistica_reciclado_1_container_reciclado | D69: Logistica | E69: Reciclado | F69: 1 Container reciclado | J69: 300 | K69: 300 | L69: €/Uni
A70: COSTE | B70: 85 | C70: pintor_blanca | D70: Pintor | E70: Blanca | J70: 7 | K70: 7 | L70: €/m2 | M70: Guayaba | N70: Guayaba
A71: COSTE | B71: 86 | C71: pintor_color | D71: Pintor | E71: Color | J71: 10 | K71: 10 | L71: €/m2 | M71: Guayaba | N71: Guayaba
A72: COSTE | B72: 87 | C72: pintor_1_capa_almacen_y_vinilo | D72: Pintor | E72: 1 Capa | F72: Almacen y Vinilo | J72: 4.5 | K72: 4.5 | L72: €/m2 | M72: Guayaba | N72: Guayaba
A73: COSTE | B73: 88 | C73: pintor_barniz | D73: Pintor | E73: Barniz | J73: 11.5 | K73: 11.5 | L73: €/m2 | M73: Guayaba | N73: Guayaba
A74: COSTE | B74: 89 | C74: lacado_blanco_lacado_blanco_mueble_montado | D74: Lacado | E74: Blanco | F74: Lacado blanco mueble montado | J74: 40.7 | K74: =COMPARATIVA!G127 | L74: €/m2 | M74: Gopecosa | N74: Gopecosa
A75: COSTE | B75: 90 | C75: lacado_color_lacado_color_mueble_montado | D75: Lacado | E75: Color | F75: Lacado Color mueble montado | J75: 44.7 | K75: =COMPARATIVA!G128 | L75: €/m2 | M75: Gopecosa | N75: Gopecosa

Sheet COMPARATIVA_IMPORT
A1: COMPARATIVA NORMALIZADA
A2: source_sheet | B2: source_row | C2: item_key | D2: family | E2: subfamily_material | F2: description | G2: x_mm | H2: y_mm | I2: thickness_mm | J2: price_current | K2: price_raw | L2: unit | M2: provider_current | N2: provider_raw | O2: extra_1_value_current | P2: extra_1_value_raw | Q2: extra_1_label | R2: extra_2_value_current | S2: extra_2_value_raw | T2: extra_2_label | U2: extra_3_value_current | V2: extra_3_value_raw | W2: extra_3_label | X2: notes_or_extra
A3: COMPARATIVA | B3: 3 | C3: personal_diseno | D3: Personal | E3: Diseño | J3: 21.26 | K3: 21.26 | L3: €/h | M3: ESWood | N3: ESWood
A4: COMPARATIVA | B4: 4 | C4: personal_fabricacion | D4: Personal | E4: Fabricación | J4: 22.4 | K4: 22.4 | L4: €/h | M4: ESWood | N4: ESWood | O4: 23.7 | P4: 23.7 | Q4: H. Extra | R4: 13.52 | S4: 13.52 | T4: 1/2Dieta | U4: 67 | V4: 67 | W4: Dieta completa
A5: COMPARATIVA | B5: 5 | C5: personal_montaje | D5: Personal | E5: Montaje | J5: 19.23 | K5: 19.23 | L5: €/h | M5: ESWood | N5: ESWood | O5: 23.7 | P5: 23.7 | Q5: H. Extra | R5: 13.52 | S5: 13.52 | T5: 1/2Dieta | U5: 67 | V5: 67 | W5: Dieta completa
A6: COMPARATIVA | B6: 6 | C6: personal_desmontaje | D6: Personal | E6: Desmontaje | J6: 19.23 | K6: 19.23 | L6: €/h | M6: ESWood | N6: ESWood | O6: 23.7 | P6: 23.7 | Q6: H. Extra | R6: 13.52 | S6: 13.52 | T6: 1/2Dieta | U6: 67 | V6: 67 | W6: Dieta completa
A7: COMPARATIVA | B7: 7 | C7: personal_externo_montaje_desmontaje_externo_al_dia_german | D7: Personal | E7: Externo | F7: Montaje / Desmontaje Externo al dia (German) | J7: 250 | K7: 250 | L7: dia | M7: German | N7: German
A8: COMPARATIVA | B8: 8 | C8: personal_coordinador_externo_montaje_desmontaje_coordinador_externo_al_dia_german | D8: Personal | E8: Coordinador Externo | F8: Montaje / Desmontaje Coordinador Externo al dia (German) | J8: 300 | K8: 300 | L8: dia | M8: German | N8: German
A9: COMPARATIVA | B9: 9 | C9: personal_externo_herrameintas | D9: Personal | E9: Externo+Herrameintas
A10: COMPARATIVA | B10: 10 | C10: personal_externo_herrameintas | D10: Personal | E10: Externo+Herrameintas
A11: COMPARATIVA | B11: 11 | C11: cnc_corte | D11: CNC | E11: Corte | J11: 23 | K11: 23 | L11: Tablero | M11: ESWood | N11: ESWood
A12: COMPARATIVA | B12: 13 | C12: tablero_mel_blanca_melamina_blanca_8685_bs_kronos | D12: Tablero | E12: Mel. Blanca | F12: Melamina Blanca 8685 BS KRONOS | G12: 2800 | H12: 2070 | I12: 16 | J12: 4.79 | K12: 4.79 | L12: €/m2 | M12: Closa | N12: Closa | O12: 0.58 | P12: 0.58 | Q12: Corte (+/-m2) | R12: 1.35 | S12: 1.35 | T12: Cadel (+/-m2) | X12: =((D13/1000)*(E13/1000))*G13
A13: COMPARATIVA | B13: 14 | C13: tablero_mel_blanca_melamina_blanco_k_110_pe_2_c_sef_16_mm | D13: Tablero | E13: Mel. Blanca | F13: Melamina Blanco K-110 PE 2/c Sef 16 mm | G13: 2800 | H13: 2070 | I13: 16 | J13: 6.35 | K13: 6.35 | L13: €/m2 | M13: Mausa | N13: Mausa | O13: 1.98 | P13: 1.98 | Q13: Corte (+/-m2) | X13: =((D14/1000)*(E14/1000))*G14
A14: COMPARATIVA | B14: 15 | C14: tablero_mel_branca_melamina_blanca_tiza_w908_st7 | D14: Tablero | E14: Mel. Branca | F14: Melamina Blanca TIZA W908 ST7 | G14: 2800 | H14: 2070 | I14: 16 | J14: 5.35 | K14: 5.35 | L14: €/m2 | M14: Albertch | N14: Albertch | U14: 5.16 | V14: 5.16 | W14: Paquete | X14: =((D15/1000)*(E15/1000))*G15
A15: COMPARATIVA | B15: 16 | C15: tablero_mel_blanca_melamina_blanca_8685_bs_kronos | D15: Tablero | E15: Mel. Blanca | F15: Melamina Blanca 8685 BS KRONOS | G15: 2800 | H15: 2070 | I15: 16 | J15: 5.07 | K15: 5.07 | L15: €/m2 | M15: Albertch | N15: Albertch | U15: 4.9 | V15: 4.9 | W15: Paquete | X15: =((D16/1000)*(E16/1000))*G16
A16: COMPARATIVA | B16: 17 | C16: tablero_mel_negra_melamina_negra_16mm | D16: Tablero | E16: Mel. Negra | F16: Melamina Negra 16mm | G16: 2800 | H16: 2070 | I16: 16 | J16: 4.79 | K16: 4.79 | L16: €/m2 | M16: Closa | N16: Closa | O16: 0.58 | P16: 0.58 | Q16: Corte (+/-m2) | R16: 1.35 | S16: 1.35 | T16: Cadel (+/-m2) | X16: =((D17/1000)*(E17/1000))*G17
A17: COMPARATIVA | B17: 18 | C17: tablero_mel_negra_melamina_negra_u_190_vl_16_mm | D17: Tablero | E17: Mel. Negra | F17: Melamina Negra U-190 VL 16 mm | G17: 2800 | H17: 2070 | I17: 16 | L17: €/m2 | M17: Mausa | N17: Mausa | O17: 1.98 | P17: 1.98 | Q17: Corte (+/-m2) | X17: =((D18/1000)*(E18/1000))*G18
A18: COMPARATIVA | B18: 19 | C18: tablero_mel_negra_melamina_negra_0190_bs_kronos | D18: Tablero | E18: Mel. Negra | F18: Melamina Negra 0190 BS KRONOS | G18: 2850 | H18: 2100 | I18: 16 | J18: 5.07 | K18: 5.07 | L18: €/m2 | M18: Albertch | N18: Albertch | U18: 4.9 | V18: 4.9 | W18: Paquete | X18: =((D19/1000)*(E19/1000))*G19
A19: COMPARATIVA | B19: 20 | C19: tablero_mel_velvet_melamina_velvet_oak_d_2693_mw_16_mm | D19: Tablero | E19: Mel. Velvet | F19: Melamina Velvet Oak D-2693 MW 16 mm | G19: 2800 | H19: 2070 | I19: 16 | L19: €/m2 | M19: Mausa | N19: Mausa | O19: 1.98 | P19: 1.98 | Q19: Corte (+/-m2) | X19: =((D20/1000)*(E20/1000))*G20
A20: COMPARATIVA | B20: 21 | C20: tablero_mel_niagra_melamina_niagara_oak_d_2240_vl_16_mm | D20: Tablero | E20: Mel. Niagra | F20: Melamina Niagara Oak D-2240 VL 16 mm | G20: 2800 | H20: 2070 | I20: 16 | J20: 9.8 | K20: 9.8 | L20: €/m2 | M20: Mausa | N20: Mausa | O20: 1.98 | P20: 1.98 | Q20: Corte (+/-m2) | X20: =((D21/1000)*(E21/1000))*G21
A21: COMPARATIVA | B21: 22 | C21: tablero_mel_papaya_melamina_monument_papaya_luxor_19_mm | D21: Tablero | E21: Mel. Papaya | F21: Melamina Monument Papaya Luxor 19 mm | G21: 2850 | H21: 2100 | I21: 19 | L21: €/m2 | M21: Mausa | N21: Mausa | O21: 1.98 | P21: 1.98 | Q21: Corte (+/-m2) | X21: =((D22/1000)*(E22/1000))*G22
A22: COMPARATIVA | B22: 24 | C22: tablero_aglomerado_aglomerado_1a_standard_16mm | D22: Tablero | E22: Aglomerado | F22: Aglomerado 1a standard 16mm | G22: 2800 | H22: 2070 | I22: 16 | J22: 3.78 | K22: 3.78 | L22: €/m2 | M22: Closa | N22: Closa | O22: 0.58 | P22: 0.58 | Q22: Corte (+/-m2) | R22: 1.35 | S22: 1.35 | T22: Cadel (+/-m2) | X22: =((D24/1000)*(E24/1000))*G24
A23: COMPARATIVA | B23: 25 | C23: tablero_aglomerado_aglomerado_1a_standard_16mm | D23: Tablero | E23: Aglomerado | F23: Aglomerado 1a standard 16mm | G23: 2800 | H23: 2070 | I23: 16 | J23: 3.69 | K23: 3.69 | L23: €/m2 | M23: Albaertch | N23: Albaertch | U23: 3.57 | V23: 3.57 | W23: Paquete | X23: =((D25/1000)*(E25/1000))*G25
A24: COMPARATIVA | B24: 26 | C24: tablero_aglomerado_aglomerado_1a_standard_16mm | D24: Tablero | E24: Aglomerado | F24: Aglomerado 1a standard 16mm | G24: 2800 | H24: 2070 | I24: 16 | J24: 4.02 | K24: 4.02 | L24: €/m2 | M24: Gabarro | N24: Gabarro | O24: 1.81 | P24: =425.35/235 | Q24: Corte (+/-m2) | R24: 1.4480068 | S24: =428.61/296 | T24: Cadel (+/-m2) | X24: =((D26/1000)*(E26/1000))*G26
A25: COMPARATIVA | B25: 27 | C25: tablero_aglomerado_aglomerado_1a_standard_16mm | D25: Tablero | E25: Aglomerado | F25: Aglomerado 1a standard 16mm | G25: 2800 | H25: 2070 | I25: 16 | J25: 4.65 | K25: 4.65 | L25: €/m2 | M25: Mausa | N25: Mausa | O25: 1.98 | P25: 1.98 | Q25: Corte (+/-m2) | X25: =((D27/1000)*(E27/1000))*G27
A26: COMPARATIVA | B26: 28 | C26: tablero_aglomerado_aglomerado_1a_standard_16mm | D26: Tablero | E26: Aglomerado | F26: Aglomerado 1a standard 16mm | G26: 3660 | H26: 2070 | I26: 16 | J26: 3.78 | K26: 3.78 | L26: €/m2 | M26: Closa | N26: Closa | O26: 0.58 | P26: 0.58 | Q26: Corte (+/-m2) | R26: 1.35 | S26: 1.35 | T26: Cadel (+/-m2) | X26: =((D28/1000)*(E28/1000))*G28
A27: COMPARATIVA | B27: 29 | C27: tablero_aglomerado_aglomerado_1a_standard_16mm | D27: Tablero | E27: Aglomerado | F27: Aglomerado 1a standard 16mm | G27: 3660 | H27: 2070 | I27: 16 | J27: 4.02 | K27: 4.02 | L27: €/m2 | M27: Gabarro | N27: Gabarro | O27: 1.81 | P27: =425.35/235 | Q27: Corte (+/-m2) | R27: 1.4480068 | S27: =428.61/296 | T27: Cadel (+/-m2) | X27: =((D29/1000)*(E29/1000))*G29
A28: COMPARATIVA | B28: 30 | C28: tablero_aglomerado_aglomerado_1a_standard_16mm | D28: Tablero | E28: Aglomerado | F28: Aglomerado 1a standard 16mm | G28: 3660 | H28: 2070 | I28: 16 | J28: 4.65 | K28: 4.65 | L28: €/m2 | M28: Mausa | N28: Mausa | O28: 1.98 | P28: 1.98 | Q28: Corte (+/-m2) | X28: =((D30/1000)*(E30/1000))*G30
A29: COMPARATIVA | B29: 31 | C29: tablero_aglomerado_aglomerado_1a_standard_16mm | D29: Tablero | E29: Aglomerado | F29: Aglomerado 1a standard 16mm | G29: 3050 | H29: 2070 | I29: 16 | J29: 4.61 | K29: 4.61 | L29: €/m2 | M29: Gabarro | N29: Gabarro | O29: 1.81 | P29: =425.35/235 | Q29: Corte (+/-m2) | R29: 1.4480068 | S29: =428.61/296 | T29: Cadel (+/-m2) | X29: =((D31/1000)*(E31/1000))*G31
A30: COMPARATIVA | B30: 32 | C30: tablero_aglomerado_aglomerado_1a_standard_16mm | D30: Tablero | E30: Aglomerado | F30: Aglomerado 1a standard 16mm | G30: 3050 | H30: 2070 | I30: 16 | J30: 3.69 | K30: 3.69 | L30: €/m2 | M30: Albaertch | N30: Albaertch | U30: 3.57 | V30: 3.57 | W30: Paquete | X30: =((D32/1000)*(E32/1000))*G32
A31: COMPARATIVA | B31: 33 | C31: tablero_aglomerado_aglomerado_1a_standard_16mm | D31: Tablero | E31: Aglomerado | F31: Aglomerado 1a standard 16mm | G31: 4000 | H31: 2070 | I31: 16 | J31: 4.61 | K31: 4.61 | L31: €/m2 | M31: Gabarro | N31: Gabarro | O31: 1.81 | P31: =425.35/235 | Q31: Corte (+/-m2) | R31: 1.4480068 | S31: =428.61/296 | T31: Cadel (+/-m2) | X31: =((D33/1000)*(E33/1000))*G33
A32: COMPARATIVA | B32: 34 | C32: tablero_aglomerado_aglomerado_1a_standard_16mm | D32: Tablero | E32: Aglomerado | F32: Aglomerado 1a standard 16mm | G32: 4000 | H32: 2070 | I32: 16 | J32: 3.69 | K32: 3.69 | L32: €/m2 | M32: Albaertch | N32: Albaertch | U32: 3.57 | V32: 3.57 | W32: Paquete | X32: =((D34/1000)*(E34/1000))*G34
A33: COMPARATIVA | B33: 35 | C33: tablero_aglomerado_aglomerado_1a_standard_19mm | D33: Tablero | E33: Aglomerado | F33: Aglomerado 1a standard 19mm | G33: 2800 | H33: 2070 | I33: 19 | J33: 4.53 | K33: 4.53 | L33: €/m2 | M33: Closa | N33: Closa | O33: 0.58 | P33: 0.58 | Q33: Corte (+/-m2) | R33: 1.35 | S33: 1.35 | T33: Cadel (+/-m2) | X33: =((D35/1000)*(E35/1000))*G35
A34: COMPARATIVA | B34: 37 | C34: tablero_mdf_blanco_mdf_lacado_blanco_1_cara | D34: Tablero | E34: MDF Blanco | F34: MDF Lacado Blanco 1/Cara | G34: 244 | H34: 122 | I34: 5 | J34: 5.07 | K34: 5.07 | L34: €/m2 | M34: Closa | N34: Closa | O34: 0.58 | P34: 0.58 | Q34: Corte (+/- m2) | X34: =((D37/1000)*(E37/1000))*G37
A35: COMPARATIVA | B35: 38 | C35: tablero_mdf_tablex_blanco_5mm_zocalo | D35: Tablero | E35: MDF | F35: Tablex Blanco 5mm (Zocalo) | G35: 2440 | H35: 1220 | I35: 5 | L35: €/m2 | M35: Mausa | N35: Mausa | X35: =((D38/1000)*(E38/1000))*G38
A36: COMPARATIVA | B36: 39 | C36: tablero_mdf_tablex_negro_5mm_zocalo | D36: Tablero | E36: MDF | F36: Tablex Negro 5mm (Zocalo) | G36: 2440 | H36: 1220 | I36: 5 | J36: 7 | K36: 7 | L36: €/m2 | M36: Closa | N36: Closa | O36: 0.58 | P36: 0.58 | Q36: Corte (+/- m2) | X36: =((D39/1000)*(E39/1000))*G39
A37: COMPARATIVA | B37: 40 | C37: tablero_mdf_tablex_negro_5mm_zocalo | D37: Tablero | E37: MDF | F37: Tablex Negro 5mm (Zocalo) | G37: 2440 | H37: 1220 | I37: 5 | L37: €/m2 | M37: Mausa | N37: Mausa | X37: =((D40/1000)*(E40/1000))*G40
A38: COMPARATIVA | B38: 41 | C38: tablero_mdf_mdf_standard_3_mm | D38: Tablero | E38: MDF | F38: MDF Standard 3 mm | G38: 2440 | H38: 1220 | I38: 3 | J38: 3 | K38: 3 | L38: €/m2 | M38: Closa | N38: Closa | O38: 0.58 | P38: 0.58 | Q38: Corte (+/-m2) | X38: =((D41/1000)*(E41/1000))*G41
A39: COMPARATIVA | B39: 42 | C39: tablero_mdf_mdf_standard_5_mm | D39: Tablero | E39: MDF | F39: MDF Standard 5 mm | G39: 2440 | H39: 1220 | I39: 5 | J39: 2.4 | K39: 2.4 | L39: €/m2 | M39: Closa | N39: Closa | O39: 0.58 | P39: 0.58 | Q39: Corte (+/-m2) | X39: =((D42/1000)*(E42/1000))*G42
A40: COMPARATIVA | B40: 43 | C40: tablero_mdf_mdf_standard_5_mm | D40: Tablero | E40: MDF | F40: MDF Standard 5 mm | G40: 2440 | H40: 1220 | I40: 5 | J40: 3.05 | K40: 3.05 | L40: €/m2 | M40: Gabarro | N40: Gabarro | O40: 1.81 | P40: =425.35/235 | Q40: Corte (+/-m2) | R40: 1.4480068 | S40: =428.61/296 | T40: Cadel (+/-m2) | X40: =((D43/1000)*(E43/1000))*G43
A41: COMPARATIVA | B41: 44 | C41: tablero_mdf_mdf_standard_5_mm | D41: Tablero | E41: MDF | F41: MDF Standard 5 mm | G41: 2440 | H41: 1220 | I41: 5 | J41: 3.03 | K41: 3.03 | L41: €/m2 | M41: Mausa | N41: Mausa | X41: =((D44/1000)*(E44/1000))*G44
A42: COMPARATIVA | B42: 45 | C42: tablero_mdf_mdf_standard_5_mm | D42: Tablero | E42: MDF | F42: MDF Standard 5 mm | G42: 2440 | H42: 1220 | I42: 5 | J42: 2.58 | K42: 2.58 | L42: €/m2 | M42: Albaertch | N42: Albaertch | U42: 2.5 | V42: 2.5 | W42: Paquete | X42: =((D45/1000)*(E45/1000))*G45
A43: COMPARATIVA | B43: 46 | C43: tablero_mdf_mdf_standard_16_mm | D43: Tablero | E43: MDF | F43: MDF Standard 16 mm | G43: 2800 | H43: 2070 | I43: 16 | J43: 6.36 | K43: 6.36 | L43: €/m2 | M43: Closa | N43: Closa | O43: 0.58 | P43: 0.58 | Q43: Corte (+/-m2) | R43: 1.35 | S43: 1.35 | T43: Cadel (+/-m2) | X43: =((D46/1000)*(E46/1000))*G46
A44: COMPARATIVA | B44: 47 | C44: tablero_mdf_mdf_standard_16_mm | D44: Tablero | E44: MDF | F44: MDF Standard 16 mm | G44: 2800 | H44: 2070 | I44: 16 | J44: 5.94 | K44: 5.94 | L44: €/m2 | M44: Albaertch | N44: Albaertch | U44: 5.74 | V44: 5.74 | W44: Paquete | X44: =((D47/1000)*(E47/1000))*G47
A45: COMPARATIVA | B45: 48 | C45: tablero_mdf_mdf_standard_16_mm | D45: Tablero | E45: MDF | F45: MDF Standard 16 mm | G45: 3660 | H45: 2070 | I45: 16 | J45: 6.5 | K45: 6.5 | L45: €/m2 | M45: Gabarro | N45: Gabarro | O45: 1.81 | P45: =425.35/235 | Q45: Corte (+/-m2) | R45: 1.4480068 | S45: =428.61/296 | T45: Cadel (+/-m2) | X45: =((D48/1000)*(E48/1000))*G48
A46: COMPARATIVA | B46: 49 | C46: tablero_mdf_mdf_standard_16_mm | D46: Tablero | E46: MDF | F46: MDF Standard 16 mm | G46: 3660 | H46: 2070 | I46: 16 | J46: 5.94 | K46: 5.94 | L46: €/m2 | M46: Albaertch | N46: Albaertch | U46: 5.74 | V46: 5.74 | W46: Paquete | X46: =((D49/1000)*(E49/1000))*G49
A47: COMPARATIVA | B47: 50 | C47: tablero_mdf_mdf_standard_16_mm | D47: Tablero | E47: MDF | F47: MDF Standard 16 mm | G47: 3660 | H47: 2070 | I47: 16 | J47: 6.581 | K47: 6.581 | L47: €/m2 | M47: Mausa | N47: Mausa | X47: =((D50/1000)*(E50/1000))*G50
A48: COMPARATIVA | B48: 51 | C48: tablero_mdf_mdf_standard_19_mm | D48: Tablero | E48: MDF | F48: MDF Standard 19 mm | G48: 2800 | H48: 2070 | I48: 19 | J48: 7.58 | K48: 7.58 | L48: €/m2 | M48: Closa | N48: Closa | O48: 0.58 | P48: 0.58 | Q48: Corte (+/-m2) | R48: 1.35 | S48: 1.35 | T48: Cadel (+/-m2) | X48: =((D51/1000)*(E51/1000))*G51
A49: COMPARATIVA | B49: 52 | C49: tablero_mdf_mdf_standard_19_mm | D49: Tablero | E49: MDF | F49: MDF Standard 19 mm | G49: 2800 | H49: 2070 | I49: 19 | J49: 7.08 | K49: 7.08 | L49: €/m2 | M49: Albaertch | N49: Albaertch | U49: 6.84 | V49: 6.84 | W49: Paquete | X49: =((D52/1000)*(E52/1000))*G52
A50: COMPARATIVA | B50: 53 | C50: tablero_mdf_mdf_standard_19_mm | D50: Tablero | E50: MDF | F50: MDF Standard 19 mm | G50: 3660 | H50: 2070 | I50: 19 | J50: 7.81 | K50: 7.81 | L50: €/m2 | M50: Gabarro | N50: Gabarro | O50: 1.81 | P50: =425.35/235 | Q50: Corte (+/-m2) | R50: 1.4480068 | S50: =428.61/296 | T50: Cadel (+/-m2) | X50: =((D53/1000)*(E53/1000))*G53
A51: COMPARATIVA | B51: 54 | C51: tablero_mdf_mdf_standard_19_mm | D51: Tablero | E51: MDF | F51: MDF Standard 19 mm | G51: 3660 | H51: 2070 | I51: 19 | J51: 8.36 | K51: 8.36 | L51: €/m2 | M51: Mausa | N51: Mausa | X51: =((D54/1000)*(E54/1000))*G54
A52: COMPARATIVA | B52: 55 | C52: tablero_mdf_mdf_standard_19_mm | D52: Tablero | E52: MDF | F52: MDF Standard 19 mm | G52: 3660 | H52: 2070 | I52: 19 | J52: 7.08 | K52: 7.08 | L52: €/m2 | M52: Albaertch | N52: Albaertch | U52: 6.84 | V52: 6.84 | W52: Paquete | X52: =((D55/1000)*(E55/1000))*G55
A53: COMPARATIVA | B53: 57 | C53: tablero_chopo_bb_bb | D53: Tablero | E53: Chopo | F53: BB/BB | G53: 2440 | H53: 1220 | I53: 5 | J53: 5.77 | K53: 5.77 | L53: €/m2 | M53: Closa | N53: Closa | O53: 0.58 | P53: 0.58 | Q53: Corte (+/-m2) | X53: =((D57/1000)*(E57/1000))*G57
A54: COMPARATIVA | B54: 58 | C54: tablero_chopo_bb_bb | D54: Tablero | E54: Chopo | F54: BB/BB | G54: 2500 | H54: 1220 | I54: 4 | J54: 5.97 | K54: 5.97 | L54: €/m2 | M54: Gabarro | N54: Gabarro | O54: 1.81 | P54: =425.35/235 | Q54: Corte (+/-m2) | R54: 1.4480068 | S54: =428.61/296 | T54: Cadel (+/-m2) | X54: =((D58/1000)*(E58/1000))*G58
A55: COMPARATIVA | B55: 59 | C55: tablero_chopo_bb_bb | D55: Tablero | E55: Chopo | F55: BB/BB | G55: 2500 | H55: 1220 | I55: 4 | J55: 5.4 | K55: 5.4 | L55: €/m2 | M55: Albaertch | N55: Albaertch | U55: 5.22 | V55: 5.22 | W55: Paquete | X55: =((D59/1000)*(E59/1000))*G59
A56: COMPARATIVA | B56: 60 | C56: tablero_chopo_bb_bb | D56: Tablero | E56: Chopo | F56: BB/BB | G56: 2500 | H56: 1220 | I56: 5 | J56: 7.64 | K56: 7.64 | L56: €/m2 | M56: Mausa | N56: Mausa | X56: =((D60/1000)*(E60/1000))*G60
A57: COMPARATIVA | B57: 61 | C57: tablero_chopo_bb_bb | D57: Tablero | E57: Chopo | F57: BB/BB | G57: 2500 | H57: 1220 | I57: 5 | J57: 6.18 | K57: 6.18 | L57: €/m2 | M57: Albaertch | N57: Albaertch | U57: 5.98 | V57: 5.98 | W57: Paquete | X57: =((D61/1000)*(E61/1000))*G61
A58: COMPARATIVA | B58: 62 | C58: tablero_chopo_felx_tablero_fromager_flexible_5_mm_mostrador | D58: Tablero | E58: Chopo Felx. | F58: Tablero Fromager flexible 5 mm (mostrador) | G58: 1220 | H58: 2500 | I58: 5 | J58: 8.18 | K58: 8.18 | L58: €/m2 | M58: Closa | N58: Closa | X58: =((D62/1000)*(E62/1000))*G62
A59: COMPARATIVA | B59: 63 | C59: tablero_chopo_felx_tablero_fromager_flexible_5_mm_mostrador | D59: Tablero | E59: Chopo Felx. | F59: Tablero Fromager flexible 5 mm (mostrador) | G59: 1220 | H59: 2500 | I59: 5 | L59: €/m2 | M59: Gabarro | N59: Gabarro | X59: =((D63/1000)*(E63/1000))*G63
A60: COMPARATIVA | B60: 64 | C60: tablero_chopo_felx_tablero_fromager_flexible_5_mm_mostrador | D60: Tablero | E60: Chopo Felx. | F60: Tablero Fromager flexible 5 mm (mostrador) | G60: 1220 | H60: 2500 | I60: 5 | J60: 9.6 | K60: 9.6 | L60: €/m2 | M60: Albaertch | N60: Albaertch | U60: 9.6 | V60: 9.6 | W60: Paquete | X60: =((D64/1000)*(E64/1000))*G64
A61: COMPARATIVA | B61: 65 | C61: tablero_chopo_felx_tablero_fromager_flexible_5_mm_mostrador | D61: Tablero | E61: Chopo Felx. | F61: Tablero Fromager flexible 5 mm (mostrador) | G61: 1220 | H61: 2500 | I61: 5 | L61: €/m2 | M61: Mausa | N61: Mausa
A62: COMPARATIVA | B62: 66 | C62: tablero_chopo_felx_tablero_fromager_flexible_5_mm_columna | D62: Tablero | E62: Chopo Felx. | F62: Tablero Fromager flexible 5 mm (Columna) | G62: 1220 | H62: 2500 | I62: 5 | J62: 8.18 | K62: 8.18 | L62: €/m2 | M62: Closa | N62: Closa | X62: =((D66/1000)*(E66/1000))*G66
A63: COMPARATIVA | B63: 67 | C63: tablero_chopo_felx_tablero_fromager_flexible_5_mm_columna | D63: Tablero | E63: Chopo Felx. | F63: Tablero Fromager flexible 5 mm (Columna) | G63: 1220 | H63: 2500 | I63: 5 | L63: €/m2 | M63: Gabarro | N63: Gabarro | X63: =((D67/1000)*(E67/1000))*G67
A64: COMPARATIVA | B64: 68 | C64: tablero_chopo_felx_tablero_fromager_flexible_5_mm_columna | D64: Tablero | E64: Chopo Felx. | F64: Tablero Fromager flexible 5 mm (Columna) | G64: 1220 | H64: 2500 | I64: 5 | L64: €/m2 | M64: Mausa | N64: Mausa
A65: COMPARATIVA | B65: 69 | C65: tablero_chopo_bb_bb | D65: Tablero | E65: Chopo | F65: BB/BB | G65: 2440 | H65: 1220 | I65: 10 | J65: 9.46 | K65: 9.46 | L65: €/m2 | M65: Closa | N65: Closa | O65: 0.58 | P65: 0.58 | Q65: Corte (+/-m2) | X65: =((D69/1000)*(E69/1000))*G69
A66: COMPARATIVA | B66: 70 | C66: tablero_chopo_bb_bb | D66: Tablero | E66: Chopo | F66: BB/BB | G66: 2440 | H66: 1220 | I66: 15 | J66: 13.25 | K66: 13.25 | L66: €/m2 | M66: Closa | N66: Closa | O66: 0.58 | P66: 0.58 | Q66: Corte (+/-m2) | X66: =((D70/1000)*(E70/1000))*G70
A67: COMPARATIVA | B67: 71 | C67: tablero_chopo_bb_bb | D67: Tablero | E67: Chopo | F67: BB/BB | G67: 2500 | H67: 1220 | I67: 15 | J67: 14.27 | K67: 14.27 | L67: €/m2 | M67: Gabarro | N67: Gabarro | O67: 1.81 | P67: =425.35/235 | Q67: Corte (+/-m2) | X67: =((D71/1000)*(E71/1000))*G71
A68: COMPARATIVA | B68: 72 | C68: tablero_chopo_bb_bb | D68: Tablero | E68: Chopo | F68: BB/BB | G68: 2500 | H68: 1220 | I68: 15 | J68: 13.5 | K68: 13.5 | L68: €/m2 | M68: Albaertch | N68: Albaertch | U68: 13.05 | V68: 13.05 | W68: Paquete | X68: =((D72/1000)*(E72/1000))*G72
A69: COMPARATIVA | B69: 73 | C69: tablero_chopo_bb_bb | D69: Tablero | E69: Chopo | F69: BB/BB | G69: 2500 | H69: 1220 | I69: 15 | J69: 20.3 | K69: 20.3 | L69: €/m2 | M69: Mausa | N69: Mausa | X69: =((D73/1000)*(E73/1000))*G73
A70: COMPARATIVA | B70: 75 | C70: tablero_osb_tablero_osb_3_xop | D70: Tablero | E70: OSB | F70: Tablero OSB 3 XOP | G70: 2500 | H70: 1250 | I70: 9 | J70: 4.16 | K70: 4.16 | L70: €/m2 | M70: Closa | N70: Closa | U70: 3.91 | V70: 3.91 | W70: Paquete
A71: COMPARATIVA | B71: 76 | C71: tablero_osb_tablero_osb_3_xop | D71: Tablero | E71: OSB | F71: Tablero OSB 3 XOP | G71: 2500 | H71: 1250 | I71: 15 | J71: 6.18 | K71: 6.18 | L71: €/m2 | M71: Closa | N71: Closa | U71: 5.82 | V71: 5.82 | W71: Paquete
A72: COMPARATIVA | B72: 77 | C72: tablero_osb_tablero_osb_3_xop | D72: Tablero | E72: OSB | F72: Tablero OSB 3 XOP | G72: 2500 | H72: 1250 | I72: 18 | J72: 7.88 | K72: 7.88 | L72: €/m2 | M72: Closa | N72: Closa | U72: 7.41 | V72: 7.41 | W72: Paquete
A73: COMPARATIVA | B73: 78 | C73: tablero_osb_tablero_osb_3_xop | D73: Tablero | E73: OSB | F73: Tablero OSB 3 XOP | G73: 2500 | H73: 1250 | I73: 22 | J73: 9.86 | K73: 9.86 | L73: €/m2 | M73: Closa | N73: Closa | U73: 9.27 | V73: 9.27 | W73: Paquete
A74: COMPARATIVA | B74: 80 | C74: liston_pino_liston_flandes_45_21 | D74: Liston | E74: Pino | F74: Liston Flandes 45*21 | G74: 4500 | H74: 45 | I74: 21 | J74: 0.66 | K74: 0.66 | L74: €/ml | M74: Forestal Vic | N74: Forestal Vic
A75: COMPARATIVA | B75: 81 | C75: liston_pino_liston_flandes_45_21 | D75: Liston | E75: Pino | F75: Liston Flandes 45*21 | G75: 4500 | H75: 45 | I75: 21 | J75: 0.73 | K75: 0.73 | L75: €/ml | M75: Albaertch | N75: Albaertch
A76: COMPARATIVA | B76: 82 | C76: liston_pino_liston_flandes_45_21 | D76: Liston | E76: Pino | F76: Liston Flandes 45*21 | G76: 4500 | H76: 45 | I76: 21 | J76: 0.9 | K76: 0.9 | L76: €/ml | M76: Mausa | N76: Mausa
A77: COMPARATIVA | B77: 83 | C77: liston_pino_liston_flandes_45_20 | D77: Liston | E77: Pino | F77: Liston Flandes 45*20 | G77: 4500 | H77: 45 | I77: 20 | J77: 1.02 | K77: 1.02 | L77: €/ml | M77: Closa | N77: Closa | U77: 0.97 | V77: 0.97 | W77: Paquete
A78: COMPARATIVA | B78: 84 | C78: liston_pino_liston_flandes_45_45 | D78: Liston | E78: Pino | F78: Liston Flandes 45*45 | G78: 4500 | H78: 45 | I78: 45 | J78: 1.33 | K78: 1.33 | L78: €/ml | M78: Forestal Vic | N78: Forestal Vic
A79: COMPARATIVA | B79: 85 | C79: liston_pino_liston_flandes_45_45_son_de_12mts_les_podem_vendre_a_3000_4000_5000_6000_70000 | D79: Liston | E79: Pino | F79: Liston Flandes 45*45 (SON DE 12MTS, LES PODEM VENDRE A 3000,4000,5000,6000,70000) | G79: 4500 | H79: 45 | I79: 45 | J79: 1.1 | K79: 1.1 | L79: €/ml | M79: Albaertch | N79: Albaertch
A80: COMPARATIVA | B80: 86 | C80: liston_pino_liston_flandes_45_45 | D80: Liston | E80: Pino | F80: Liston Flandes 45*45 | G80: 4500 | H80: 45 | I80: 45 | J80: 1.67 | K80: 1.67 | L80: €/ml | M80: Closa | N80: Closa | U80: 1.67 | V80: 1.67 | W80: Paquete
A81: COMPARATIVA | B81: 87 | C81: liston_pino_liston_flandes_45_70 | D81: Liston | E81: Pino | F81: Liston Flandes 45*70 | G81: 4500 | H81: 45 | I81: 70 | J81: 1.99 | K81: 1.99 | L81: €/ml | M81: Forestal Vic | N81: Forestal Vic
A82: COMPARATIVA | B82: 88 | C82: liston_pino_liston_flandes_45_70_son_de_12mts_les_podem_vendre_a_3000_4000_5000_6000_70000 | D82: Liston | E82: Pino | F82: Liston Flandes 45*70 (SON DE 12MTS, LES PODEM VENDRE A 3000,4000,5000,6000,70000) | G82: 4500 | H82: 45 | I82: 70 | J82: 1.45 | K82: 1.45 | L82: €/ml | M82: Albaertch | N82: Albaertch
A83: COMPARATIVA | B83: 89 | C83: liston_pino_liston_flandes_45_70 | D83: Liston | E83: Pino | F83: Liston Flandes 45*70 | G83: 4500 | H83: 45 | I83: 70 | J83: 2.37 | K83: 2.37 | L83: €/ml | M83: Closa | N83: Closa | U83: 2.25 | V83: 2.25 | W83: Paquete
A84: COMPARATIVA | B84: 90 | C84: liston_pino_liston_flandes_20_90 | D84: Liston | E84: Pino | F84: Liston Flandes 20*90 | G84: 4200 | H84: 20 | I84: 90 | J84: 1.95 | K84: 1.95 | L84: €/ml | M84: Forestal Vic | N84: Forestal Vic
A85: COMPARATIVA | B85: 91 | C85: liston_pino_liston_flandes_22_96 | D85: Liston | E85: Pino | F85: Liston Flandes 22*96 | G85: 3900 | H85: 22 | I85: 96 | J85: 1.45 | K85: 1.45 | L85: €/ml | M85: Albertch | N85: Albertch
A86: COMPARATIVA | B86: 92 | C86: liston_aveto_biga_laminada_avet_gl24h | D86: Liston | E86: Aveto | F86: Biga laminada avet GL24H | G86: 6500 | H86: 120 | I86: 60 | J86: 5.84 | K86: 5.84 | L86: €/ml | M86: Forestal Vic | N86: Forestal Vic
A87: COMPARATIVA | B87: 93 | C87: liston_aveto_biga_laminada_avet_gl24h_son_de_12mts_les_podem_vendre_a_3000_4000_5000_6000_70000 | D87: Liston | E87: Aveto | F87: Biga laminada avet GL24H (SON DE 12MTS, LES PODEM VENDRE A 3000,4000,5000,6000,70000) | G87: 6500 | H87: 120 | I87: 60 | J87: 4.92 | K87: 4.92 | L87: €/ml | M87: Albaertch | N87: Albaertch
A88: COMPARATIVA | B88: 94 | C88: liston_aveto_biga_laminada_avet_120_120 | D88: Liston | E88: Aveto | F88: Biga laminada avet 120*120 | G88: 6500 | H88: 120 | I88: 120 | J88: 12 | K88: 12 | L88: €/ml | M88: Forestal Vic | N88: Forestal Vic
A89: COMPARATIVA | B89: 96 | C89: canto_haya_canto_xapa_22_0_8_mm_haya_natural_es_natural | D89: Canto | E89: Haya | F89: Canto xapa 22*0,8 mm Haya Natural (Es natural??) | H89: 22 | I89: 5 | J89: 0.42 | K89: 0.42 | L89: €/ml | M89: Closa | N89: Closa
A90: COMPARATIVA | B90: 97 | C90: canto_haya_canto_xapa_22_5mm_haya_natural | D90: Canto | E90: Haya | F90: Canto xapa 22*5mm Haya Natural | H90: 22 | I90: 5 | J90: 0.35 | K90: 0.35 | L90: €/ml | M90: M&M Cantos | N90: M&M Cantos
A91: COMPARATIVA | B91: 98 | C91: canto_negro_cantell_negre_22_x_0_8 | D91: Canto | E91: Negro | F91: CANTELL NEGRE 22 X 0,8 | H91: 22 | I91: 0.8 | J91: 0.38 | K91: 0.38 | L91: €/ml | M91: Closa | N91: Closa
A92: COMPARATIVA | B92: 99 | C92: canto_negro_canto_abs_negro_u_190_23_0_8 | D92: Canto | E92: Negro | F92: Canto ABS Negro U-190 23*0,8 | H92: 23 | I92: 0.8 | J92: 0.68 | K92: 0.68 | L92: €/ml | M92: Mausa | N92: Mausa
A93: COMPARATIVA | B93: 100 | C93: canto_blanco_cantell_blanco_22_x_0_8 | D93: Canto | E93: Blanco | F93: CANTELL Blanco 22 X 0,8 | H93: 22 | I93: 0.8 | J93: 0.18 | K93: 0.18 | L93: €/ml | M93: Closa | N93: Closa
A94: COMPARATIVA | B94: 101 | C94: canto_velvet_oak_canto_velvet_oak | D94: Canto | E94: Velvet Oak | F94: Canto Velvet Oak | H94: 22 | I94: 0.8 | J94: 0.35217 | K94: =35.217/100 | L94: €/ml | M94: M&M Cantos | N94: M&M Cantos
A95: COMPARATIVA | B95: 102 | C95: canto_niagara_oak_canto_niagara_oak | D95: Canto | E95: Niagara Oak | F95: Canto Niagara Oak | H95: 22 | I95: 0.8 | J95: 0.35217 | K95: =35.217/100 | L95: €/ml | M95: M&M Cantos | N95: M&M Cantos
A96: COMPARATIVA | B96: 103 | C96: canto_papaya_canto_papaya | D96: Canto | E96: Papaya | F96: Canto Papaya | H96: 22 | I96: 0.8 | J96: 0.35217 | K96: =35.217/100 | L96: €/ml | M96: M&M Cantos | N96: M&M Cantos
A97: COMPARATIVA | B97: 105 | C97: perfil_aluminio_negro_perfil_40_20_negro_brillante | D97: Perfil | E97: Aluminio Negro | F97: Perfil 40*20 Negro Brillante | G97: 6000 | H97: 40 | I97: 20 | J97: 2.541 | K97: 2.541 | L97: €/ml | M97: Provedal | N97: Provedal
A98: COMPARATIVA | B98: 106 | C98: perfil_aluminio_blanco_perfil_40_20_blanco_brillante | D98: Perfil | E98: Aluminio Blanco | F98: Perfil 40*20 Blanco Brillante | G98: 6000 | H98: 40 | I98: 20 | J98: 2.36 | K98: 2.36 | L98: €/ml | M98: Provedal | N98: Provedal
A99: COMPARATIVA | B99: 107 | C99: pletina_aluminio_negro_pletina_20_3_negro_brillante | D99: Pletina | E99: Aluminio Negro | F99: Pletina 20*3 Negro Brillante | G99: 6000 | H99: 20 | I99: 3 | J99: 2.39 | K99: 2.39 | L99: €/ml | M99: Provedal | N99: Provedal
A100: COMPARATIVA | B100: 108 | C100: perfil_textil_para_textiles_silicona | D100: Perfil | E100: Textil | F100: Para Textiles Silicona | J100: 5 | K100: 5 | L100: €/ml | M100: ? | N100: ?
...

Sheet CALCULADORA_FLAT
A1: CALCULADORA NORMALIZADA
A2: block | B2: source_row | C2: col_a | D2: col_b | E2: col_c | F2: col_d | G2: col_e
A3: CALCULAR €/m2 DE TABLERO | B3: 2 | C3: Largo m | D3: Ancho m | E3: m2 | F3: € Tablero | G3: €/m2
A4: CALCULAR €/m2 DE TABLERO | B4: 3 | C4: 2.8 | D4: 2.07 | E4: 5.796 | F4: 106.2 | G4: 18.322981
A5: CALCULAR €/m2 DE CORTE | B5: 6 | C5: Tableros | D5: Largo m | E5: Ancho m | F5: m2 | G5: m2 TOT
A6: CALCULAR €/m2 DE CORTE | B6: 7 | C6: 8 | D6: 2.44 | E6: 1.22 | F6: 2.9768 | G6: 23.8144
A7: CALCULAR € TABLERO | B7: 10 | C7: Largo m | D7: Ancho m | E7: m2 | F7: € Tablero | G7: €/m2
A8: CALCULAR € TABLERO | B8: 11 | C8: 2.8 | D8: 2.07 | E8: 5.796 | F8: 29.38572 | G8: 5.07
